Workbook

Sheet Försättsblad
A4: Dokument/Listor | B4: Beskrivning
A5: Beställningar - huvudfil | B5: Orderfilen med alla beställningar
A6: Lager "På vift" | B6: Dragkrokar mm. som finns "i lager" men inte i Borås - än.. Här ska alla krokar som är extra eller blir över föras in. När någon vara tas härifrån, ska den markeras röd samt skrivas i kolumn P till vilken bil den tas. När en vara legat röd ett tag, sätt ett "x" i kolumn O. Om dragkrokar tas hem till Borås, markera hela raden i gult och skriv i kolumn S.
A7: Lager Borås | B7: Administration lagret i Borås
A8: Prislista dragkrokar | B8: Prislista för dragkrokar. Westfalia, Witter, Steinhof och Imiola finns i huvudfliken. Övriga går att hitta i separat blad i filen.
A9: Prislista ECS | B9: Prislista på elsatser från ECS. Aktuellt lagersaldo hemma finns i kolumn J (Borås) och K ("På vift"-listan)
A10: Menabo Application list | B10: Aktuell lista från Menabo med vilka takräcken som passar vilka bilar.
A11: Order Steinhof | B11: Fil som vi lägger in alla ordrar till Steinhof. Ordrar som läggs innan kl 10.00 skickas samma dag.
A12: Order Imiola | B12: Fil som vi lägger in alla ordrar till Imiola. Lägg även ett mail till Imiola (office@imiola.pl) när order lagts här i, de går inte in och kikar regelbundet som Steinhof.
A13: Order Westfalia | B13: Ordrar till Westfalia läggs i deras Webshop. Det går även att beställa via mail till ea-dk-sales@horizonglobal.com eller telefon ‭0220-225 41‬
A14: Order Martec | B14: Ordrar på Autohak eller Brink görs per mail till Martec, export@martec.pl. Martec lägger sedan in ordrarna i denna fil.
A15: Order Umbra Rimorchi | B15: Ordrar på Umbra läggs i detta dokumentet. Skicka ett mail till export@umbrarimorchi.it när order lagts. De kikar inte jämnt i denna listan.
... A22: Bibeln | B22: Bibeln med frågor och svar samt lite policy som vi samlat på oss genom åren.
A25: Google Drive
A26: Delade dokument och bra att ha | B26: Finns i Google drive länkat
A28: Statistik
A29: Försäljning Statistik
A33: Dokument
A34: Marknadsföring: Leverantörer | B34: Texter och beskrivningar om våra leverantörer
A35: Produktblad Monteringspartner | B35: Produktblad monteringspartners, hur vi jobbar och fördelningar mm

Sheet Lager
M1: SKA TILL: | AB1: 1€= | AC1: 11.6
A2: Antal | B2: Typ | C2: Fabrikat | D2: Artikelnummer | E2: Typ | F2: Bil | G2: Årsmodell | H2: Var? | I2: Tillhörde / Ursprung Reg.nr | J2: Övrigt / Orsak / Skick | K2: EAN Codes | L2: I lagret 181212 | M2: Ligga kvar | N2: Borås | O2: Kontoret | P2: Leverantör | Q2: Kund / Verkstad | R2: Bokat upphämtning? | S2: KLART ? | T2: Tagen till Reg.nr / Ordernummer | U2: Göm / KLAR ? | V2: Övrigt | W2: Mått på paketet | X2: Övrigt 2 | Y2: Ta upp som lager 2018 | Z2: På lager 2023-12-31 | AA2: Inventering 2024-11-30 | AC2: Inköpspris | AD2: Till prislistan | AE2: Till prislistan
A3: 25 med reg nr nfr489. | B3: Elsatser | C3: STARC | E3: 7-polig | H3: Lager | K3: =IFNA(VLOOKUP(D3,'EAN Codes'!A:C,2,False),"") | U3: TRUE | Z3: FALSE
A4: 70 | B4: Dragkrokar | C4: Blandat | E4: S-kulor | F4: 2 st silver 1 guld. 2 bultade | H4: Kontoret | K4: =IFNA(VLOOKUP(D4,'EAN Codes'!A:C,2,False),"") | U4: TRUE | V4: Tagit en silver 5/9 -17 //TC | Z4: FALSE
A5: 15 | B5: Dragkrokar | D5: ZK-2 | F5: Adapterkula | H5: Lager | K5: =IFNA(VLOOKUP(D5,'EAN Codes'!A:C,2,False),"") | U5: TRUE | Z5: FALSE
A6: 971 | B6: Dragkrokar | C6: Steinhof | D6: A-037 | E6: Fast | F6: ALFA ROMEO 159 Sedan 2005> ALFA ROMEO 159 Kombi 2006> | G6: 2005> | H6: Linköping Speedy | K6: =IFNA(VLOOKUP(D6,'EAN Codes'!A:C,2,False),"") -> 5907615800986 | U6: TRUE | V6: Foaad klarade inte att montera den på OTH308. Ta hem krok. Skickad till HNE833 | Z6: FALSE
B7: Dragkrokar | C7: Steinhof | D7: A-042 | E7: AV | F7: ALFA ROMEO Giulietta Halvkombi 2010> | G7: 2010> | H7: Umeå | K7: =IFNA(VLOOKUP(D7,'EAN Codes'!A:C,2,False),"") -> 5907615801037 | U7: TRUE | V7: Tillhörde MXK761 som avbokat. Vänta ev med att ta hem detta draget. Se om kund bokar på. | Z7: FALSE
A8: 711 | B8: Motorvärmare | C8: DEFA | D8: 440052 | E8: Bluetooth Kit | F8: Alla bilar. Bluetooth Upgrade Kit | H8: Lager | I8: E2 | K8: =IFNA(VLOOKUP(D8,'EAN Codes'!A:C,2,False),"") | U8: TRUE | Z8: FALSE
A9: 878 | B9: Dragkrokar | C9: Westfalia | D9: 317114600001 | E9: Avtagbar | F9: Audi A1 2010> | H9: Lager | I9: D1 | K9: =IFNA(VLOOKUP(D9,'EAN Codes'!A:C,2,False),"") | U9: TRUE | Z9: FALSE
A10: 600 | B10: Dragkrokar | C10: Westfalia | D10: 317131 | E10: Fast | F10: Audi A3 , VW Golf , Seat Leon, Skoda | G10: 2012> | H10: Lager | I10: Kök | K10: =IFNA(VLOOKUP(D10,'EAN Codes'!A:C,2,False),"") | L10: Ja | U10: TRUE | V10: Till bil POW788 | Y10: x | Z10: FALSE
A11: 408 | B11: Dragkrokar | C11: Kovil | D11: 10023 | E11: fixed | F11: Audi A3 (8PA) 5D-Sportback 2WD | G11: 2004-9/2012 | H11: Lager | I11: B2 | K11: =IFNA(VLOOKUP(D11,'EAN Codes'!A:C,2,False),"") | L11: Ja | U11: TRUE | V11: GOK540 | Y11: x | Z11: FALSE
A12: 898 | B12: Dragkrokar | C12: Westfalia | D12: 321885 | E12: AV | F12: AUDI A3 04>13 3d Cab 2008> ej sportback VW Golf 5 , 5+ , 6 , 6+ , GTI , Cross | G12: 2005-2011 2011> | H12: Lager | I12: Stora rummet | K12: =IFNA(VLOOKUP(D12,'EAN Codes'!A:C,2,False),"") | U12: TRUE | Z12: FALSE
A13: 729 | B13: Bagagematta | C13: GJK | D13: 102030 | F13: Audi A3 2012 3-dörr | G13: 12> | H13: Lager | I13: A4 | K13: =IFNA(VLOOKUP(D13,'EAN Codes'!A:C,2,False),"") | U13: TRUE | Z13: FALSE
A14: 105 | C14: Westfalia | D14: 305299 | E14: Fast | F14: Audi A3 Sportback | G14: 2004>2013 | H14: Lagret | I14: B2 | K14: =IFNA(VLOOKUP(D14,'EAN Codes'!A:C,2,False),"") | U14: TRUE | Z14: FALSE
A15: 3 | C15: Westfalia | D15: 317132 | E15: AV | F15: Audi A3 Sportback | G15: 2012> | H15: Kontoret | I15: C3 | K15: =IFNA(VLOOKUP(D15,'EAN Codes'!A:C,2,False),"") | U15: TRUE | V15: Eklunds Bil 14/2 | Z15: FALSE
A16: 596 | B16: Dragkrokar | C16: Westfalia | D16: 305299 | E16: Fast | F16: Audi A3 Sportback | G16: 04>13 | H16: Lager | I16: TC | K16: =IFNA(VLOOKUP(D16,'EAN Codes'!A:C,2,False),"") | L16: Ja | U16: TRUE | V16: Tagen till KSX869 | Y16: x | Z16: FALSE
A17: 193 | C17: Steinhof | D17: V-063 | E17: Avtagbar | F17: Audi A3 Sportback | G17: 13> | H17: Lager | I17: A1 | K17: =IFNA(VLOOKUP(D17,'EAN Codes'!A:C,2,False),"") -> 5907615826146 | U17: TRUE | Z17: FALSE
A18: 192 | B18: Dragkrokar | C18: Steinhof | D18: A-067 | E18: Avtagbar | F18: Audi A3 Sportback | G18: 2004>2013 | H18: Lager | I18: A3 | K18: =IFNA(VLOOKUP(D18,'EAN Codes'!A:C,2,False),"") -> 5907615800573 | U18: TRUE | Z18: FALSE
A19: 459 | B19: Dragkrokar | C19: Westfalia | D19: 305299 | E19: Fast | F19: Audi A3 Sportback (8PA | G19: 2004>2013 | H19: Lager | I19: TC Kontor | K19: =IFNA(VLOOKUP(D19,'EAN Codes'!A:C,2,False),"") | L19: Ja | U19: TRUE | V19: KER358 | Y19: x | Z19: FALSE
A20: 450 | B20: Dragkrokar | C20: Westfalia | D20: 305299 | E20: Fast | F20: Audi A3 Sportback (8PA) | G20: 2004>2013 | H20: Lager | I20: B3 | K20: =IFNA(VLOOKUP(D20,'EAN Codes'!A:C,2,False),"") | L20: Ja | U20: TRUE | V20: MRS451 | Y20: x | Z20: FALSE
A21: 72 | C21: Westfalia | D21: 317132 | E21: Avtagbar | F21: Audi A3 Sportback / Sedan / Golf 7 / Golf Sportswan / Seat Leon Halvkombi / kombi / Skoda Octavia kombi / Halvkombi | G21: 12> | H21: Kontoret | I21: C3 | K21: =IFNA(VLOOKUP(D21,'EAN Codes'!A:C,2,False),"") | U21: TRUE | Z21: FALSE
A22: 571 | B22: Dragkrokar | C22: Westfalia | D22: 321885 | E22: AV | F22: Audi A3 Vw GOLF V | G22: 2003>2013 | H22: Lager | I22: TC | K22: =IFNA(VLOOKUP(D22,'EAN Codes'!A:C,2,False),"") | L22: Ja | U22: TRUE | Y22: x | Z22: FALSE
A23: 928 | B23: Dragkrokar | C23: Westfalia | D23: 317132 | E23: AV | F23: Audi A3, Audi Q2, Skoda Octavia, Seat Leon, VW Golf, VW T-Roc M FL | G23: 2012> | H23: Lager | I23: B1 | K23: =IFNA(VLOOKUP(D23,'EAN Codes'!A:C,2,False),"") | U23: TRUE | V23: OJG369 | Z23: FALSE
A24: 555 | B24: Dragkrokar | C24: Westfalia | D24: 321865 | E24: Fast | F24: Audi A3, VW Golf HB | G24: 2003>2013 | H24: Lager | I24: TC | K24: =IFNA(VLOOKUP(D24,'EAN Codes'!A:C,2,False),"") | U24: TRUE | V24: Tagen till VF97777 | Z24: FALSE
A25: 592 | B25: Dragkrokar | C25: Westfalia | D25: 321865 | E25: Fast | F25: Audi A3, VW Golf HB | G25: 03>13 | H25: Lager | I25: TC Kontor | K25: =IFNA(VLOOKUP(D25,'EAN Codes'!A:C,2,False),"") | L25: Ja | U25: TRUE | V25: KTZ082 | Y25: x | Z25: FALSE
B26: Dragkrokar | C26: Elsats | D26: Westfalia 305406300107 | E26: 7-pol | F26: Audi A3, VW Golf, Seat Leon, Skoda Octavia - passar många | G26: 2012> | H26: Lager | K26: =IFNA(VLOOKUP(D26,'EAN Codes'!A:C,2,False),"") | U26: TRUE | V26: Finns hos Halléns | Z26: FALSE
A27: 448 | B27: Dragkrokar | C27: Westfalia | D27: 305447 | E27: Avtagbar | F27: Audi A4 | G27: 2015> | H27: Lager | I27: B3 | K27: =IFNA(VLOOKUP(D27,'EAN Codes'!A:C,2,False),"") | L27: Ja | U27: TRUE | Y27: x | Z27: FALSE
A28: 869 | B28: Dragkrokar | C28: Witter | D28: AD44AQ | E28: Avtagbar | F28: Audi A4 | G28: 2005>2008 | H28: Äpplekullen | K28: =IFNA(VLOOKUP(D28,'EAN Codes'!A:C,2,False),"") -> 5060128530082 | U28: TRUE | V28: Tillhörde Xwe033 som avbokat monteringen. | Z28: FALSE
A29: 458 | B29: Dragkrokar | C29: Westfalia | D29: 305301 | E29: Fast | F29: Audi A4 | G29: 43198 | H29: Lager | I29: B3 | K29: =IFNA(VLOOKUP(D29,'EAN Codes'!A:C,2,False),"") | L29: Ja | U29: TRUE | V29: tagen till XUS797 | Y29: x | Z29: FALSE
A30: 527 | B30: Dragkrokar | C30: Steinhof | D30: A-053 | E30: Fast | F30: Audi A4 , Allroad, sedan m fl | G30: 2016> | H30: Lager | I30: C3 | K30: =IFNA(VLOOKUP(D30,'EAN Codes'!A:C,2,False),"") -> 5907615800450 | L30: Ja | U30: TRUE | V30: PJP624 | Y30: x | Z30: FALSE
A31: 389 | B31: Dragkrokar | C31: Kovil | D31: 10024 | E31: fixed | F31: Audi A4 (8K/B8) SDN/AVANT '08- | G31: 2008- | H31: Lager | I31: E1 | K31: =IFNA(VLOOKUP(D31,'EAN Codes'!A:C,2,False),"") | U31: TRUE | V31: NPL779 | Z31: FALSE
A32: 390 | B32: Dragkrokar | C32: Kovil | D32: 10024 | E32: fixed | F32: Audi A4 (8K/B8) SDN/AVANT '08- | G32: 2008- | H32: Lager | I32: E1 | K32: =IFNA(VLOOKUP(D32,'EAN Codes'!A:C,2,False),"") | U32: TRUE | V32: Till LWO919 | Z32: FALSE
A33: 412 | B33: Dragkrokar | C33: witter | D33: AD55Q | E33: Vertical | F33: AUDI A4 (B9) Sdn/Avant 2016- | G33: 2016- | H33: Lager | I33: D1 | K33: =IFNA(VLOOKUP(D33,'EAN Codes'!A:C,2,False),"") -> 5060128530259 | L33: Ja | U33: TRUE | V33: YTP188 | Y33: x | Z33: FALSE
A34: 554 | B34: Dragkrokar | C34: Westfalia | D34: 305301 | E34: Fast | F34: Audi A4 (kaross B7) | G34: 2004>2008 | H34: Lager | I34: TC | K34: =IFNA(VLOOKUP(D34,'EAN Codes'!A:C,2,False),"") | L34: Ja | U34: TRUE | V34: tagen till AEB410 | Y34: x | Z34: FALSE
A35: 607 | B35: Dragkrokar | C35: Westfalia | D35: 305445 | E35: AV | F35: Audi A4 / A5 | G35: 2007>2016 | H35: Lager | I35: HL kontor | K35: =IFNA(VLOOKUP(D35,'EAN Codes'!A:C,2,False),"") | U35: TRUE | Z35: FALSE
A36: 611 | B36: Dragkrokar | C36: Westfalia | D36: 305445 | E36: AV | F36: Audi A4 / A5 | G36: 2007>2016 | H36: Lager | I36: HL kontor | K36: =IFNA(VLOOKUP(D36,'EAN Codes'!A:C,2,False),"") | U36: TRUE | Z36: FALSE
A37: 161 | C37: Steinhof | D37: A-074 | E37: Fast | F37: Audi A4 A5 | G37: 07> | H37: Lager | I37: D2 | K37: =IFNA(VLOOKUP(D37,'EAN Codes'!A:C,2,False),"") -> 5907615800641 | U37: TRUE | Z37: FALSE
A38: 473 | B38: Dragkrokar | C38: Westfalia | D38: 305443 | E38: Fast | F38: Audi A4 Avant / Audi A5 | G38: 2007>2015 | H38: Lager | I38: TC Kontor | K38: =IFNA(VLOOKUP(D38,'EAN Codes'!A:C,2,False),"") | L38: Nej | U38: TRUE | Z38: FALSE
B39: Dragkrokar | C39: Witter | D39: AD48BQ | E39: AV | F39: Audi A4 B8 Sedan, estate 6.2008-.2015 | G39: 2008-.2015 | H39: Antingen här eller i Tyresö eller tagen?? | K39: =IFNA(VLOOKUP(D39,'EAN Codes'!A:C,2,False),"") | U39: TRUE | V39: Tillhörde LYK081 | Z39: FALSE
A40: 99 | B40: Dragkrokar | C40: Steinhof | D40: A-075 | E40: Avtagbar | F40: Audi A4 kombi | G40: 07> | H40: Lagret | I40: D1 | K40: =IFNA(VLOOKUP(D40,'EAN Codes'!A:C,2,False),"") -> 5907615800658 | U40: TRUE | Z40: FALSE
A41: 170 | C41: Steinhof | D41: A-074 | E41: Fast | F41: Audi A4 kombi | G41: 08> | H41: Lager | I41: D2 | K41: =IFNA(VLOOKUP(D41,'EAN Codes'!A:C,2,False),"") -> 5907615800641 | U41: TRUE | Z41: FALSE
B42: Bagagematta | C42: GJK | D42: Standard | F42: Audi A4 Kombi | G42: 2008>2015 | H42: Lager | I42: TC | K42: =IFNA(VLOOKUP(D42,'EAN Codes'!A:C,2,False),"") | U42: TRUE | Z42: FALSE
A43: 1014 | B43: Dragkrokar | C43: Steinhof | D43: A-074 | E43: Fast | F43: AUDI A4 Kombi 2008-2016 AUDI A4 Sedan 2008-2016 | G43: 2008-2016 | H43: Lager | I43: E1 | K43: =IFNA(VLOOKUP(D43,'EAN Codes'!A:C,2,False),"") -> 5907615800641 | U43: TRUE | V43: Tillhörde SYX800, passade inte bilen. | Z43: FALSE
A44: 1007 | B44: Dragkrokar | C44: Autohak | D44: A23 | E44: Fast | F44: AUDI A4 Kombi 2008>2016 AUDI A4 Sedan 2007>2016 AUDI A5 2007>2015 | G44: 2008>2016 | H44: Järfälla | K44: =IFNA(VLOOKUP(D44,'EAN Codes'!A:C,2,False),"") -> 01145 | U44: TRUE | V44: Beställt dubbelt till JNP012 // Tagen från Järfälla till MTD099 | Z44: FALSE
A45: 950 | B45: Dragkrokar | C45: Umbra | D45: 02028/C | E45: Avtagbar | F45: AUDI A4 Kombi 2008>2016 AUDI A4 Sedan 2007>2016 AUDI A5 2007>2015 AUDI A5 Cab 2009> | G45: 2008>2015 | H45: Lager | I45: D1 | K45: =IFNA(VLOOKUP(D45,'EAN Codes'!A:C,2,False),"") -> 8058772226670 | U45: TRUE | V45: Tillhörde förmodligen CNK069. SKICKAS TILL GCH094 | Z45: FALSE
A46: 195 | B46: Dragkrokar | C46: Steinhof | D46: A-075 | E46: Avtagbar | F46: Audi A4 kombi- sedan A5 Coupe | G46: 07> | H46: Lager | I46: B1 | K46: =IFNA(VLOOKUP(D46,'EAN Codes'!A:C,2,False),"") -> 5907615800658 | U46: TRUE | V46: Tagen till order RMR295 22/1 | Z46: FALSE
A47: 349 | B47: Dragkrokar | C47: Steinhof | D47: A-074 | E47: Fast | F47: Audi A4 sedan | G47: 07>16 | H47: Lager | I47: A2 | K47: =IFNA(VLOOKUP(D47,'EAN Codes'!A:C,2,False),"") -> 5907615800641 | U47: TRUE | V47: Tagen till Ola, MRB908 | Z47: FALSE
A48: 990 | B48: Dragkrokar | C48: Umbra | D48: 02028/VM | E48: AV | F48: AUDI A4 Sedan 2007>2016 AUDI A4 Kombi 2008>2016 AUDI A5 2007>2015 | G48: 2007>2015 | H48: Lager | I48: B3 | K48: =IFNA(VLOOKUP(D48,'EAN Codes'!A:C,2,False),"") -> 8058772226687 | U48: TRUE | V48: Tillhörde LYK081, nu inköpt av TNN488. TNN488 lämnade tillbaka draget strax efter att han hämtat det. //TC 6/4. Nu skickat till LMD135. 19/8 FP | Z48: FALSE
A49: 850 | B49: Dragkrokar | C49: Umbra | D49: 02028/C | E49: AH | F49: Audi A4 sedan och kombi Audi A5 coupe och sportback | G49: 2007> | H49: Äpplekullen | K49: =IFNA(VLOOKUP(D49,'EAN Codes'!A:C,2,False),"") -> 8058772226670 | U49: TRUE | V49: CNK069 som bytte till Westfalia istället. Kommit hit, se ny rad. | Z49: FALSE
A50: 585 | B50: Dragkrokar | C50: Westfalia | D50: 305445 | E50: AV | F50: Audi A4, A5 | G50: 2007> | H50: Lager | I50: Kök | K50: =IFNA(VLOOKUP(D50,'EAN Codes'!A:C,2,False),"") | U50: TRUE | V50: Till bil MDX016 | Y50: x | Z50: FALSE
A51: 709 | B51: Elsatser | C51: Erich Jaeger | D51: 736921 | E51: 7-pol | F51: Audi A4, A5 4d, kombi, Coupe, Sportback | G51: 2007>2017 | H51: Lager | K51: =IFNA(VLOOKUP(D51,'EAN Codes'!A:C,2,False),"") | U51: TRUE | V51: GGY323 | Z51: FALSE
A52: 566 | B52: Dragkrokar | C52: Westfalia | D52: 305443 | E52: Fast | F52: Audi A4, Audi A5 alla | G52: 2007>2017 | H52: Lager | I52: TC | K52: =IFNA(VLOOKUP(D52,'EAN Codes'!A:C,2,False),"") | L52: Nej | U52: TRUE | V52: Tagen till PYN261 | Z52: FALSE
A53: 561 | B53: Dragkrokar | C53: Westfalia | D53: 305443 | E53: Fast | F53: Audi A4, Audi A5 alla | G53: 2007>2017 | H53: Lager | I53: TC | K53: =IFNA(VLOOKUP(D53,'EAN Codes'!A:C,2,False),"") | U53: TRUE | V53: Tagen till Mrz262 | Z53: FALSE
A54: 567 | B54: Dragkrokar | C54: Westfalia | D54: 305443 | E54: Fast | F54: Audi A4, Audi A5 alla | G54: 2007>2017 | H54: Lager | I54: TC | K54: =IFNA(VLOOKUP(D54,'EAN Codes'!A:C,2,False),"") | U54: TRUE | V54: Till bil NTS310 | Z54: FALSE
A55: 114 | C55: Westfalia | D55: 305274 | E55: Fast | F55: Audi A6 | G55: 2005>2011 | H55: Lagret | I55: A1 | K55: =IFNA(VLOOKUP(D55,'EAN Codes'!A:C,2,False),"") | U55: TRUE | Z55: FALSE
A56: 100 | C56: Steinhof | D56: A-088 | F56: AUDI A6 | G56: 2005> | H56: Lagret | I56: D2 | K56: =IFNA(VLOOKUP(D56,'EAN Codes'!A:C,2,False),"") -> 5907615800788 | U56: TRUE | Z56: FALSE
A57: 451 | B57: Dragkrokar | C57: Westfalia | D57: 305429 | E57: Avtagbar | F57: Audi A6 | G57: 2011> | H57: Lager | I57: B3 | K57: =IFNA(VLOOKUP(D57,'EAN Codes'!A:C,2,False),"") | L57: Ja | U57: TRUE | V57: JMJ052 | Y57: x | Z57: FALSE
A58: 449 | B58: Dragkrokar | C58: Westfalia | D58: 305429 | E58: Avtagbar | F58: Audi A6 | G58: 2011> | H58: Lager | I58: C2 | K58: =IFNA(VLOOKUP(D58,'EAN Codes'!A:C,2,False),"") | L58: Ja | U58: TRUE | V58: Tagen till BWE757 | Y58: x | Z58: FALSE
A59: 695 | B59: Dragkrokar | C59: Steinhof | D59: A-089/1 | E59: Avtagbar | F59: Audi A6 | G59: 2005>2011 | H59: Lager | I59: D1 | K59: =IFNA(VLOOKUP(D59,'EAN Codes'!A:C,2,False),"") -> 5907615800801 | L59: Ja | U59: TRUE | V59: Tillhörde Aukea. Tagen till LWF694 | Y59: x | Z59: FALSE
A60: 453 | B60: Dragkrokar | C60: Westfalia | D60: 305429 | E60: Avtagbar | F60: Audi A6 | G60: 2011> | H60: Lager | I60: E1 | K60: =IFNA(VLOOKUP(D60,'EAN Codes'!A:C,2,False),"") | L60: Nej | U60: TRUE | V60: JSD78L | Z60: FALSE
A61: 407 | B61: Dragkrokar | C61: witter | D61: AD43AS | E61: fixed | F61: Audi A6 (C6/4F) SDN & Avant | G61: 2004-2/2011 | H61: Lager | I61: A1 | K61: =IFNA(VLOOKUP(D61,'EAN Codes'!A:C,2,False),"") -> 5060128530068 | U61: TRUE | V61: Vallåkra 9/5 | Z61: FALSE
A62: 413 | B62: Dragkrokar | C62: witter | D62: AD51Q | E62: Vertical | F62: Audi A6 (C7/4G) SDN&AVANT 03/11- | G62: 03/2011- | H62: Lager | I62: B2 | K62: =IFNA(VLOOKUP(D62,'EAN Codes'!A:C,2,False),"") -> 5060128530181 | U62: TRUE | V62: tagen till FPs polare WLK924. | Z62: FALSE
A63: 388 | B63: Dragkrokar | C63: Kovil | D63: 10125LA | E63: Vertical | F63: Audi A6 (C7/4G) SDN&AVANT 03/11- | G63: 03/2011- | H63: Lager | I63: E1 | K63: =IFNA(VLOOKUP(D63,'EAN Codes'!A:C,2,False),"") | U63: TRUE | V63: Tagen till NAR983 | Z63: FALSE
A64: 219 | C64: Steinhof | D64: A-098 | E64: Fast | F64: Audi A6 / A7 | G64: 2011> | H64: Lager | I64: C3 | K64: =IFNA(VLOOKUP(D64,'EAN Codes'!A:C,2,False),"") -> 5907615800887 | U64: TRUE | Z64: FALSE
A65: 108 | C65: Westfalia | D65: 305429 | E65: Avtagbar | F65: Audi A6 / A7 Quattro S-line | G65: 2011> | H65: Lagret | I65: C3 | K65: =IFNA(VLOOKUP(D65,'EAN Codes'!A:C,2,False),"") | U65: TRUE | V65: Hittar ej detta draget. Ligger inte på sin plats. //TC 11/4 -17 | Z65: FALSE
A66: 569 | B66: Dragkrokar | C66: Westfalia | D66: 305428 | E66: Fast | F66: Audi A6 A7 | G66: 2011> | H66: Lager | I66: TC | K66: =IFNA(VLOOKUP(D66,'EAN Codes'!A:C,2,False),"") | L66: Ja | U66: TRUE | V66: yfk524 | Y66: x | Z66: FALSE
A67: 23 | B67: Dragkrokar | C67: Autohak | D67: A 28V | E67: AV | F67: Audi A6 Allroad | G67: 2006>2012 | H67: Lager | I67: A3 | K67: =IFNA(VLOOKUP(D67,'EAN Codes'!A:C,2,False),"") | U67: TRUE | V67: Finns kula på annat ställe. | W67: Tagen till Fhn614 | Z67: FALSE
A68: 471 | B68: Dragkrokar | C68: Westfalia | D68: 305428 | E68: Fast | F68: Audi A6 Avant | G68: 2011> | H68: Lager | I68: TC Kontor | K68: =IFNA(VLOOKUP(D68,'EAN Codes'!A:C,2,False),"") | L68: Ja | U68: TRUE | V68: Tagen till NJX713 | Y68: x | Z68: FALSE
A69: 121 | C69: Westfalia | D69: 305428 | E69: Fast | F69: Audi A6 avant, A7 Sportback | G69: 11> | H69: Lagret | I69: B1 | K69: =IFNA(VLOOKUP(D69,'EAN Codes'!A:C,2,False),"") | U69: TRUE | Z69: FALSE
A70: 300 | B70: Dragkrokar | C70: Westfalia | D70: 305429600001 | E70: AV | F70: Audi A6 Kombi | G70: 2011> | H70: Lager | I70: B2 | K70: =IFNA(VLOOKUP(D70,'EAN Codes'!A:C,2,False),"") | U70: TRUE | V70: Kund hoppat av. Krasniqi reg nr MXJ698 | Z70: FALSE
C71: Steinhof | D71: A-098 | E71: Fast | F71: Audi A6 kombi | G71: 11> | H71: Lagret | I71: C2 | K71: =IFNA(VLOOKUP(D71,'EAN Codes'!A:C,2,False),"") -> 5907615800887 | U71: TRUE | V71: Fått denna dragkrok av Steinhof för att testa på Avant-modellen. Måste ta bilder under monteringen och skicka ner. Dragkrok avsedd till att monteras på motornavet | Z71: FALSE
A72: 153 | C72: Steinhof | D72: A-082 | E72: Fast | F72: Audi A6 kombi | G72: 1997>2005 | H72: Lager | I72: C3 | K72: =IFNA(VLOOKUP(D72,'EAN Codes'!A:C,2,False),"") -> 5907615800726 | U72: TRUE | Z72: FALSE
A73: 624 | B73: Dragkrokar | C73: Westfalia | D73: 305274 | E73: Fast | F73: Audi A6 kombi | G73: 2005>2011 | H73: Lager | I73: A2 | K73: =IFNA(VLOOKUP(D73,'EAN Codes'!A:C,2,False),"") | L73: Nej | U73: TRUE | V73: HPR385 | Z73: FALSE
A74: 897 | B74: Dragkrokar | C74: Witter | D74: AD51S | E74: Fast | F74: AUDI A6 kombi / sedan 2011>2015 | G74: 2011-2015 | H74: Lager | I74: Stora rummet | K74: =IFNA(VLOOKUP(D74,'EAN Codes'!A:C,2,False),"") | U74: TRUE | V74: Mud888 | Z74: FALSE
A75: 973 | B75: Dragkrokar | C75: Imiola | D75: A/012 | E75: Fast | F75: AUDI A6 KOMBI 2004>2011 | G75: 2004>2011 | H75: Lager | I75: C2 | K75: =IFNA(VLOOKUP(D75,'EAN Codes'!A:C,2,False),"") | U75: TRUE | Z75: FALSE
A76: 815 | B76: Dragkrokar | C76: Witter | D76: AD51S | E76: Fast | F76: AUDI A6 Kombi 2011> | G76: 2011> | H76: Lager | I76: E2 | K76: =IFNA(VLOOKUP(D76,'EAN Codes'!A:C,2,False),"") -> 5056150100058 | U76: TRUE | Z76: FALSE
A77: 870 | B77: Dragkrokar | C77: Witter | D77: AD56Q | E77: Avtagbar | F77: AUDI A6 Kombi 2015> AUDI A6 Sedan 2016> | G77: 2015> | H77: Lager | I77: B3 | K77: =IFNA(VLOOKUP(D77,'EAN Codes'!A:C,2,False),"") -> 5056150100126 | U77: TRUE | V77: KXZ975 | Z77: FALSE
A78: 912 | B78: Dragkrokar | C78: Umbra | D78: 02021/C | E78: AH | F78: Audi A6 kombi/sedan | G78: 1997>2005 | H78: Äpplekullen | K78: =IFNA(VLOOKUP(D78,'EAN Codes'!A:C,2,False),"") | U78: TRUE | V78: Tillhörde WDM896 som bytte till Westfalia istället. Kommit hit, se ny rad. | Z78: FALSE
A79: 948 | B79: Dragkrokar | C79: Umbra | D79: 02021/C | E79: Avtagbar | F79: AUDI A6 Sedan 1997>2004 AUDI A6 Kombi 1998>2005 | G79: 1997>2005 | H79: Lager | I79: D1 | K79: =IFNA(VLOOKUP(D79,'EAN Codes'!A:C,2,False),"") | U79: TRUE | V79: Tillhörde WDM896. Saknar handtaget. Lägg dit ett sådant Tagen till RUB171 - 15/12 FP | Z79: FALSE
A80: 823 | B80: Dragkrokar | C80: Steinhof | D80: A-098 | E80: Fast | F80: AUDI A6 Sedan 2011> (och kombi) | G80: 2011>2017 | H80: Lager | I80: C1 | K80: =IFNA(VLOOKUP(D80,'EAN Codes'!A:C,2,False),"") -> 5907615800887 | U80: TRUE | V80: Är till JV DLT550 | Z80: FALSE
A81: 226 | C81: Steinhof | D81: A-099 | E81: AV | F81: Audi A6 sedan/kombi/ A7 m fl | G81: 2011> | H81: Lager | I81: B3 | K81: =IFNA(VLOOKUP(D81,'EAN Codes'!A:C,2,False),"") -> 5907615800894 | U81: TRUE | V81: Kund hämtat här 170505 //TC | Z81: FALSE
A82: 873 | B82: Dragkrokar | C82: Westfalia | D82: 305429600001 | E82: Avtagbar | F82: Audi A6, Audi A7 | G82: 2011> | H82: Lager | I82: B2 | K82: =IFNA(VLOOKUP(D82,'EAN Codes'!A:C,2,False),"") | L82: Ja | U82: TRUE | V82: Tillhörde SRF290 som avbokades. tagen till RXH770 | Z82: FALSE
A83: 267 | B83: Dragkrokar | C83: Witter | D83: AD52AQ | E83: Avtagbar | F83: Audi Q3 | G83: 2012> | H83: Lager | I83: D2 | K83: =IFNA(VLOOKUP(D83,'EAN Codes'!A:C,2,False),"") | U83: TRUE | Z83: FALSE
A84: 410 | B84: Dragkrokar | C84: witter | D84: WAD52Q | E84: Vertical | F84: Audi Q3 2011- | G84: 2011- | H84: Lager | I84: C1 | K84: =IFNA(VLOOKUP(D84,'EAN Codes'!A:C,2,False),"") | L84: Ja | U84: TRUE | V84: Till OWP380 | Z84: FALSE
A85: 406 | B85: Dragkrokar | C85: witter | D85: WAD49AQ | E85: Vertical | F85: Audi Q5 2008- | G85: 2008- | H85: Lager | I85: C1 | K85: =IFNA(VLOOKUP(D85,'EAN Codes'!A:C,2,False),"") | U85: TRUE | V85: Tagen till Äpple, OMY541 | Z85: FALSE
B86: Elsatser | C86: Erich Jaeger | D86: 748688 | E86: 13-pol | F86: Audi Q5 2008- | G86: 2008- | H86: Lager | I86: Tagen till FNC416 | K86: =IFNA(VLOOKUP(D86,'EAN Codes'!A:C,2,False),"") | U86: TRUE | Z86: FALSE
A87: 886 | B87: Dragkrokar | C87: Steinhof | D87: A-106 | E87: Avtagbar | F87: AUDI Q5 2008> | G87: 2008> | H87: Lager | I87: E1 | K87: =IFNA(VLOOKUP(D87,'EAN Codes'!A:C,2,False),"") -> 5907615800405 | U87: TRUE | V87: Tagen till BT16856 | Z87: FALSE
A88: 901 | B88: Dragkrokar | C88: Steinhof | D88: A-106 | E88: Avtagbar | F88: AUDI Q5 2008> | G88: 2008> | H88: Lager | I88: E1 | K88: =IFNA(VLOOKUP(D88,'EAN Codes'!A:C,2,False),"") -> 5907615800405 | U88: TRUE | V88: OEP055 | Z88: FALSE
A89: 1005 | B89: Dragkrokar | C89: Steinhof | D89: A-094 | E89: Fast | F89: AUDI Q5 2008> | G89: 2008> | H89: Lager | I89: C2 | K89: =IFNA(VLOOKUP(D89,'EAN Codes'!A:C,2,False),"") -> 5907615800849 | U89: TRUE | V89: Tillhörde TRG198 som blev dubbelbeställd. tagen till HUZ220 | Z89: FALSE
A90: 707 | B90: Dragkrokar | C90: Steinhof | D90: A-106 + SMP-4pe | F90: Audi Q5, Porsche Macan | G90: 2008>2016 | H90: Vallentuna | K90: =IFNA(VLOOKUP(D90,'EAN Codes'!A:C,2,False),"") | L90: Nej | U90: TRUE | V90: Tillhörde ordern för WYY053 som avbokat. (vi kunde ändå inte ta den) | Z90: FALSE
A91: 438 | B91: Bagagematta | C91: GJK | E91: Golvmattor premium | F91: Audi Q7 | G91: 2007 | H91: Lager | I91: A4 | K91: =IFNA(VLOOKUP(D91,'EAN Codes'!A:C,2,False),"") | U91: TRUE | V91: Retur CS dubbelbeställt | Z91: FALSE
A92: 48 | C92: Bosal | D92: 029-743 | E92: AV | F92: Audi Q7, VW Touareg | G92: 2006> | H92: Lagret | I92: D3 | K92: =IFNA(VLOOKUP(D92,'EAN Codes'!A:C,2,False),"") | U92: TRUE | Z92: FALSE
A93: 601 | B93: Dragkrokar | C93: Westfalia | D93: 317131 | E93: Fast | F93: Audi, Vw ,Seat Skoda | G93: 2012> | H93: Lager | I93: Kök | K93: =IFNA(VLOOKUP(D93,'EAN Codes'!A:C,2,False),"") | U93: TRUE | V93: Tagen till WXJ041 | Z93: FALSE
A94: 573 | B94: Dragkrokar | C94: Westfalia | D94: 317131 | E94: Fast | F94: Audi, Vw ,Seat Skoda | G94: 2012> | H94: Lager | I94: TC | K94: =IFNA(VLOOKUP(D94,'EAN Codes'!A:C,2,False),"") | U94: TRUE | Z94: FALSE
A95: 712 | B95: Motorvärmare | C95: DEFA | D95: 471280 | E95: WarmUp Bluetooth | F95: Bluetooth WarmUp 1400, alla bilar | H95: Lager | I95: E2 | K95: =IFNA(VLOOKUP(D95,'EAN Codes'!A:C,2,False),"") | U95: TRUE | V95: Tagen till SKF125 | Z95: FALSE
A96: 986 | B96: Dragkrokar | C96: Witter | D96: BM44Q | E96: AV | F96: BMW | H96: Lager | I96: A1 | K96: =IFNA(VLOOKUP(D96,'EAN Codes'!A:C,2,False),"") -> 5060128530792 | U96: TRUE | V96: Tagen till NTX810 | Z96: FALSE
C97: Steinhof | D97: B-045 | E97: Fast | F97: BMW 1 och 3 | G97: 05> | H97: Lager | I97: A2 | K97: =IFNA(VLOOKUP(D97,'EAN Codes'!A:C,2,False),"") -> 5907615801198 | U97: TRUE | V97: HITTAR INTE???? | Z97: FALSE
A98: 735 | B98: Dragkrokar | C98: Steinhof | D98: B-045 | E98: Fast | F98: BMW 1 och 3 serie | H98: Lager | I98: B3 | K98: =IFNA(VLOOKUP(D98,'EAN Codes'!A:C,2,False),"") -> 5907615801198 | U98: TRUE | V98: RNU990 | Y98: x | Z98: FALSE
A99: 174 | C99: Steinhof | D99: B-046 | E99: AV | F99: BMW 1- och 3-serie | G99: 05>12 | H99: Lager | I99: A1 | K99: =IFNA(VLOOKUP(D99,'EAN Codes'!A:C,2,False),"") -> 5907615801174 | U99: TRUE | Z99: FALSE
A100: 468 | B100: Dragkrokar | C100: Westfalia | D100: 303323 | E100: AV | F100: BMW 1-serie | G100: 06>13 | H100: Lager | I100: TC Kontor | K100: =IFNA(VLOOKUP(D100,'EAN Codes'!A:C,2,False),"") | U100: TRUE | V100: Tagen till Äpplekullen CXN154 | Z100: FALSE
...

Sheet Våra Verkstäder
A1: Hur boka? | B1: Namn | C1: Lånebil | D1: Avtal | E1: Info om verkstad | F1: Kontaktperson | G1: Adress | J1: Telefonnummer | K1: E-post | M1: Org-nr | N1: Rabatt på beställningar | O1: Ansvarig hos B&J (förslag?) | P1: Skrift. Avtal? | Q1: Senast uppdaterade villkor | R1: Aktuell info, lediga tider mm? | S1: Aktiv | T1: Begränsningar | U1: Kan ta in husbilar | V1: Verkstadskontakter 3 | W1: Verkstadskontakter 4
B2: Car Care Sthlm AB | D2: 1600 kr exkl moms. (Han har fattat det som 1680 kr exkl moms) | F2: Daniel Johansson | G2: Örkroken 2 | H2: 138 40 | I2: Älta | J2: 08-41030038 | K2: info@carcare-sthlm.se | L2: =B2&" "&G2&" "&H2&" "&I2&" Telefon: "&J2 -> Car Care Sthlm AB Örkroken 2 138 40 Älta Telefon: 08-41030038 | O2: Tobias | Q2: 42614 | S2: Nej
B3: Vallentuna Däcktion AB | D3: 1600 kr exkl moms. | F3: Fredrik Faraj | G3: Moränvägen 1 | H3: 186 40 | I3: Vallentuna | J3: 070-0929723 | K3: vallentunadack@gmail.com | L3: =B3&" "&G3&" "&H3&" "&I3&" Telefon: "&J3 -> Vallentuna Däcktion AB Moränvägen 1 186 40 Vallentuna Telefon: 070-0929723 | O3: Tobias | Q3: 43070 | S3: Nej
B4: VTL Teknik | F4: Morgan | G4: Södra Orredsvägen 2 | H4: 439 74 | I4: Fjärås | J4: 072-325 56 86 | Q4: 42370 | S4: Nej
B5: Halléns Bilservice AB | D5: 1600 kr exkl moms | F5: Fredrik | G5: Kabelvägen 6 | H5: 553 02 | I5: Jönköping | J5: 070-285 81 69 | Q5: 42370 | S5: Nej | T5: B&J Skylt skickad 14/11
A6: Bjuda in i kalendern och även mail | B6: CE Motor | C6: Nej | D6: 2000 kr exkl moms. Övr. se ute i kanten | E6: Vill ha bilen 09.15 | F6: Christian | G6: Energivägen 2 | H6: 135 49 | I6: Tyresö | J6: 08-7703409 Christian 0707-397767 | K6: Christian@cemotor.se | L6: =B6&" "&G6&" "&H6&" "&I6&" Telefon: "&J6 -> CE Motor Energivägen 2 135 49 Tyresö Telefon: 08-7703409 Christian 0707-397767 | N6: Lämna 8.30 på morgonen Kan inte programmera. | O6: Frederik | Q6: 43864 | R6: Jobbar ej torsdag eller fredag i verkstaden. 10% ibland. | S6: Nej | T6: Bättre betalt vid fordonsspecifikt. Mer av kunden (i utgångspunkt) vid extra arbete såsom rost mm.
B7: S-Service Din Bilverkstad AB | D7: 1610 kr + moms /montering | F7: Savo | G7: Fjärestadsvägen 344 | H7: 253 42 | I7: Vallåkra | J7: 042-99208 | L7: =B7&" "&G7&" "&H7&" "&I7&" Telefon: "&J7 -> S-Service Din Bilverkstad AB Fjärestadsvägen 344 253 42 Vallåkra Telefon: 042-99208 | O7: Frederik | Q7: 42370 | S7: Nej
B8: Holmbergs Autoservice | D8: 1600 kr exkl moms. | F8: Markus | G8: Industrigatan 10 | H8: 273 35 | I8: Tomelilla | J8: 0738-133031 | K8: markus@holmbergsautoservice.se | L8: =B8&" "&G8&" "&H8&" "&I8&" Telefon: "&J8 -> Holmbergs Autoservice Industrigatan 10 273 35 Tomelilla Telefon: 0738-133031 | O8: Henrik | Q8: 42736 | S8: Nej
A9: Bjuda in i kalendern | B9: JHS Bilservice | C9: TRUE | D9: 1800 kr exkl moms. | E9: Vill helst ha bilen 09.00 Kan ta 2 bilar per dag. | F9: Jack | G9: Jättevägen 4 | H9: 17677 | I9: Järfälla | J9: 08-58352820 (JACK) 070-881 67 98 | K9: jhs.dragkrok@gmail.com | L9: =B9&" "&G9&" "&H9&" "&I9&" Telefon: "&J9 -> JHS Bilservice Jättevägen 4 17677 Järfälla Telefon: 08-58352820 (JACK) 070-881 67 98 | N9: Fri frakt -10% på dragen | O9: Håkan | P9: FALSE | Q9: 46057 | R9: Nöjd med samarbetet, har mycket att göra i verkstaden - boka ca 1.5 vecka fram | S9: Ja | U9: TRUE
B10: Motornavet | C10: TRUE | D10: 1600 kr exkl moms. | F10: Niklas | G10: Varholmsgatan 12 | H10: 414 74 | I10: Göteborg | J10: 031-128117 | K10: info@motornavet.se | N10: Fri frakt -10% på dragen | O10: Håkan | P10: FALSE | Q10: 42370 | S10: Nej | U10: FALSE
B11: 414 Industries | C11: TRUE | D11: 1600 kr exkl moms. | F11: Ola | H11: 414 74 | I11: Göteborg | J11: 072-7268393 | K11: ola.svalander@gmail.com | L11: =B11&" "&G11&" "&H11&" "&I11&" Telefon: "&J11 -> 414 Industries 414 74 Göteborg Telefon: 072-7268393 | N11: Fri frakt -10% på dragen | O11: Håkan | P11: FALSE | Q11: 42979 | S11: NEJ | U11: FALSE
B12: Tistings Träförädling | C12: TRUE | F12: Oskar | N12: Fri frakt -10% på dragen | O12: Håkan | P12: FALSE | Q12: 42370 | S12: Nej | U12: FALSE
A13: Bjuda in i kalendern | B13: Supreme Autoservice | C13: TRUE | D13: 2250 kr exkl moms Fordonsspecifik 800 ex moms extra om den är jobbig. Extra matarsats 800 ex moms extra. Udda bilar, lyxbilar diskuteras innan. | E13: Vill ha bilen 08.00 Boka upp 3 timmar i kalendern | F13: Ilker | G13: Cypressvägen 10 | H13: 213 63 | I13: Malmö | J13: 040-213 580 ILKER: 0736-600974 | K13: info@supremeauto.se | L13: =B13&" "&G13&" "&H13&" "&I13&" Telefon: "&J13 -> Supreme Autoservice Cypressvägen 10 213 63 Malmö Telefon: 040-213 580 ILKER: 0736-600974 | N13: Fri frakt -10% på dragen | O13: Håkan | P13: FALSE | Q13: 42370 | R13: Nöjd med samarbetet, har mycket att göra i verkstaden - boka ca 1.5 vecka fram | S13: Ja | U13: FALSE
A14: Bjuda in i kalendern och även mail | B14: Tågaborgs Bilservice | C14: TRUE | D14: 2500 kr exkl moms | E14: Öppnar 07.00 och stänger 16.30 | F14: Jonas och Hacim | G14: Florettgatan 7 | H14: 254 67 | I14: Helsingborg | J14: 042-201804 | K14: jonas@tagaborgsbil.com hacim@tagaborgsbil.com info@tagaborgsbil.com | L14: =B14&" "&G14&" "&H14&" "&I14&" Telefon: "&J14 -> Tågaborgs Bilservice Florettgatan 7 254 67 Helsingborg Telefon: 042-201804 | N14: Fri frakt -10% på dragen | O14: Håkan | P14: FALSE | Q14: 43591 | S14: Nej | T14: Pratar med Jonas om att kontrollera dragkrokar innan montering. Bra samtal. Han nämnde även priser, och var överrens om att det är dumt att ändra något nu i svajig marknad. Men prata till hösten igen om kanske 2000 kr + moms för monteringarna (hans förslag) | U14: FALSE
B15: Motala Bilpartner | C15: TRUE | F15: Denis | G15: Vintergatan 4 | H15: 591 32 | I15: Motala | J15: 0141-55990 | N15: Fri frakt -10% på dragen | O15: Håkan | P15: FALSE | Q15: 42370 | S15: Nej | U15: FALSE
A16: Ringa och boka med Sanel | B16: Williams Garage | C16: FALSE | D16: 1600 kr exkl moms (kan komma att höjas) | E16: Vill ha bilen 08.00 | F16: Sanel | G16: Förrådsgatan 10 | H16: 542 35 | I16: Mariestad | J16: 0737-266323 | K16: info@williamsgarage.se | L16: =B16&" "&G16&" "&H16&" "&I16&" Telefon: "&J16 -> Williams Garage Förrådsgatan 10 542 35 Mariestad Telefon: 0737-266323 | N16: Fri frakt -10% på dragen | O16: Håkan | P16: FALSE | Q16: 46057 | R16: Mailat och återkommer om prisbild | S16: Nej | U16: FALSE
A17: Ring innan om tid! | B17: AB Ystad Meck & Däck | C17: TRUE | D17: 2000 kr exkl moms. | E17: Vill ha bilen 08.00 | F17: Marcus | G17: Mässingsgatan 9 | H17: 271 39 | I17: Ystad | J17: 0411-72422 | K17: verkstad@ystaddack.se | L17: =B17&" "&G17&" "&H17&" "&I17&" Telefon: "&J17 -> AB Ystad Meck & Däck Mässingsgatan 9 271 39 Ystad Telefon: 0411-72422 | N17: Fri frakt -10% på dragen | O17: Håkan | P17: FALSE | Q17: 46057 | R17: Nöjd med samarbetet, har mycket att göra i verkstaden - boka ca 2.5 vecka fram och ring före bokning | S17: Ja | U17: FALSE
A18: Bjud in i kalendern | B18: IM Bilservice | C18: TRUE | D18: Dragkrok: 2400 kr + moms Motorvärmare: 2000 kr + moms | E18: Vill ha bilen 08.00. | F18: Issam | G18: Kvällsvindsgatan 6 | H18: 652 21 | I18: Karlstad | J18: 054-85 68 70 | K18: imbilservice@boschcarservice.se samassaad5@gmail.com | L18: =B18&" "&G18&" "&H18&" "&I18&" Telefon: "&J18 -> IM Bilservice Kvällsvindsgatan 6 652 21 Karlstad Telefon: 054-85 68 70 | N18: Fri frakt -10% på dragen | O18: Håkan | P18: FALSE | Q18: 46057 | R18: Fortsätter sammarbetet men tar krokarna ifrån Experten tyvärr efter strul med 3 st leveranser Boka 1,5 vecka fram | S18: Ja | U18: FALSE
B19: Frösö Gummi AB | C19: TRUE | F19: Fredrik | G19: Frösövägen 63 | H19: 832 44 | I19: FRÖSÖN | J19: 063-104666 | N19: Fri frakt -10% på dragen | O19: Håkan | P19: FALSE | Q19: 42736 | S19: Nej | U19: FALSE
B20: HH Bilservice HB | C20: TRUE | D20: 1600 kr exkl moms. | F20: Fredrik Faraj | G20: Jättevägen 4 | H20: 176 77 | I20: Järfälla | J20: 08-58352820 | N20: Fri frakt -10% på dragen | O20: Håkan | P20: FALSE | Q20: 42614 | S20: Nej | U20: FALSE
A21: Bjuda in i kalendern och även mail maila först och kolla läget | B21: Speedy Bilservice Åhus (Åhus Fordonsteknik AB) | C21: FALSE | D21: 2500kr exkl moms. | E21: Vill ha bilen 08.00. | F21: Robin och Alex | G21: Koriandervägen 4 | H21: 296 41 | I21: Åhus | J21: 044-24 00 57 | K21: ahus@speedybilservice.se | L21: =B21&" "&G21&" "&H21&" "&I21&" Telefon: "&J21 -> Speedy Bilservice Åhus (Åhus Fordonsteknik AB) Koriandervägen 4 296 41 Åhus Telefon: 044-24 00 57 | N21: Fri frakt -10% på dragen | O21: Håkan | P21: FALSE | Q21: 46057 | R21: Mycket jobb just nu så vi mailar om bokning Ändrat till 2500+ moms. Snackat även om clipps sats till inredning som går sönder vid demontering, att det framgår till kund att det kostar extra ex 500kr | S21: Ja | U21: FALSE
B22: Brännlunds Garage | D22: 1600 kr exkl moms. | F22: Peter | G22: Snäppvägen 3 | H22: 802 91 | I22: Gävle | J22: 0703-980894 | K22: info@brannlundsgarage.com | L22: =B22&" "&G22&" "&H22&" "&I22&" Telefon: "&J22 -> Brännlunds Garage Snäppvägen 3 802 91 Gävle Telefon: 0703-980894 | N22: Fri frakt -10% på dragen | O22: Håkan | P22: FALSE | Q22: 42887 | S22: Nej | U22: FALSE
A23: Maila och ringa | B23: Magnus Snabbservice | D23: 2000 kr exkl moms. | E23: Vill ha bilen 08.00 | F23: Magnus och Daniel | G23: Skallebackavägen 20 | H23: 302 41 | I23: Halmstad | J23: 035-10 00 55 0733-854120 | K23: info@magnussnabbservice.se magnus@magnussnabbservice.se fredrik@magnussnabbservice.se | L23: =B23&" "&G23&" "&H23&" "&I23&" Telefon: "&J23 -> Magnus Snabbservice Skallebackavägen 20 302 41 Halmstad Telefon: 035-10 00 55 0733-854120 | N23: Fri frakt -10% på dragen | O23: Håkan | P23: FALSE | Q23: 43490 | S23: Nej | U23: FALSE
B24: Pettsons Bilservice | D24: 2000 kr exkl moms. | F24: Agne | G24: Västerhejde Gamla Kyrkvägen 8 | H24: 622 61 | I24: Visby | J24: 0706-296146 | N24: Fri frakt -10% på dragen | O24: Håkan | P24: FALSE | Q24: 42370 | S24: Nej | U24: FALSE
A25: Bjuda in i kalendern och även mail | B25: Speedy Bilservice Falkenberg | C25: 195 | D25: 2300 kr exkl moms. | E25: Vill ha bilen 08.00 helst | F25: Andreas | G25: Oktanvägen 1c | H25: 311 32 | I25: Falkenberg | J25: 0346-216969 0705-880519 | K25: falkenberg@speedybilservice.se | L25: =B25&" "&G25&" "&H25&" "&I25&" Telefon: "&J25 -> Speedy Bilservice Falkenberg Oktanvägen 1c 311 32 Falkenberg Telefon: 0346-216969 0705-880519 | N25: Fri frakt -10% på dragen | O25: Håkan | P25: FALSE | Q25: 43496 | S25: Nej | U25: FALSE
B26: Bil och Maskinteknik AB | D26: 1600 kr exkl moms. | F26: Magnus, Mikael | G26: Ahlmarksvägen 1 | H26: 953 36 | I26: Haparanda | J26: 072-2197848 | K26: 34009@okq8bilverkstad.se | L26: =B26&" "&G26&" "&H26&" "&I26&" Telefon: "&J26 -> Bil och Maskinteknik AB Ahlmarksvägen 1 953 36 Haparanda Telefon: 072-2197848 | N26: Fri frakt -10% på dragen | O26: Håkan | P26: FALSE | Q26: 43490 | S26: Nej | T26: De jobbar bara en i verkstaden nu, den andra i gruvan. Kör varannan vecka. //TC 3/11 | U26: FALSE
A27: Bjuda in i kalendern | B27: Drakängens Bilservice | C27: TRUE | D27: 1600 kr exkl moms. | E27: Vill ha bilen 08.00. | F27: Robban | G27: Drakängen Attsjö | H27: 36593 | I27: Furuby/växjö | J27: 0704-644547 | K27: robban300zx@hotmail.com | L27: =B27&" "&G27&" "&H27&" "&I27&" Telefon: "&J27 -> Drakängens Bilservice Drakängen Attsjö 36593 Furuby/växjö Telefon: 0704-644547 | N27: Fri frakt -10% på dragen | O27: Håkan | P27: FALSE | Q27: 46057 | R27: Nöjd med samarbetet, har mycket att göra i verkstaden - boka ca 1.5 vecka fram sem 26/4 - 2 veckor | S27: Ja | U27: FALSE
A28: Bjuda in i kalendern | B28: JV Automontage | C28: 295 kr (vår egen) | D28: 1800 kr exkl moms | E28: Vill ha bilen 09.15 | F28: Jesper Vinquist | G28: EA Rosengrens gata 27 | H28: 421 32 | I28: Västra Frölunda | J28: 0735-180195 | K28: jesper@jvautomontage.se | L28: =B28&" "&G28&" "&H28&" "&I28&" Telefon: "&J28 -> JV Automontage EA Rosengrens gata 27 421 32 Västra Frölunda Telefon: 0735-180195 | N28: Fri frakt -10% på dragen | O28: Håkan | P28: FALSE | Q28: 43617 | S28: Nej | U28: FALSE
B29: Speedy Bilservice Karlskrona | D29: 1600 kr exkl moms. | F29: Nikki | G29: Sunnavägen 99 | H29: 371 41 | I29: Karlskrona | J29: 0455-192 20 | K29: karlskrona@speedybilservice.se | L29: =B29&" "&G29&" "&H29&" "&I29&" Telefon: "&J29 -> Speedy Bilservice Karlskrona Sunnavägen 99 371 41 Karlskrona Telefon: 0455-192 20 | N29: Fri frakt -10% på dragen | O29: Håkan | P29: FALSE | Q29: 43490 | S29: NEJ | U29: FALSE
A30: Lägga in i kalendern | B30: Äpplekullen Bil & Däckservice | C30: TRUE | D30: 2000 kr exkl moms. | E30: Vill ha bilen 08.00 | F30: Roger (Marcus & Mikael) | G30: Ekenleden 1 | H30: 428 36 | I30: Kållered | J30: 031-7951000 (0735-361705) | K30: info@applekullen.se | L30: =B30&" "&G30&" "&H30&" "&I30&" Telefon: "&J30 -> Äpplekullen Bil & Däckservice Ekenleden 1 428 36 Kållered Telefon: 031-7951000 (0735-361705) | N30: Fri frakt -10% på dragen | O30: Håkan | P30: FALSE | Q30: 46057 | R30: "Nöjd med samarbetet, har mycket att göra i verkstaden - boka ca 2 veckor fram | S30: Ja | U30: TRUE
A31: Skicka info på SMS. | B31: Widhedens Bil AB | D31: 1600 kr exkl moms 10% när han handlar | E31: Vill ha bilen 08.00 | F31: Richard | G31: Björbäcksvägen 6 | H31: 451 55 | I31: Uddevalla | J31: 0763-048909(Widhedens) 0738-219725(Richard) | K31: widhedenbil@gmail.com | L31: =B31&" "&G31&" "&H31&" "&I31&" Telefon: "&J31 -> Widhedens Bil AB Björbäcksvägen 6 451 55 Uddevalla Telefon: 0763-048909(Widhedens) 0738-219725(Richard) | N31: Fri frakt -10% på dragen | O31: Håkan | P31: FALSE | Q31: 44222 | S31: Nej | U31: FALSE
A32: Skicka info på SMS. | B32: 1st Class Bil & Lackering | D32: 1600 kr exkl moms 10% när han handlar | F32: Ivar | G32: Skälebol Mossen 1 | H32: 464 92 | I32: Mellerud | J32: 0764-14 25 66 | K32: Ivar.Borresen2022@outlook.com | L32: =B32&" "&G32&" "&H32&" "&I32&" Telefon: "&J32 -> 1st Class Bil & Lackering Skälebol Mossen 1 464 92 Mellerud Telefon: 0764-14 25 66 | N32: Fri frakt -10% på dragen | O32: Håkan | P32: FALSE | Q32: 44208 | S32: Nej | T32: Meddelat 23/1 att han ej kan fakturera längre och därmed inte kan montera. | U32: FALSE
B33: Nybrons Bilservice AB | D33: 1600 kr exkl moms. | F33: Roger | G33: Bergslenagatan 49 | H33: 506 30 | I33: Borås | J33: 033-131780 | K33: info@nybronsbilservice.se | L33: =B33&" "&G33&" "&H33&" "&I33&" Telefon: "&J33 -> Nybrons Bilservice AB Bergslenagatan 49 506 30 Borås Telefon: 033-131780 | N33: Fri frakt -10% på dragen | O33: Håkan | P33: FALSE | Q33: 43503 | S33: Nej | U33: FALSE
B34: Bilverkstan i Sundsvall AB | D34: 1600 kr exkl moms. | F34: Kent-Ove Nordin | G34: Tegelvägen 8B | H34: 853 50 | I34: Sundsvall | J34: 070-330 24 11 | K34: nordan@bilverkstanisundsvall.se | L34: =B34&" "&G34&" "&H34&" "&I34&" Telefon: "&J34 -> Bilverkstan i Sundsvall AB Tegelvägen 8B 853 50 Sundsvall Telefon: 070-330 24 11 | N34: Fri frakt -10% på dragen | O34: Håkan | P34: FALSE | Q34: 43501 | S34: Nej | U34: FALSE
B35: Speedy Bilservice Jönköping | D35: 1600 kr exkl moms. | F35: Ivan | G35: Bangårdsgatan 4 | H35: 553 03 | I35: Jönköping | J35: 036-2913000 | K35: jonkoping@speedybilservice.se | L35: =B35&" "&G35&" "&H35&" "&I35&" Telefon: "&J35 -> Speedy Bilservice Jönköping Bangårdsgatan 4 553 03 Jönköping Telefon: 036-2913000 | N35: Fri frakt -10% på dragen | O35: Håkan | P35: FALSE | Q35: 43475 | S35: Nej | U35: FALSE
B36: Speedy Bilservice Östermalm | D36: 1600 kr exkl moms. 3000kr + moms ska dem ha //TC | F36: Gleb | G36: Valhallavägen 161 Mitt emot Fältöversten. T-station 15 m. | H36: 115 53 | I36: Stockholm | J36: 08-662 60 65 0736-974541 | K36: ostermalm@speedybilservice.se | L36: =B36&" "&G36&" "&H36&" "&I36&" Telefon: "&J36 -> Speedy Bilservice Östermalm Valhallavägen 161 Mitt emot Fältöversten. T-station 15 m. 115 53 Stockholm Telefon: 08-662 60 65 0736-974541 | N36: Fri frakt -10% på dragen | O36: Håkan | P36: FALSE | Q36: 43525 | S36: NEJ | U36: FALSE
A37: Bjuda in i kalendern och även mail | B37: Sjömarkens Motor & Aluminium | C37: FALSE | D37: 2500 kr exkl moms | E37: Vill ha bilen 08.00 | F37: Jonas | G37: Göteborgsvägen 25 | H37: 51840 | I37: Sjömarken/Borås | J37: 070-9296019 | K37: info@aluminiumiboras.se | L37: =B37&" "&G37&" "&H37&" "&I37&" Telefon: "&J37 -> Sjömarkens Motor & Aluminium Göteborgsvägen 25 51840 Sjömarken/Borås Telefon: 070-9296019 | N37: Fri frakt -10% på dragen | O37: Håkan | P37: FALSE | Q37: 46057 | R37: """Nöjd med samarbetet, har lagomt att göra i verkstaden - boka ca 1,5 veckor fram " | S37: Ja | U37: FALSE
A38: Maila och ev SMS:a han | B38: Skarstad Bilverkstad // Daniel Bergendahl | C38: FALSE | D38: 1600 kr exkl moms. | E38: Vill ha bilen kl 10.00 och Tisdagar, andra dagar får vi ringa om | F38: Daniel | G38: Basegården 11 Skarstad | H38: 53495 | I38: Vara | J38: 0707-589796 | K38: turbomani1@hotmail.com | L38: =B38&" "&G38&" "&H38&" "&I38&" Telefon: "&J38 -> Skarstad Bilverkstad // Daniel Bergendahl Basegården 11 Skarstad 53495 Vara Telefon: 0707-589796 | N38: Fri frakt -10% på dragen | O38: Håkan | P38: FALSE | Q38: 43490 | S38: Ja | U38: FALSE
B39: Skäggetorps Bilverkstad | D39: 1600 kr exkl moms. | F39: Foaad Daniel | G39: Skäggetorp Centrum 8 | H39: 586 44 | I39: Linköping | J39: 013-17 16 18 076-225 09 11 | K39: foaad_daniel@hotmail.com | L39: =B39&" "&G39&" "&H39&" "&I39&" Telefon: "&J39 -> Skäggetorps Bilverkstad Skäggetorp Centrum 8 586 44 Linköping Telefon: 013-17 16 18 076-225 09 11 | N39: Fri frakt -10% på dragen | O39: Håkan | P39: FALSE | Q39: 43525 | S39: NEJ | U39: FALSE
B40: Speedy Bilservice Tagene | D40: 1600 kr exkl moms. | F40: Jonas | G40: Karlsbogårdsgatan 2 (samma hus som Besikta) | H40: 425 37 | I40: Hising Kärra | J40: 031-57 11 99 | L40: =B40&" "&G40&" "&H40&" "&I40&" Telefon: "&J40 -> Speedy Bilservice Tagene Karlsbogårdsgatan 2 (samma hus som Besikta) 425 37 Hising Kärra Telefon: 031-57 11 99 | N40: Fri frakt -10% på dragen | O40: Håkan | P40: FALSE | Q40: 43525 | S40: NEJ | U40: FALSE
B41: Bilhuset I Kalmar | D41: 1600 kr exkl moms. | F41: Tror han heter Mikael | G41: Trångsundsvägen 4 | H41: 392 39 | I41: Kalmar | J41: 0480-273 10 073-9800717 | K41: Bilhusetikalmar@hotmail.com | L41: =B41&" "&G41&" "&H41&" "&I41&" Telefon: "&J41 -> Bilhuset I Kalmar Trångsundsvägen 4 392 39 Kalmar Telefon: 0480-273 10 073-9800717 | N41: Fri frakt -10% på dragen | O41: Håkan | P41: FALSE | Q41: 43545 | S41: NEJ | U41: FALSE
A42: Bjuda in i kalendern och även mail | B42: Bilverkstadscenter i Jönköping AB | C42: NEJ | D42: 1800 kr exkl moms. | E42: Vill ha bilen 08.00 | F42: Samer (& Sara) | G42: Grossistgatan 3 | H42: 553 02 | I42: Jönköping | J42: 070-285 81 69 Sara 0707-363239 | K42: bilverkstadcenter@gmail.com | L42: =B42&" "&G42&" "&H42&" "&I42&" Telefon: "&J42 -> Bilverkstadscenter i Jönköping AB Grossistgatan 3 553 02 Jönköping Telefon: 070-285 81 69 Sara 0707-363239 | N42: Fri frakt -10% på dragen | O42: Håkan | P42: FALSE | Q42: 42856 | S42: Nej | U42: FALSE
B43: Viamotor Borlänge | C43: 200 | D43: 1600 kr exkl moms. | F43: Elias (0243-204533) | G43: Hugo Hedströms väg 6 | H43: 781 72 | I43: Borlänge | J43: 0243-175 50 | K43: Info@viamotor.se | L43: =B43&" "&G43&" "&H43&" "&I43&" Telefon: "&J43 -> Viamotor Borlänge Hugo Hedströms väg 6 781 72 Borlänge Telefon: 0243-175 50 | N43: Fri frakt -10% på dragen | O43: Håkan | P43: FALSE | Q43: 43607 | S43: Nej | U43: FALSE
A44: Ringa | B44: CULO autoservice | C44: Nej | D44: 1600 kr exkl moms. | F44: Ulf | G44: Förrådsgatan 5 | H44: 575 36 | I44: Eksjö | J44: 072-5890987 | K44: culoautoservice@gmail.com | L44: =B44&" "&G44&" "&H44&" "&I44&" Telefon: "&J44 -> CULO autoservice Förrådsgatan 5 575 36 Eksjö Telefon: 072-5890987 | N44: Fri frakt -10% på dragen | O44: Håkan | P44: FALSE | Q44: 42979 | S44: Nej | U44: FALSE
A45: Ring och Maila SMS:a innan om tider | B45: Speedy Bilservice Linköping / Fikratsson Bil AB | C45: Ja, 200kr (e-bil) | D45: 2100kr exkl moms. Ring om fs elsats | E45: Lämna bilen kl 09.00 på morgonen Vet inte om de kan programmera." | F45: Martin | G45: Gillbergagatan 23 | H45: 582 73 | I45: Linköping | J45: 013-707 72 0723-609520 | K45: tornby@speedybilservice.se | L45: =B45&" "&G45&" "&H45&" "&I45&" Telefon: "&J45 -> Speedy Bilservice Linköping / Fikratsson Bil AB Gillbergagatan 23 582 73 Linköping Telefon: 013-707 72 0723-609520 | N45: Fri frakt -10% på dragen | O45: Håkan | P45: FALSE | Q45: 44166 | S45: Nej | U45: FALSE
A46: Bjuda in i kalendern och även mail | B46: Speedy Bilservice Eskilstuna | C46: FALSE | D46: 2800 kr exkl moms för dragkrokar motorvärmare 3500+m | E46: Vill ha bilen 08.00 | F46: Nikita eller Elvir | G46: Mått Johanssons Väg 14 | H46: 633 46 | I46: Eskilstuna | J46: 016-5423828 | K46: eskilstuna@speedybilservice.se | L46: =B46&" "&G46&" "&H46&" "&I46&" Telefon: "&J46 -> Speedy Bilservice Eskilstuna Mått Johanssons Väg 14 633 46 Eskilstuna Telefon: 016-5423828 | N46: Fri frakt -10% på dragen | O46: Håkan | P46: FALSE | Q46: 46057 | R46: Samtal och mailat om lägre priser övk 2800+m drag | S46: Ja | U46: FALSE
A47: Maila SMS:a innan om tider | B47: Gunnarssons Serviceteknik | C47: Tyvär ingen lånebil | D47: 1600 kr exkl moms | E47: Vill ha bilen 08.00 | F47: Anders Gunnarsson | G47: Storgatan 205 Säbylund | H47: 655 95 | I47: Väse | J47: 0706-051194 | K47: info.gunnarssonsst@gmail.com (Privat a67gunnarsson@gmail.com) | L47: =B47&" "&G47&" "&H47&" "&I47&" Telefon: "&J47 -> Gunnarssons Serviceteknik Storgatan 205 Säbylund 655 95 Väse Telefon: 0706-051194 | N47: Fri frakt -10% på dragen | O47: Håkan | P47: FALSE | Q47: 44098 | S47: Ja | T47: "Karlstad" | U47: FALSE
A48: Bjuda in i kalendern och även mail | B48: Speedy Bilservice Örebro | C48: Ja | D48: Dragkrok 2000 kr exkl moms. Motorvärmare 1600 kr exkl moms. Lånebil 250 kr | E48: Vill ha bilen 08.00 | F48: Monir | G48: Radiatorvägen 5 | H48: 702 27 | I48: Örebro | J48: 0704-566702 019-25 42 10 | K48: orebro@speedybilservice.se | L48: =B48&" "&G48&" "&H48&" "&I48&" Telefon: "&J48 -> Speedy Bilservice Örebro Radiatorvägen 5 702 27 Örebro Telefon: 0704-566702 019-25 42 10 | N48: Fri frakt -10% på dragen | O48: Håkan | P48: FALSE | Q48: 42675 | S48: Nej | T48: Mailat nya priser till kund 161201 //TC | U48: FALSE
B49: AD Bilverkstad B-Bus & Kuma Bilservice AB | D49: 1600 kr exkl moms. | F49: Mathias | G49: Faktorsgatan 14 | H49: 461 37 | I49: Trollhättan | J49: 0520-400581 070-723 69 17 | K49: b-bus.kuma@live.com | L49: =B49&" "&G49&" "&H49&" "&I49&" Telefon: "&J49 -> AD Bilverkstad B-Bus & Kuma Bilservice AB Faktorsgatan 14 461 37 Trollhättan Telefon: 0520-400581 070-723 69 17 | N49: Fri frakt -10% på dragen | O49: Håkan | P49: FALSE | Q49: 43758 | S49: Nej | U49: FALSE
A50: Bjuda in i kalendern och även mail | B50: Speedy Bilservice Västerås | C50: TRUE | D50: 1850 kr exkl moms. | E50: Vill ha bilen 08.00 | F50: Marius | G50: Strömledningsgatan 3 | H50: 721 37 | I50: Västerås | J50: 021-81 14 35 (Marius)0729-005752 | K50: vasteras@speedybilservice.se | L50: =B50&" "&G50&" "&H50&" "&I50&" Telefon: "&J50 -> Speedy Bilservice Västerås Strömledningsgatan 3 721 37 Västerås Telefon: 021-81 14 35 (Marius)0729-005752 | N50: Fri frakt -10% på dragen | O50: Håkan | P50: FALSE | Q50: 43525 | S50: Ja | U50: FALSE
A51: Maila innan vi bokar in tid | B51: S.A Performance cars AB | C51: FALSE | D51: 2050 kr + moms 10% rabatt och fri frakt | E51: Vill ha bilen 09.00 | F51: Adel Hassoun Toni Kimbrell | G51: Bälinge-Svista 45 | H51: 755 93 | I51: Uppsala | J51: 018-444 01 92 018-444 01 94 | K51: adel@saperformance.se saperformance@autoexperten.se | L51: =B51&" "&G51&" "&H51&" "&I51&" Telefon: "&J51 -> S.A Performance cars AB Bälinge-Svista 45 755 93 Uppsala Telefon: 018-444 01 92 018-444 01 94 | M51: 559375-0242 | N51: Fri frakt -10% på dragen | O51: Håkan | P51: FALSE | Q51: 46056 | R51: Ringde,inget svar.Mailat dom,återkommer sen meddelar dom. | S51: Ja | U51: FALSE
B52: Bilvårdshuset i Gävle | D52: 1600 kr exkl moms. | F52: Abbas | G52: Kanalvägen 1 | H52: 803 09 | I52: Gävle | J52: 076-2180910 | K52: abbas5008@hotmail.com | L52: =B52&" "&G52&" "&H52&" "&I52&" Telefon: "&J52 -> Bilvårdshuset i Gävle Kanalvägen 1 803 09 Gävle Telefon: 076-2180910 | N52: Fri frakt -10% på dragen | O52: Håkan | P52: FALSE | Q52: 43753 | S52: Nej | U52: FALSE
A53: Bjuda in i kalendern och även mail | B53: Autoservice AB | D53: 1600 kr exkl moms. | E53: Vill ha bilen 08.00 | F53: Henrik | G53: Långsandsvägen 2B | H53: 814 93 | I53: Skutskär/gävle | J53: 070-4324555(Henrik) 026-600 832 | K53: revtechswe@gmail.com | L53: =B53&" "&G53&" "&H53&" "&I53&" Telefon: "&J53 -> Autoservice AB Långsandsvägen 2B 814 93 Skutskär/gävle Telefon: 070-4324555(Henrik) 026-600 832 | N53: Fri frakt -10% på dragen | O53: Håkan | P53: FALSE | Q53: 44616 | S53: Nej | U53: FALSE
A54: Bjuda in och även mail i kalendern | B54: Mekonomen Bilverkstad Sundsvall / Haga Bilteknik AB | C54: Gratis | D54: 1600 kr exkl moms. | F54: Kenny | G54: Hagavägen 76 | H54: 856 44 | I54: Sundsvall | J54: 060-15 92 65 0706-624509 | K54: hagabilteknik@gmail.com Sundsvallnorr@mekonomenbilverkstad.se | L54: =B54&" "&G54&" "&H54&" "&I54&" Telefon: "&J54 -> Mekonomen Bilverkstad Sundsvall / Haga Bilteknik AB Hagavägen 76 856 44 Sundsvall Telefon: 060-15 92 65 0706-624509 | N54: Fri frakt -10% på dragen | O54: Håkan | P54: FALSE | Q54: 43728 | S54: Nej | U54: FALSE
A55: Maila | B55: 4Car | C55: FALSE | D55: Dragkrokar 2240 kr exkl moms. Värmare 2240 kr exkl moms | E55: Vill ha bilen 08.00 0706-655510 (Marcus) | F55: Magnus och Markus | G55: Sandbäcksgatan 15 | H55: 906 20 | I55: Umeå | J55: 090-701400 | K55: info@4car.se | L55: =B55&" "&G55&" "&H55&" "&I55&" Telefon: "&J55 -> 4Car Sandbäcksgatan 15 906 20 Umeå Telefon: 090-701400 | N55: Fri frakt -10% på dragen | O55: Håkan | P55: FALSE | Q55: 42887 | S55: Ja | U55: FALSE
B56: Sikeå Bil & Rep | D56: 1600 kr exkl moms. | F56: Joakim | G56: Sikeå 53 | H56: 915 93 | I56: Robertsfors | J56: 0934-30070 | K56: info@sikeabilrep.se | L56: =B56&" "&G56&" "&H56&" "&I56&" Telefon: "&J56 -> Sikeå Bil & Rep Sikeå 53 915 93 Robertsfors Telefon: 0934-30070 | N56: Fri frakt -10% på dragen | O56: Håkan | P56: FALSE | Q56: 43846 | S56: Nej | U56: FALSE
A57: Bjuda in i kalendern och även mail | B57: Piteå Bilverkstad | C57: FALSE | D57: 1920 3000kr exkl moms Motorvärmare 1500 kr + moms 10% rabatt | E57: Vill ha bilen kl 08.00 | F57: Peter | G57: Nötögrundsvägen 175 | H57: 941 41 | I57: Piteå | J57: 0706-806565 | K57: piteabilverkstad@gmail.com | L57: =B57&" "&G57&" "&H57&" "&I57&" Telefon: "&J57 -> Piteå Bilverkstad Nötögrundsvägen 175 941 41 Piteå Telefon: 0706-806565 | N57: Fri frakt -10% på dragen | O57: Håkan | P57: FALSE | Q57: 42370 | S57: Ja | U57: FALSE
A58: Bjuda in i kalendern och även mail | B58: AutoTuning i Norden AB | C58: NEJ. Kan hämta bil i Sundsvall alt. skjutsa kunden. | D58: 1800 kr exkl moms Drag och motorvärmare | E58: Vill ha bilen kl 08.00 | F58: Dennis | G58: Gubbyn 591, Besöksadress: Byn 186 | H58: 841 96 | I58: Erikslund/Sundsvall | J58: 072-1732470 | K58: dennis@autotuning.nu | L58: =B58&" "&G58&" "&H58&" "&I58&" Telefon: "&J58 -> AutoTuning i Norden AB Gubbyn 591, Besöksadress: Byn 186 841 96 Erikslund/Sundsvall Telefon: 072-1732470 | N58: Fri frakt -10% på dragen | O58: Håkan | P58: FALSE | Q58: 44628 | S58: Nej | T58: Org.nr 559152-0126 | U58: FALSE
A59: Bjuda in i kalendern och även mail | B59: Peters bil & båtverkstad | C59: JA. 200 kr | D59: 1800 kr exkl moms Drag, motorvärmare och LED-ramper | E59: Vill ha bilen kl 08.00 | F59: Peter | G59: VÄSSBY NORDLID 4 | H59: 452 92 | I59: Strömstad | J59: 073-9523011 | K59: mellqvist1@hotmail.com | L59: =B59&" "&G59&" "&H59&" "&I59&" Telefon: "&J59 -> Peters bil & båtverkstad VÄSSBY NORDLID 4 452 92 Strömstad Telefon: 073-9523011 | N59: Fri frakt -10% på dragen | O59: Håkan | P59: FALSE | Q59: 44628 | S59: Nej | T59: Org.nr: 650825-4890-00001 | U59: FALSE
A60: Bjuda in och även mail i kalendern | B60: Segersjö Bilservice AB | C60: JA, 195 kr + drivmedel | D60: 1800 kr exkl moms Drag och motorvärmare. Kan programmera(inga inga prisuppgifter än) | E60: Vill ha bilen kl 08.00, har ett inkasst för att lämna nyckeln utanför öppet tider. | F60: Michael och Benny | G60: Drottningvägen 12 | H60: 14731 | I60: Tumba | J60: Michael: 070-2830873 Verkstaden: 08-530 363 63 | K60: segersjo@mekopartner.se | L60: =B60&" "&G60&" "&H60&" "&I60&" Telefon: "&J60 -> Segersjö Bilservice AB Drottningvägen 12 14731 Tumba Telefon: Michael: 070-2830873 Verkstaden: 08-530 363 63 | N60: Fri frakt -10% på dragen | O60: Håkan | P60: FALSE | Q60: 44658 | S60: Nej | U60: FALSE
A61: Bjuda in i kalendern och även mail | B61: Speedy Bilservice Skövde | C61: NEJ | D61: 1800 kr exkl moms Drag och motorvärmare. (LED-ramper). Kan programmera Autel 480 kr exkl moms. | E61: Vill ha bilen kl 07.30-08.00, har ett inkasst för att lämna nyckeln utanför öppet tider. | F61: Johannes | G61: Magasinsgatan 4 | H61: 541 34 | I61: Skövde | J61: Johannes: 073-1504118 Verkstaden: 0500272080 | K61: skovde@speedybilservice.se | L61: =B61&" "&G61&" "&H61&" "&I61&" Telefon: "&J61 -> Speedy Bilservice Skövde Magasinsgatan 4 541 34 Skövde Telefon: Johannes: 073-1504118 Verkstaden: 0500272080 | N61: Fri frakt -10% på dragen | O61: Håkan | P61: FALSE | Q61: 44658 | S61: Nej | U61: FALSE
A62: Bjuda in i kalendern och även mail | B62: Melvin Bilverkstad | C62: FALSE | D62: 2520 kr exkl moms. EJ montering av motorvärmare eller programmering. | E62: Vill ha bilen kl 09.00 | F62: Melvin | G62: Franska vägen 23 | H62: 39356 | I62: Kalmar | J62: 0480-20900 0768-091839 | K62: info@melvinbilverkstad.se | L62: =B62&" "&G62&" "&H62&" "&I62&" Telefon: "&J62 -> Melvin Bilverkstad Franska vägen 23 39356 Kalmar Telefon: 0480-20900 0768-091839 | N62: Fri frakt -10% på dragen | O62: Håkan | P62: FALSE | Q62: 44673 | S62: Ja | U62: FALSE
A63: Bjuda in i kalendern och även mail | B63: Bilvårdshuset i Gävle | C63: NEJ | D63: 2000 kr exkl moms Drag och motorvärmare. Kan programmera(fråga om pris). | E63: Vill ha bilen kl 08.00 | F63: Abbas | G63: Kanalvägen 1-3 | H63: 80309 | I63: Gävle | J63: 026-600525 Abbas Mobil:076-2180910 | K63: info@bilvardshuset.se | L63: =B63&" "&G63&" "&H63&" "&I63&" Telefon: "&J63 -> Bilvårdshuset i Gävle Kanalvägen 1-3 80309 Gävle Telefon: 026-600525 Abbas Mobil:076-2180910 | N63: Fri frakt -10% på dragen | O63: Håkan | P63: FALSE | Q63: 44684 | S63: Nej | T63: https://www.bilvardshuset.se/ | U63: FALSE
A64: Bjuda in i kalendern och även mail | B64: Speedy Bilservice Mjölby | C64: Ja, 200 kr + tanka för det man kör | D64: 2100 kr exkl moms. Ring om spec elsats | E64: Vill ha bilen kl 09.00 | F64: Martin | G64: Albacksvägen 6 | H64: 595 50 | I64: Mjölby | J64: 0142-60 59 00 0723-609520 | K64: mjolby@speedybilservice.se | L64: =B64&" "&G64&" "&H64&" "&I64&" Telefon: "&J64 -> Speedy Bilservice Mjölby Albacksvägen 6 595 50 Mjölby Telefon: 0142-60 59 00 0723-609520 | N64: Fri frakt -10% på dragen | O64: Håkan | P64: FALSE | Q64: 44739 | S64: Nej | U64: FALSE
A65: Bjuda in i kalendern och även mail | B65: MEKIAN Bilverkstad | C65: NEJ | D65: 2000kr exkl moms. | E65: Vill ha bilen kl 08.00 | F65: Kosrat | G65: Nytorpsvägen 2A | H65: 183 53 | I65: Täby | J65: 08-768 45 70 | K65: info@mekian.com | L65: =B65&" "&G65&" "&H65&" "&I65&" Telefon: "&J65 -> MEKIAN Bilverkstad Nytorpsvägen 2A 183 53 Täby Telefon: 08-768 45 70 | N65: Fri frakt -10% på dragen | O65: Håkan | P65: FALSE | Q65: 44825 | S65: Nej | U65: FALSE
A66: Ring in bokningen (de första gångerna) | B66: Njutångers Bil & Allservice AB Hudiksvall | C66: Ja (Betala bensin | D66: 1800 kr 2200 kr exkl moms Drag och motorvärmare. | E66: Vill ha bilen kl 08.00 Mån till torsdag helst ej fredagar | F66: Lars | G66: Barnängsvägen 10 | H66: 82592 | I66: Njutånger | J66: 073-817 74 48 | K66: njutangersbil@gmail.com | L66: =B66&" "&G66&" "&H66&" "&I66&" Telefon: "&J66 -> Njutångers Bil & Allservice AB Hudiksvall Barnängsvägen 10 82592 Njutånger Telefon: 073-817 74 48 | N66: Fri frakt -10% på dragen | O66: Håkan | P66: FALSE | S66: Nej | U66: FALSE
A67: Bjuda in i kalendern och även mail | B67: Kungälvs Bil & Motorservice AB | C67: NEJ | D67: 1900 kr exkl moms Programmering 400 kr exkl moms. | E67: Vill ha bilen kl 09.00, vill kunden ställa bilen tidigare så kan dem ställa bilen andra sidan gatan och lämna nyckeln i brevlådan som alternativ. | F67: Josef | G67: Bultgatan 19 | H67: 442 40 | I67: Kungälv | J67: Verkstad: 0303-37 99 12 Josef: 0764-218218 | K67: info@kungalvsbil.se | L67: =B67&" "&G67&" "&H67&" "&I67&" Telefon: "&J67 -> Kungälvs Bil & Motorservice AB Bultgatan 19 442 40 Kungälv Telefon: Verkstad: 0303-37 99 12 Josef: 0764-218218 | N67: Fri frakt -10% på dragen | O67: Håkan | P67: FALSE | Q67: 44847 | S67: Nej | U67: FALSE
A68: Ring in bokningen (de första gångerna) | B68: PowerCar Service AB | C68: TRUE | D68: 2500 kr inkl moms | E68: Öppnar 08.00 | F68: Niklas | G68: Doktorsvägen 4 | H68: 14730 | I68: Tumba | J68: 08-91 52 65 08-7229670 Niklas: 070-7995265, 0735-141201 (privata) | K68: niklas@powercar.se | L68: =B68&" "&G68&" "&H68&" "&I68&" Telefon: "&J68 -> PowerCar Service AB Doktorsvägen 4 14730 Tumba Telefon: 08-91 52 65 08-7229670 Niklas: 070-7995265, 0735-141201 (privata) | N68: Fri frakt -10% på dragen | O68: Håkan | P68: FALSE | S68: Ja | U68: FALSE
A69: Bjuda in i kalendern och även mail | B69: Linköpings Bilvaruhus AB | C69: nej | D69: 2000 kr + moms Drag och motorvärmare. Mer betalt när det är jobbiga monteringar. | F69: Haidar Vugar | G69: Rönögatan 12 | H69: 58278 | I69: Linköping Sweden | J69: 0728-333366 | K69: haidar.jaber@linkopingsbilvaruhus.se | L69: =B69&" "&G69&" "&H69&" "&I69&" Telefon: "&J69 -> Linköpings Bilvaruhus AB Rönögatan 12 58278 Linköping Sweden Telefon: 0728-333366 | M69: 559266-1465 | N69: Fri frakt -10% på dragen | O69: Håkan | P69: FALSE | Q69: 45089 | S69: Ja | U69: FALSE
A70: Bjuda in i kalendern och även mail eller sms | B70: Manos Bilservice & Lack | C70: Lånebil 250 kr. Vi lägger på detta på priset till kunden. | D70: 1800 kr + moms. Drag och motorvärmare | E70: Vill ha bilen kl 09.00 | F70: Johnny och Sirop (ägare) | G70: Rudu 6 | H70: 56192 | I70: Huskvarna | J70: 0765-607551 | K70: manosservice@gmail.com | L70: =B70&" "&G70&" "&H70&" "&I70&" Telefon: "&J70 -> Manos Bilservice & Lack Rudu 6 56192 Huskvarna Telefon: 0765-607551 | M70: 930130-1934 | N70: Fri frakt -10% på dragen | O70: Håkan | P70: FALSE | Q70: 45196 | S70: Ja | T70: Johnny och Sirup (ägare) | U70: FALSE
A71: Bjuda in i kalendern och även mail | B71: Gästrike Autoservice AB | C71: FALSE | D71: 2400 kr + moms. Drag och motorvärmare Basservice 1995kr AC-service 1995kr Hjulinst 1275 kr Vi har 15% per tillägg som vi drar av på deras montering | E71: Vill ha bilen 08.00 | F71: Henrik | G71: Fredriksrovägen 8 | H71: 81491 | I71: Furuvik | J71: 026-600 832 | K71: revtechswe@gmail.com | L71: =B71&" "&G71&" "&H71&" "&I71&" Telefon: "&J71 -> Gästrike Autoservice AB Fredriksrovägen 8 81491 Furuvik Telefon: 026-600 832 | N71: Fri frakt -10% på dragen | O71: Håkan | P71: FALSE | Q71: 46058 | R71: """""""Nöjd med samarbetet, har lagomt att göra i verkstaden - boka ca 1,5 veckor fram """ | S71: Ja | T71: Henrik | U71: FALSE
A72: Bjuda in i kalendern och även mail maila ALLTID från Partner mailen | B72: Imotor | C72: 200kr per dag+bränsle betalas direkt till verkstaden | D72: 2000kr + moms. Drag och motorvärmare | E72: Vill ha bilen 08.00 | F72: Serbaz | G72: Tagenevägen 14A | H72: 42259 | I72: Hisings backa | J72: 010-1676866 0707967230 0700 686766 | K72: service@imotor.se | L72: =B72&" "&G72&" "&H72&" "&I72&" Telefon: "&J72 -> Imotor Tagenevägen 14A 42259 Hisings backa Telefon: 010-1676866 0707967230 0700 686766 | M72: 559300-0887 | N72: Fri frakt -10% på dragen | O72: Håkan | P72: FALSE | Q72: 45358 | S72: Ja | U72: FALSE
A73: Bjuda in i kalendern och även mail | B73: Daniels Bilverkstad | C73: TRUE | D73: 2200 kr exkl moms | E73: Vill ha bilen 08.00 | F73: Daniel | G73: Lindaregatan 13 | H73: 25475 | I73: Ödåkra | J73: 070-4301541 | K73: daniels.bilverkstad@gmail.com | L73: =B73&" "&G73&" "&H73&" "&I73&" Telefon: "&J73 -> Daniels Bilverkstad Lindaregatan 13 25475 Ödåkra Telefon: 070-4301541 | N73: Fri frakt -10% på dragen | O73: Håkan | P73: FALSE | Q73: 46058 | R73: """""""""""""""Nöjd med samarbetet, har lagomt att göra i verkstaden - boka ca 1,5 veckor fram höjde till 2200+m """"""" | S73: Ja | T73: Daniel | U73: TRUE
A74: Bjuda in i kalendern och även mail | B74: Point 58 Bildepån (CarOx AB) | C74: FALSE | D74: 1800 kr exkl moms | E74: Öppnar kl 09.00 men man kan lämna bilen innan och lägga nyckel i brevinkast. Helst kl 09.00 | F74: Lasse Direkt 070-3450706 | G74: Smålandsvägen 3 | H74: 611 56 | I74: NYKÖPING | J74: 010-455 04 40 | K74: info@carox.se | L74: Point 58 (CarOx AB) Smålandsvägen 3 611 56 NYKÖPING Telefon 010-455 04 40 | M74: 5566018338 | N74: Fri frakt -10% på dragen | O74: Håkan | P74: FALSE | Q74: 45460 | S74: Ja | T74: Lasse | U74: FALSE
A75: Bjuda in i kalendern och även mail | B75: Samppas Custom Garage AB | C75: TRUE | D75: 2895kr exkl moms för nyare bilar | E75: Vill ha bilen 08.00 | F75: Sammi | G75: Göteborgsvägen 102 | H75: 445 55 | I75: Surte | J75: 0703-795062 | K75: samppascustom@gmail.com | L75: =B75&" "&G75&" "&H75&" "&I75&" Telefon: "&J75 -> Samppas Custom Garage AB Göteborgsvägen 102 445 55 Surte Telefon: 0703-795062 | M75: 559454-6490 | N75: Fri frakt -10% på dragen | O75: Håkan | P75: FALSE | Q75: 45477 | S75: Ja | U75: FALSE
A76: --- | B76: Aotoexperten Nödinge | C76: TRUE | D76: 2000 kr exkl moms 2895kr exkl moms för nyare bilar | E76: Vill ha bilen 08.00 | F76: Sammi | G76: Nödingevägen 2 | H76: 449 31 | I76: Nödinge | J76: 0703-795062 Martin 076 3931360 | K76: samppascustom@gmail.com | L76: =B76&" "&G76&" "&H76&" "&I76&" Telefon: "&J76 -> Aotoexperten Nödinge Nödingevägen 2 449 31 Nödinge Telefon: 0703-795062 Martin 076 3931360 | N76: Fri frakt -10% på dragen | O76: Håkan | P76: FALSE | S76: Ja | U76: FALSE
A77: Bjuda in i kalendern och även mail | B77: Motor och Bilservice i Dalarna AB | C77: FALSE | D77: 2000+moms drag Motorvärmare+komfort sats 2000+moms Ring honom om bilen är nyare än 2021 om han kan ta åt sig. | F77: Yasir | G77: Mästargatan 2 | H77: 78171 | I77: Borlänge | J77: 076 3903110 | K77: info@motorbilservice.se | L77: =B77&" "&G77&" "&H77&" "&I77&" Telefon: "&J77 -> Motor och Bilservice i Dalarna AB Mästargatan 2 78171 Borlänge Telefon: 076 3903110 | M77: 559222-3183 | N77: Fri frakt -10% på dragen | O77: Håkan | P77: FALSE | Q77: 45674 | R77: 22 och nyare bilar ringer vi och kollar om han klarar av att göra | S77: Ja | T77: Yasir | U77: FALSE
A78: Bjuda in i kalendern och även mail | B78: DHS Bilservice AB | C78: FALSE | D78: drag 7pol 2500+m. 13 pol och bilspec 4000+m | E78: Öppnar kl 09:00 | F78: Stephan | G78: Hejargränd 2 | H78: 721 33 | I78: Västerås | J78: 021-35 35 58 | K78: stephan@dhsbil.se | L78: =B78&" "&G78&" "&H78&" "&I78&" Telefon: "&J78 -> DHS Bilservice AB Hejargränd 2 721 33 Västerås Telefon: 021-35 35 58 | M78: 556637-0960 | N78: Fri frakt -10% på dragen | O78: Håkan | P78: FALSE | Q78: 45741 | S78: Ja | T78: Stephan | U78: FALSE
A79: Bjuda in i kalendern och även mail | B79: Autoval I Sundsvall | C79: TRUE | D79: Drag 3000+moms Motorvärmare 2500+moms | E79: Öppnar kl 07:00 | F79: Mattias | G79: Östermovägen 48 | H79: 854 62 | I79: Sundsvall | J79: 060 15 46 10 | K79: mattias.lindstrom@autoval.se Efakt.5565286548@cogidocs.net | L79: =B79&" "&G79&" "&H79&" "&I79&" Telefon: "&J79 -> Autoval I Sundsvall Östermovägen 48 854 62 Sundsvall Telefon: 060 15 46 10 | M79: 556528-6548 | N79: Fri frakt -10% på dragen | O79: Håkan | P79: FALSE | Q79: 45786 | S79: Ja | T79: Mattias | U79: FALSE
A80: Bjuda in i kalendern och även mail | B80: Ferro autocar | C80: FALSE | D80: Drag 2500 + moms | E80: Öppnar kl 08:00 | F80: Feramez Askeri | G80: Fagerstagatan 9 | H80: 163 53 | I80: Lunda | J80: 073 736 30 69 | K80: kia.faramarz.a@gmail.com | L80: =B80&" "&G80&" "&H80&" "&I80&" Telefon: "&J80 -> Ferro autocar Fagerstagatan 9 163 53 Lunda Telefon: 073 736 30 69 | M80: 650321-4436 | N80: Fri frakt -10% på dragen | O80: Håkan | P80: FALSE | S80: Ja | T80: Feramez Askeri | U80: FALSE
A81: mail | B81: Fordonslogistik sverige AB | C81: TRUE | D81: 3000 + moms | E81: Öppnar kl 08:00 | F81: Joakim | G81: Västermalmsvägen 5 | H81: 791 77 | I81: Falun | J81: 023 22888 070 0262250 | K81: Info@fordonslogistik.se | L81: =B81&" "&G81&" "&H81&" "&I81&" Telefon: "&J81 -> Fordonslogistik sverige AB Västermalmsvägen 5 791 77 Falun Telefon: 023 22888 070 0262250 | M81: 559235-7320 | N81: Fri frakt -10% på dragen | O81: Håkan | P81: FALSE | Q81: 46058 | R81: Nöjd med samarbetet, har lagomt att göra i verkstaden - boka ca 1,5 veckor fram | S81: Ja | T81: Joakim | U81: FALSE
A82: Bjuda in i kalendern och även mail | B82: Bilverkstadcenter i Jönköping AB | C82: FALSE | D82: 2000+m pragramering 1250+m motorvärmare 2000+m | E82: Öppnar kl 08:00-18.00 | F82: Samer | G82: Grossistgatan 3 | H82: 55302 | I82: Jönköping | J82: 036 - 18 61 09 070 - 2858169 | K82: bilverkstadcenter@gmail.com | L82: =B82&" "&G82&" "&H82&" "&I82&" Telefon: "&J82 -> Bilverkstadcenter i Jönköping AB Grossistgatan 3 55302 Jönköping Telefon: 036 - 18 61 09 070 - 2858169 | M82: 559107-3662 | N82: Fri frakt -10% på dragen | O82: Håkan | P82: FALSE | Q82: 46059 | R82: Nöjd med samarbetet, har lagomt att göra i verkstaden - boka ca 1,5 veckor fram | S82: Ja | T82: Samer | U82: FALSE
A83: mail + ring | B83: OKQ8 Vikingstad verkstad | C83: TRUE | D83: 2500 + moms | E83: å | F83: Baktiyar Gulahmadov | G83: Åstorpsgatan 2 | H83: 583 72 | I83: Vikingstad | J83: 0701445444 0765774107 privat | K83: bggryningbil2023@gmail.com | L83: =B83&" "&G83&" "&H83&" "&I83&" Telefon: "&J83 -> OKQ8 Vikingstad verkstad Åstorpsgatan 2 583 72 Vikingstad Telefon: 0701445444 0765774107 privat | N83: Fri frakt -10% på dragen | O83: Håkan | P83: FALSE | S83: Ja | U83: FALSE
A84: Kalender | B84: TB-CJ Industriradio i Mjölby Aktiebolag | C84: FALSE | D84: 2000kr + moms | E84: Öppnar kl 08:00 | F84: Tobias | G84: Huljegatan 11, | H84: 595 94 | I84: Mjölby | J84: 0730435435 0814218400 | K84: info@tbcj.se | L84: =B84&" "&G84&" "&H84&" "&I84&" Telefon: "&J84 -> TB-CJ Industriradio i Mjölby Aktiebolag Huljegatan 11, 595 94 Mjölby Telefon: 0730435435 0814218400 | M84: 556369-1814 | N84: Fri frakt -10% på dragen | O84: Håkan | P84: FALSE | S84: Ja | T84: Abbos | U84: FALSE
A85: mail/Ring | B85: RH BILMEK | C85: TRUE | D85: 3000+moms Montera endast specifika elsatser | E85: Öppnar 07,00-17,00 | F85: Daniel | G85: Vasaloppsvägen 228 | H85: 792 94 | I85: Mora | J85: 0250-310 22 | K85: info@rhbilmek.se | L85: =B85&" "&G85&" "&H85&" "&I85&" Telefon: "&J85 -> RH BILMEK Vasaloppsvägen 228 792 94 Mora Telefon: 0250-310 22 | M85: 559418-7394 | N85: Fri frakt -10% på dragen | O85: Håkan | P85: FALSE | Q85: 45911 | S85: Ja | T85: Daniel | U85: FALSE | X85: 46056 | Y85: Sommarstängt 29,30,31
A86: Maila/Ring | B86: Karlskrona bilmekaniska AB | C86: TRUE | D86: Ring | E86: 07:00 - 17:00 | F86: Nick | G86: Ronnebyvägen 5 | H86: 371 45 | I86: Karlskrona | J86: 0455-38 31 30 | K86: skonstavik@mekonomenbilverkstad.se | L86: =B86&" "&G86&" "&H86&" "&I86&" Telefon: "&J86 -> Karlskrona bilmekaniska AB Ronnebyvägen 5 371 45 Karlskrona Telefon: 0455-38 31 30 | N86: Fri frakt -10% på dragen | O86: Håkan | P86: FALSE | Q86: 45917 | S86: Ja | U86: FALSE
A87: Maila/Ring | B87: Meca/Alvar Jacobsson AB | C87: TRUE | D87: 4174 ink moms | E87: 07:00 – 16:00 | G87: Jordbrovägen 6 | H87: 668 32 | I87: Ed | J87: 0534-10442 | K87: verkstad@ajacobsson.se | L87: =B87&" "&G87&" "&H87&" "&I87&" Telefon: "&J87 -> Meca/Alvar Jacobsson AB Jordbrovägen 6 668 32 Ed Telefon: 0534-10442 | M87: 556156-4658 | N87: Fri frakt -10% på dragen | O87: Håkan | P87: FALSE | Q87: 45917 | S87: Ja | U87: FALSE
A88: Maila/Ring vill bli inbjuden i vår mail? | B88: Speedy /Proauto bilverkstad Gävle | C88: FALSE | D88: 3800+moms Motvärm 3000+moms | E88: 08:00 - 17:00 | F88: Morhaf Tarcha | G88: Kryddstigen 33 | H88: 802 92 | I88: Gävle | J88: 026-280 59 79 | K88: info@hjulteam.se | L88: =B88&" "&G88&" "&H88&" "&I88&" Telefon: "&J88 -> Speedy /Proauto bilverkstad Gävle Kryddstigen 33 802 92 Gävle Telefon: 026-280 59 79 | M88: 559515-4294 | N88: Fri frakt -10% på dragen | O88: Håkan | P88: FALSE | Q88: 45916 | S88: Ja | U88: FALSE
A89: Ring/ Maila | B89: Carpros Verkstad AB | C89: TRUE | D89: 3000+m | E89: 08:00-17:00 | F89: Christina | G89: Karlsbogårdsgatan 7 | H89: 42537 | I89: Hisings kärra | J89: 031-876100 0735001378 | K89: christina@carpros.se | L89: =B89&" "&G89&" "&H89&" "&I89&" Telefon: "&J89 -> Carpros Verkstad AB Karlsbogårdsgatan 7 42537 Hisings kärra Telefon: 031-876100 0735001378 | M89: 559178-0373 | N89: Fri frakt -10% på dragen | O89: Håkan | P89: FALSE | Q89: 2025 -09-24 | S89: Ja | U89: FALSE
A90: Ring/ Maila | B90: Mobil & Marin montage Sverige AB | C90: TRUE | D90: 2500+moms | E90: 08:00-17:00 | G90: GULLBERNAVÄGEN 20 | H90: 371 47 | I90: Karlskrona | J90: 0708-39 00 80 | K90: lasse@mobilmontage.com | L90: =B90&" "&G90&" "&H90&" "&I90&" Telefon: "&J90 -> Mobil & Marin montage Sverige AB GULLBERNAVÄGEN 20 371 47 Karlskrona Telefon: 0708-39 00 80 | M90: 556971-6979 | N90: Fri frakt -10% på dragen | O90: Håkan | P90: FALSE | Q90: 45937 | S90: Ja | U90: FALSE
A91: Ring/ Maila | B91: Speedy Bilservice Älta | C91: TRUE | D91: 2000+ moms | E91: Måndag: 07:30 – 17:00 Fredag: 07:30 -- 15:00 | F91: Peo Daniel | G91: Grustagsvägen 6 | H91: 138 40 | I91: Älta | J91: 08-410 300 38 | K91: bilverkstan@outlook.com | L91: =B91&" "&G91&" "&H91&" "&I91&" Telefon: "&J91 -> Speedy Bilservice Älta Grustagsvägen 6 138 40 Älta Telefon: 08-410 300 38 | M91: 559213-7623 | N91: Fri frakt -10% på dragen | O91: Håkan | P91: FALSE | Q91: 45940 | S91: Ja | T91: Daniel och Peo | U91: FALSE
A92: Ring/ Maila | B92: Njutångers Bil & Allservice AB | C92: FALSE | D92: 2995 kr + moms | E92: 08:00-18:00 | F92: Lars | G92: Barnängsvägen 10 | H92: 82592 | I92: Njutånger | J92: 073-8177448 | K92: njutangersbil@gmail.com | L92: =B92&" "&G92&" "&H92&" "&I92&" Telefon: "&J92 -> Njutångers Bil & Allservice AB Barnängsvägen 10 82592 Njutånger Telefon: 073-8177448 | N92: Fri frakt -10% på dragen | O92: Håkan | P92: FALSE | S92: Ja | U92: FALSE
A93: Ring /Maila | B93: ES Bilservice AB | C93: TRUE | D93: 2700 + moms ej elbilar | E93: 08:00-17:00 | F93: Emil | G93: Fabriksgatan 9 | H93: 775 54 | I93: Krylbo | J93: 079-351 01 22 | K93: info@esbilservice.se | L93: =B93&" "&G93&" "&H93&" "&I93&" Telefon: "&J93 -> ES Bilservice AB Fabriksgatan 9 775 54 Krylbo Telefon: 079-351 01 22 | M93: 559424-3015 | N93: Fri frakt -10% på dragen | O93: Håkan | P93: FALSE | Q93: 45972 | S93: Ja | U93: FALSE
A94: Ring | B94: Auto-David Bilvård & Bilverkstad AB | C94: FALSE | D94: Ring | F94: David | G94: Göteborgsvägen 7 | H94: 443 30 | I94: Lerum | J94: 076-2827279 | K94: mokdad79@yahoo.se | L94: =B94&" "&G94&" "&H94&" "&I94&" Telefon: "&J94 -> Auto-David Bilvård & Bilverkstad AB Göteborgsvägen 7 443 30 Lerum Telefon: 076-2827279 | M94: 559217-6977 | N94: Fri frakt -10% på dragen | O94: Håkan | P94: FALSE | Q94: 45979 | S94: Ja | U94: FALSE
A95: Ring | B95: R-Sport Avesta Meca | C95: FALSE | D95: Ring,maila | E95: 07.00-16.00 | F95: Lars | G95: Högboleden 26, | H95: 774 63 | I95: Avesta | J95: 022 65 16 00 | K95: lars.nilsson@mecabilservice.se | L95: =B95&" "&G95&" "&H95&" "&I95&" Telefon: "&J95 -> R-Sport Avesta Meca Högboleden 26, 774 63 Avesta Telefon: 022 65 16 00 | N95: Fri frakt -10% på dragen | O95: Håkan | P95: FALSE | S95: Ja | U95: FALSE
A96: Bjuda in i kalendern och även mail | B96: BNM Bilverkstad AB | C96: FALSE | D96: 2800kr exkl moms Drag och motorvärmare | E96: Vill ha bilen kl 08.00 | F96: Benon | G96: Stångjärnsgatan 7 | H96: 70363 | I96: Örebro | J96: 0723 934000 | K96: holmen@mekopartner.se | L96: =B96&" "&G96&" "&H96&" "&I96&" Telefon: "&J96 -> BNM Bilverkstad AB Stångjärnsgatan 7 70363 Örebro Telefon: 0723 934000 | M96: 559553-9502 | N96: Fri frakt -10% på dragen | O96: Håkan | P96: FALSE | Q96: 46056 | R96: Förhandlade priser feb 26, nöjd med samarbetet | S96: Ja | U96: FALSE
A97: Ring | B97: Aktiebolaget Burträsk Gummiverkstad | C97: FALSE | E97: 07:30 - 16:30 Fre 07:00 - 16:30 | F97: Erik | G97: Sundbrogatan 25, | H97: 937 31 | I97: Burträsk | J97: 0914 10106 | K97: gummi@burtrask.com | L97: =B97&" "&G97&" "&H97&" "&I97&" Telefon: "&J97 -> Aktiebolaget Burträsk Gummiverkstad Sundbrogatan 25, 937 31 Burträsk Telefon: 0914 10106 | N97: Fri frakt -10% på dragen | O97: Håkan | P97: FALSE | S97: Ja | U97: FALSE
A98: Ring maila | B98: Mekonomen AC & Däckcenter i Rättvik AB | C98: TRUE | E98: 07:00-16:30 Fredag 07:00 - 14:00 | F98: Björn | G98: Filarvägen 11 | H98: 795 32 | I98: Rättvik | J98: 0248-13 000 | K98: bjorn@acdackcenter.se | L98: =B98&" "&G98&" "&H98&" "&I98&" Telefon: "&J98 -> Mekonomen AC & Däckcenter i Rättvik AB Filarvägen 11 795 32 Rättvik Telefon: 0248-13 000 | M98: 559078-8435 | N98: Fri frakt -10% på dragen | O98: Håkan | P98: FALSE | S98: Ja | U98: FALSE
A99: Ring /Maila | B99: Mullsjö Autocenter AB | C99: FALSE | D99: 2400 +moms | F99: Mike | G99: Garverigatan 4 | H99: 565 33 | I99: Mullsjö | J99: 0761-990079 | K99: Info@mullsjoautocenter.se | L99: =B99&" "&G99&" "&H99&" "&I99&" Telefon: "&J99 -> Mullsjö Autocenter AB Garverigatan 4 565 33 Mullsjö Telefon: 0761-990079 | N99: Fri frakt -10% på dragen | O99: Håkan | P99: FALSE | S99: Ja | U99: FALSE
A100: Ring /maila | B100: Hille Bensin och Service | C100: TRUE | F100: Thomas Gyllenskepp | G100: Hillevägen 38 | H100: 80469 | I100: Gävle | J100: 0702346808 | K100: hille@mecaverkstad.se | L100: =B100&" "&G100&" "&H100&" "&I100&" Telefon: "&J100 -> Hille Bensin och Service Hillevägen 38 80469 Gävle Telefon: 0702346808 | N100: Fri frakt -10% på dragen | O100: Håkan | P100: FALSE | S100: Ja | U100: FALSE
...

Sheet Nykontakt
A1: Datum | B1: Verkstad | C1: Kommentar | D1: Kontaktperson | E1: Adress | F1: Postnr | G1: Ort | H1: Telefonnummer | I1: E-post | K1: Org-nr | L1: Övrigt | M1: Ansvarig hos B&J (förslag?) | N1: Skrift. Avtal? | O1: Datum | P1: Aktuell info, lediga tider mm? | Q1: Aktiv | R1: Verkstadskontakter 1 | S1: Verkstadskontakter 2 | T1: Verkstadskontakter 3 | U1: Verkstadskontakter 4
A2: 2026-01-20 2026-02-03 | B2: Kennys Bilverkstad Vemdalen | C2: samtal och mail återkommer om mont pris
A3: 2026-01-21 2026-02-03 | B3: Mekonomen Årjäng | C3: samtal och mail återkommer om mont pris
A4: 46043 | B4: Berners Person - och Transportbilar | C4: mailat
A5: 46043 | B5: Bilhuset Småland AB | C5: mailat
A6: 46043 | B6: Fryksdalens Bil AB | C6: Mailat
A7: 46043 | B7: Autovision sverige ab | C7: Mailat
A8: 46043 | B8: Bromma bilanalys & Bilverkstad AB | C8: Mailat
A9: 46043 | B9: Bil Brodd AB | C9: Mailat
A10: 46043 | B10: MCS Sverige AB / Dunhoffbil | C10: Mailat
A11: 46043 | B11: Ljusdals Bilverkstad AB | C11: Mailat
A12: 46043 | B12: Roberts Verkstad | C12: Mailat
A13: 46043 | B13: Dannes AutoMotor AB | C13: Mailat
A14: 46043 | B14: Vinsta Bilservice AB | C14: Mailat
A15: 46043 | B15: Via Bilservice AB | C15: Mailat
... A24: 46051 | B24: Fastmec AB meka Ludvika | C24: telefon,mail återkommer om pris
A25: 46056 | B25: Williams Garage | C25: Mailat om prisfråga | D25: Sanel
A26: 46056 | B26: BNM Bilverkstad AB | C26: Sänkte priset till 2800+m | D26: Benon
A27: 46056 | B27: PS Motorsport 070-555 14 46 | C27: Mailat | D27: Patrik
A28: 46070 | B28: Enarsson bil och plåt | C28: telefon,mail
A29: 46070 | B29: Total bil i Falun | C29: Mailat ,besökt
A30: 46070 | B30: Salabilteknik Q8 | C30: Besökt | D30: Patrik
A31: 46070 | B31: Bilkompaniet Sala Volvo | C31: Besökt | D31: Jan
A32: 46070 | B32: Nordiska Bilkompaniet AB | C32: Besökt partner | D32: Hozan
A33: 46070 | B33: Norrmans bil Sala | C33: Besökt
A34: 46070 | B34: Sala bilservice | C34: Besökt
A35: 46070 | B35: AD Butik i Sala | C35: Besökt
A36: 46070 | B36: Mekonomen Butik Sala | C36: Besökt
A37: 46070 | B37: Möller bil Sala VW | C37: Besökt
A38: 46071 | B38: PA Bil & Motor Karlskoga | C38: Ringt/Mailat | D38: Sanna | H38: 0586-531 70
A39: 46072 | B39: Plåt & Mek Fagersta AB | C39: Besökt och blir partnerverkstad | D39: Alexandar | H39: 0223 - 211 11
A40: 46072 | B40: Autocenter i bergslagen AB BDS | C40: besökt | H40: 0223 14280
A41: 46072 | B41: Bilcity i Fagersta Kia | C41: besökt | D41: Stefan | H41: 0223 16170
A42: 46072 | B42: Motorforum i Fagersta | C42: besökt
A43: 46072 | B43: Luddes Hyresmaskiner | C43: besökt smsat 070 3195000 | D43: Ludde | H43: 0223 10900
A44: 46079 | B44: idrefordonsservice | C44: Besökt och blir partnerverkstad | H44: 073-061 62 91
A45: 46083 | B45: NK MEK & TUNING AB | C45: telefon /mail partner | H45: 0652-108 88 | K45: 5594077306
A46: 46083 | B46: Fordonsservice Uppland AB | C46: Telefon/mail Partner | H46: 073 767 03 11
A47: 46084 | B47: Motorbolaget i Växjö AB störst på a-traktorer | C47: Telefon /mail | H47: 0470 - 131 80
A48: 46085 | B48: Smista bil mekonomen | C48: Telefon /mail | H48: 08 55036550
A49: 46086 | B49: Autolagret i Sverige AB | C49: Mail
A50: 46086 | B50: Stockholms Bilmäklare AB | C50: Mail
A51: 46086 | B51: Melinas Bilar AB | C51: Mail | H51: 073-3580954 | I51: info@melinasbilar.se
A52: 46092 | B52: Highway Performance AB | C52: telefon , kan hjälpa om Åhus inte kan | D52: Mattias | E52: Nyängsgatan 3 | F52: 295 39 | G52: Bromölla | H52: 0456-25510 | I52: skoglund.mattias@gmail.com
A53: 46094 | B53: autohero | C53: telefon | H53: 08 12411420
A54: 46164 | B54: Electro Center i Stenungsund AB - Bosch Car Service | D54: pris 4658 ink | E54: Hantverkaregatan 22, 444 32 Stenungsund | H54: 0303-840 15 | I54: info@electrocenter.se
A55: 46170 | B55: MESSES BILSERVICE AB | C55: Ville bli partner | E55: Dalvägen 64 | F55: 147 32 | G55: Tumba | H55: 707426660 | I55: info@messes.se
A56: 46174 | B56: Autocloud | C56: Telefon | D56: Ismo | E56: Gjutargatan 32 | F56: 781 70 | G56: Borlänge | H56: 0243 226150 | I56: info@autocloud.se
A57: 46055 | B57: Fordonshallen Dalarna AB | C57: Telefon | D57: Robin | E57: Hugo Hedströms väg 6 | G57: Borlänge | H57: 0243-12220 | I57: info@fordonshallendalarna.se
A58: 46055 | B58: Bilbutiken dalarna | C58: Telefon | D58: Jimmy | E58: Tunavägen 291 | F58: 781 73 | G58: Borlänge | H58: 0243-10055 | I58: info@bilbutikendalarna.se
A59: 46176 | B59: LTE Bil AB | C59: Telefon,mail,besök | D59: Elsa | E59: Herrgårdsgatan 28 | G59: Borlänge | H59: 0243-23 00 28 | I59: info@ltebil.se | K59: 556797-0511 | L59: ev partner
A60: 46176 | B60: JMS Sweden AB | C60: Telefon, många a-traktorbyggen verkstadspartner återkommer om pris | D60: Jacob | E60: , Industrigatan 12 | F60: 732 31 | G60: Arboga | H60: 072-569 89 70 | I60: inbox.lev.1690436@arkivplats.se | K60: 559527-5545

Sheet Tilläggstjänster
A1: Förslag tilläggstjäster | B1: Prisförslag mot kund | C1: Fakturerat belopp

Sheet Leverantörer
A1: supplier_number | B1: organisation_number | C1: name | D1: invoice_address | E1: invoice_address2 | F1: invoice_zip_code | G1: invoice_city | H1: invoice_country_code | I1: invoice_country | J1: Aktiv | K1: Bör avtal finnas ? | L1: Avtal
A2: 1 | B2: 5591025852 | C2: Sendify AB | D2: Volrat Thamsgatan 4 | F2: 41260 | G2: Göteborg | H2: SE | I2: Sverige | J2: TRUE | K2: FALSE
A3: 2 | C3: MARTEC Automotive Sp. z o.o. | D3: al. M.B Fatimskiej 16 | F3: 33-100 | G3: Tarnów | H3: PL | I3: Poland | J3: TRUE | K3: FALSE
A4: 3 | B4: 6827593036 | C4: Steinhof | D4: Przemysłowa 27A | F4: 33-100 | G4: Tarnow | H4: PL | I4: Poland | J4: TRUE | K4: FALSE
A5: 4 | B5: 30687388 | C5: Bertelshofer GmbH | D5: Glockenbecherstraße 6 | F5: 86706 | G5: Weichering | H5: DE | I5: Germany | J5: FALSE | K5: FALSE
A6: 5 | B6: 5561094532 | C6: UPS AB | D6: Elektronikhöjden 6 | F6: 17543 | G6: JÄRFÄLLA | H6: SE | I6: Sverige | J6: FALSE | K6: FALSE
A7: 6 | C7: Folksam | D7: Box 53300 | F7: 40016 | G7: Göteborg | H7: SE | I7: Sverige | J7: FALSE | K7: FALSE
A8: 7 | B8: 5568170707 | C8: Reservdelshörnan i Sisjön AB | D8: Sörbyvägen 29 | F8: 47172 | G8: HJÄLTEBY | H8: SE | I8: Sverige | J8: FALSE | K8: FALSE
A9: 8 | B9: 5564300142 | C9: Telia Sverige | F9: 12386 | G9: FARSTA | H9: SE | I9: Sverige | J9: FALSE | K9: FALSE
A10: 9 | B10: 5562675164 | C10: TELE2 FÖRETAG | D10: Box 62 | F10: 16494 | G10: KISTA | H10: SE | I10: Sverige | J10: TRUE | K10: FALSE
A11: 10 | B11: 5569462129 | C11: Tistings Träförädling AB | D11: Sågbacken 6 | F11: 69450 | G11: VRETSTORP | H11: SE | I11: Sverige | J11: FALSE | K11: FALSE
A12: 11 | B12: 5568163637 | C12: HA Transport AB | D12: Växthusvägen 3 | F12: 45175 | G12: UDDEVALLA | H12: SE | I12: Sverige | J12: FALSE | K12: FALSE
A13: 12 | B13: 5566748066 | C13: Bilcentrum i Umeå AB | D13: Norra Obbolavägen 114 | F13: 90422 | G13: UMEÅ | H13: SE | I13: Sverige | J13: TRUE | K13: FALSE
A14: 13 | B14: 9697382480 | C14: Spånga Bensin & Service Handelsbolag | D14: Täbylundsvägen 63 | F14: 16347 | G14: SPÅNGA | H14: SE | I14: Sverige | J14: FALSE | K14: FALSE
A15: 14 | B15: 5567343040 | C15: Monoflex Nordic AB | D15: Box 14 | F15: 73425 | G15: HALLSTAHAMMAR | H15: SE | I15: Sverige | J15: FALSE | K15: FALSE
A16: 15 | B16: 5567884415 | C16: Äpplekullens Bil & Däckservice | D16: Ekenleden 1 | F16: 42836 | G16: KÅLLERED | H16: SE | I16: Sverige | J16: TRUE | K16: FALSE
A17: 16 | B17: 6708215055 | C17: VTL Teknik | D17: Södra Orredsvägen 2 | F17: 43974 | G17: Fjärås | J17: FALSE | K17: FALSE
A18: 17 | B18: 5567614960 | C18: Nets Sweden AB | D18: Box 778 | F18: 13124 | G18: NACKA | H18: SE | I18: Sverige | J18: TRUE | K18: FALSE
A19: 18 | B19: 5020077862 | C19: Svenska Handelsbanken AB | F19: 10670 | G19: STOCKHOLM | H19: SE | I19: Sverige | J19: FALSE | K19: FALSE
A20: 19 | B20: 5566103429 | C20: Blocket / Svea Ekonomi | F20: 16981 | G20: Stockholm | J20: FALSE | K20: FALSE
A21: 20 | B21: 5164074709 | C21: DIBS Payment Services AB | D21: Box 165 | F21: 10123 | G21: STOCKHOLM | H21: SE | I21: Sverige | J21: FALSE | K21: FALSE
A22: 21 | B22: 8024657119 | C22: Radio 88 | D22: Royne Nilsson, Box 140 | F22: 43908 | G22: FRILLESÅS | H22: SE | I22: Sverige | J22: FALSE | K22: FALSE
A23: 22 | B23: 2021006099 | C23: Transportstyrelsen | F23: 70195 | G23: Örebro | J23: FALSE | K23: FALSE
A24: 23 | B24: 5565185989 | C24: Svensk Betalningskontroll AB | D24: Box 9085 | F24: 40092 | G24: GÖTEBORG | H24: SE | I24: Sverige | J24: FALSE | K24: FALSE
A25: 24 | C25: Watling Engineers LTD. | D25: 88 Park Street Village | F25: AL2 2LR | G25: Herts | H25: GB | I25: United Kingdom | J25: FALSE | K25: FALSE
A26: 25 | B26: 5565861472 | C26: Textalk AB | D26: Krokslätts Fabriker 12 | F26: 43137 | G26: MÖLNDAL | H26: SE | I26: Sverige | J26: FALSE | K26: FALSE
A27: 26 | B27: 5566307806 | C27: City Network Hosting AB | D27: Borgmästaregatan 18 | F27: 37134 | G27: KARLSKRONA | H27: SE | I27: Sverige | J27: FALSE | K27: FALSE
A28: 27 | B28: 5569889743 | C28: Fordonsteknik Jönköping AB | D28: Herkulesvägen 16 | F28: 55303 | G28: JÖNKÖPING | H28: SE | I28: Sverige | J28: FALSE | K28: FALSE
A29: 28 | B29: 5564696291 | C29: Fortnox Aktiebolag | D29: Box 427 | F29: 35106 | G29: VÄXJÖ | H29: SE | I29: Sverige | J29: TRUE | K29: FALSE
A30: 29 | B30: 5702133215 | C30: Pettsons Bilservice | D30: VÄSTERHEJDE GAMLA KYRKVÄGEN 8 | F30: 62261 | G30: VISBY | H30: SE | I30: Sverige | J30: FALSE | K30: FALSE
A31: 30 | B31: 9112031019 | C31: Berglunds Montage | D31: Hagagatan 6 F | F31: 79430 | G31: Orsa | H31: SE | I31: Sverige | J31: FALSE | K31: FALSE
A32: 31 | B32: 5567977888 | C32: Möllerstrand Service AB | D32: Vidkärrsgatan 28 | F32: 41672 | G32: GÖTEBORG | H32: SE | I32: Sverige | J32: FALSE | K32: FALSE
A33: 32 | B33: 5569340424 | C33: Modifinder AB | D33: Stortorget 27 | F33: 21134 | G33: MALMÖ | H33: SE | I33: Sverige | J33: FALSE | K33: FALSE
A34: 33 | B34: 5590054523 | C34: Motornavet Göteborg AB | D34: Varholmsgatan 12 | F34: 41474 | G34: GÖTEBORG | H34: SE | I34: Sverige | J34: FALSE | K34: FALSE
A35: 34 | B35: 5164029257 | C35: FedEx | D35: Box 94 | F35: 19045 | G35: STOCKHOLM-ARLANDA | H35: SE | I35: Sverige | J35: FALSE | K35: FALSE
A36: 35 | B36: 5590429386 | C36: Supreme Autoservice i Malmö AB | D36: Cypressvägen 10 | F36: 21363 | G36: MALMÖ | H36: SE | I36: Sverige | J36: TRUE | K36: FALSE
A37: 36 | B37: 5564306578 | C37: EM Motor AB | D37: Karl Johansg. 146 | F37: 41451 | G37: GÖTEBORG | H37: SE | I37: Sverige | J37: FALSE | K37: FALSE
... A41: 40 | B41: 5566081716 | C41: Unifaun AB | D41: Box 2326 | F41: 40315 | G41: GÖTEBORG | H41: SE | I41: Sverige | J41: FALSE | K41: FALSE
A42: 41 | B42: 110/251/00567 | C42: M&L Automobile | D42: Delitzscher Str. 51 | F42: D-06112 | G42: Halle | H42: DE | I42: Germany | J42: FALSE | K42: FALSE
A43: 42 | C43: Felparkering Transportstyrelsen | J43: FALSE | K43: FALSE
A44: 43 | B44: 5561181040 | C44: Lennart Rönn Bil Aktiebolag | D44: Box 46 | F44: 13521 | G44: TYRESÖ | H44: SE | I44: Sverige | J44: FALSE | K44: FALSE
A45: 44 | B45: 5568871999 | C45: Mekonomen Högsbo AB | D45: Box 19542 | F45: 10432 | G45: STOCKHOLM | H45: SE | I45: Sverige | J45: TRUE | K45: FALSE
A46: 45 | B46: 5568399231 | C46: Sandgren Electronics AB | D46: box 12271 | F46: 10227 | G46: STOCKHOLM | H46: SE | I46: Sverige | J46: FALSE | K46: FALSE
A47: 46 | B47: 9168502780 | C47: Bocaj & Partner Förvaltning | D47: KNIPPLAGATAN 10 | F47: 41474 | G47: GÖTEBORG | H47: SE | I47: Sverige | J47: FALSE | K47: FALSE
A48: 47 | B48: 8504243992 | C48: Mr Tuning | D48: Box 106 | F48: 24322 | G48: Höör | H48: SE | I48: Sverige | J48: FALSE | K48: FALSE
A49: 48 | B49: 5562332592 | C49: Ansta Bildemont AB | D49: Ansta | F49: 72594 | G49: VÄSTERÅS | H49: SE | I49: Sverige | J49: FALSE | K49: FALSE
A50: 49 | B50: 5567880900 | C50: Preventia Finans AB | D50: Box 24022 | F50: 40022 | G50: GÖTEBORG | H50: SE | I50: Sverige | J50: FALSE | K50: FALSE
A51: 50 | B51: 5560530841 | C51: Handelsbanken Finans / Ecster | F51: 10635 | G51: STOCKHOLM | H51: SE | I51: Sverige | J51: FALSE | K51: FALSE
A52: 51 | B52: 5564763562 | C52: Svensk Adressändring AB | D52: Drottninggatan 82,1tr | F52: 11136 | G52: STOCKHOLM | H52: SE | I52: Sverige | J52: FALSE | K52: FALSE
A53: 52 | B53: 5565724696 | C53: GÖTEBORG ENERGI DIN EL AB | D53: Box 53 | F53: 40120 | G53: GÖTEBORG | H53: SE | I53: Sverige | J53: TRUE | K53: FALSE
A54: 53 | B54: 5566784624 | C54: Conrad Elektronik Norden AB | D54: Skeppsgatan 19 6tr | F54: 21111 | G54: MALMÖ | H54: SE | I54: Sverige | J54: FALSE | K54: FALSE
A55: 54 | B55: 5567115695 | C55: PostNord Sverige AB | D55: Affärsområde Mail & Communications | F55: 10500 | G55: STOCKHOLM | H55: SE | I55: Sverige | J55: TRUE | K55: FALSE
A56: 55 | B56: 5563626794 | C56: GÖTEBORG ENERGI AB | D56: Box 53 | F56: 40120 | G56: GÖTEBORG | H56: SE | I56: Sverige | J56: FALSE | K56: FALSE
A57: 56 | B57: 2021006099 | C57: Transportstyrelsen Fordonsskatt | J57: FALSE | K57: FALSE
A58: 57 | B58: 5561194878 | C58: Göteborgs stads parkeringsaktiebolag | D58: Box 7174 | F58: 40233 | G58: GÖTEBORG | H58: SE | I58: Sverige | J58: FALSE | K58: FALSE
A59: 58 | B59: 5567293666 | C59: Dentxpress AB | D59: Björkvägen 2 A | F59: 42837 | G59: KÅLLERED | H59: SE | I59: Sverige | J59: FALSE | K59: FALSE
A60: 59 | B60: 5563041283 | C60: Kungsstens Byggvaruhus Aktiebolag | D60: Fotögatan 10 | F60: 41474 | G60: GÖTEBORG | H60: SE | I60: Sverige | J60: FALSE | K60: FALSE
A61: 60 | B61: 5560249558 | C61: Office Depot | D61: Box 3132 | F61: 16903 | G61: SOLNA | H61: SE | I61: Sverige | J61: TRUE | K61: FALSE
A62: 61 | B62: 5591162697 | C62: DRAKÄNGEN BILSERVICE AB | D62: c/o Robert Helen | E62: Attsjö Drakängen 1 | F62: 36593 | G62: FURUBY | H62: SE | I62: Sverige | J62: FALSE | K62: FALSE
A63: 62 | B63: 5568204779 | C63: S-Service Din Bilverkstad AB | D63: Fjärestadsvägen 344 | F63: 26030 | G63: VALLÅKRA | H63: SE | I63: Sverige | J63: FALSE | K63: FALSE
A64: 63 | B64: 5569303471 | C64: Halléns Bilservice AB | D64: Grossistgatan 5 | F64: 55302 | G64: JÖNKÖPING | H64: SE | I64: Sverige | J64: FALSE | K64: FALSE
A65: 64 | B65: 5562102300 | C65: Norre Park Hotel Aktiebolag | D65: Norra vägen 7 | F65: 30231 | G65: HALMSTAD | H65: SE | I65: Sverige | J65: FALSE | K65: FALSE
A66: 65 | B66: 5409111811 | C66: Marholmen Bygg | D66: Marholmsvägen 119 | F66: 43645 | G66: Askim | J66: FALSE | K66: FALSE
A67: 66 | B67: 5562443951 | C67: Skellefteå Kraft | D67: Kanalgatan 71 | F67: 93180 | G67: SKELLEFTEÅ | H67: SE | I67: Sverige | J67: FALSE | K67: FALSE
A68: 67 | C68: UK Umbra Rimorchi | D68: 1417 DAVENPORT HOUSE | E68: 261 Bolton Road | F68: BL8 2NZ | G68: Greater Manchester | H68: GB | I68: United Kingdom | J68: TRUE | K68: FALSE
A69: 68 | B69: 5567887038 | C69: Dannevall Servicecenter AB | D69: Tyra Lundgrens Väg 26 | F69: 13440 | G69: GUSTAVSBERG | H69: SE | I69: Sverige | J69: FALSE | K69: FALSE
A70: 69 | B70: 5566314786 | C70: Adact Revisorer & Konsulter AB | D70: Odinsgatan 11 | F70: 41103 | G70: GÖTEBORG | H70: SE | I70: Sverige | J70: TRUE | K70: FALSE
A71: 70 | B71: 5569106973 | C71: Holmgrens Bil i Göteborg AB | D71: Femvägsskälet 4 | F71: 42150 | G71: VÄSTRA FRÖLUNDA | H71: SE | I71: Sverige | J71: FALSE | K71: FALSE
A72: 71 | B72: 5564732997 | C72: Eklunds Bil Aktiebolag | D72: Smidesgatan 2 | F72: 41707 | G72: GÖTEBORG | H72: SE | I72: Sverige | J72: FALSE | K72: FALSE
A73: 72 | B73: 5562309004 | C73: Dannevall - Avida Finans AB | D73: Box 38101 | F73: 10064 | G73: STOCKHOLM | H73: SE | I73: Sverige | J73: FALSE | K73: FALSE
A74: 73 | B74: 5591591879 | C74: Piteå Bilverkstad AB | D74: Nötögrundsvägen 175 | F74: 94141 | G74: PITEÅ | H74: SE | I74: Sverige | J74: TRUE | K74: FALSE
A75: 74 | B75: 5568200926 | C75: Småföretagarnas Medlemstjänst AB | D75: Box 9076 | F75: 70009 | G75: ÖREBRO | H75: SE | I75: Sverige | J75: FALSE | K75: FALSE
A76: 75 | B76: 5569079543 | C76: Car Care Sthlm AB | D76: Box 2043 | F76: 13502 | G76: TYRESÖ | H76: SE | I76: Sverige | J76: FALSE | K76: FALSE
A77: 76 | B77: 5561849836 | C77: Allt i Skyltar Aktiebolag | D77: Box 8983 | F77: 40274 | G77: GÖTEBORG | H77: SE | I77: Sverige | J77: FALSE | K77: FALSE
A78: 77 | B78: 5567420418 | C78: Mechanum Sverige AB | D78: Benjamins Väg 12 | F78: 43338 | G78: PARTILLE | H78: SE | I78: Sverige | J78: FALSE | K78: FALSE
A79: 78 | B79: 5567807358 | C79: Watt Heating AB | D79: Grävmaskinsvägen 23 | F79: 24138 | G79: ESLÖV | H79: SE | I79: Sverige | J79: FALSE | K79: FALSE
A80: 79 | B80: 5590035308 | C80: Fordonsteknik i Vadstena AB | D80: Pilgrimsvägen 8 | F80: 59231 | G80: VADSTENA | H80: SE | I80: Sverige | J80: FALSE | K80: FALSE
... A83: 82 | B83: 5591731681 | C83: IM Bilservice i Karlstad AB | D83: Nattvindsgatan 9 | F83: 65221 | G83: KARLSTAD | H83: SE | I83: Sverige | J83: FALSE | K83: FALSE
A84: 83 | C84: Micromel | D84: Nowy Olszowiec 72 | F84: 97-217 | G84: Lubochnia | H84: PL | I84: Poland | J84: FALSE | K84: FALSE
A85: 84 | B85: 5569270936 | C85: Speedy Örebro Bilservice AB | D85: Speedy autoserviec, Radiatorvägen 5 | F85: 70227 | G85: ÖREBRO | H85: SE | I85: Sverige | J85: FALSE | K85: FALSE
A86: 85 | C86: Tesat | D86: Ludowa Str. 13 | F86: 51-503 | G86: Wroclaw | H86: PL | I86: Poland | J86: FALSE | K86: FALSE
A87: 86 | B87: 9697457894 | C87: HH Bilservice Handelsbolag | D87: Jättevägen 4 | F87: 17677 | G87: JÄRFÄLLA | H87: SE | I87: Sverige | J87: FALSE | K87: FALSE
A88: 87 | B88: 5564444593 | C88: Butik Inreda 24 AB | D88: Norra Långgatan 16 | F88: 39232 | G88: KALMAR | H88: SE | I88: Sverige | J88: FALSE | K88: FALSE
A89: 88 | B89: 5568110174 | C89: Vool AB | D89: ENERGIGATAN 7 | F89: 43437 | G89: KUNGSBACKA | H89: SE | I89: Sverige | J89: FALSE | K89: FALSE
A90: 89 | B90: 5164060948 | C90: Försäkringsaktiebolaget Skandia | F90: 10655 | G90: STOCKHOLM | H90: SE | I90: Sverige | J90: TRUE | K90: FALSE
A91: 90 | B91: 5020173083 | C91: Skandia Försäkring (publ) | F91: 10655 | G91: STOCKHOLM | H91: SE | I91: Sverige | J91: TRUE | K91: FALSE
A92: 91 | B92: 5565954533 | C92: Upplands bildemontering AB | D92: Möllerswärdsgatan 8 | F92: 75450 | G92: UPPSALA | H92: SE | I92: Sverige | J92: FALSE | K92: FALSE
A93: 92 | B93: 5563396794 | C93: S.S. Bilbehör Aktiebolag | D93: Datavägen 63 | F93: 43632 | G93: ASKIM | H93: SE | I93: Sverige | J93: FALSE | K93: FALSE
A94: 93 | B94: 5568663743 | C94: Motala Bilpartner AB | D94: Vintergatan 4 | F94: 59132 | G94: MOTALA | H94: SE | I94: Sverige | J94: FALSE | K94: FALSE
A95: 94 | B95: 5569634099 | C95: First Vision i Malmö AB | D95: Skomakaregatan 12 | F95: 21134 | G95: MALMÖ | H95: SE | I95: Sverige | J95: FALSE | K95: FALSE
A96: 95 | B96: 5164060948 | C96: Skandia Tjänstegrupp liv | F96: 10655 | G96: STOCKHOLM | H96: SE | I96: Sverige | J96: TRUE | K96: FALSE
A97: 96 | B97: 5566890397 | C97: Loopia Hosting AB | D97: Lindhagensgatan 126 5TR | F97: 11251 | G97: STOCKHOLM | H97: SE | I97: Sverige | J97: TRUE | K97: FALSE
A98: 97 | B98: 5561907329 | C98: AJ Produkter Aktiebolag | F98: 30182 | G98: HALMSTAD | H98: SE | I98: Sverige | J98: TRUE | K98: FALSE
A99: 98 | B99: 5590193487 | C99: Kults Motor AB | D99: Storsjöstråket 13 | F99: 83134 | G99: ÖSTERSUND | H99: SE | I99: Sverige | J99: FALSE | K99: FALSE
A100: 99 | C100: JP China Trade Int´l Co Ltd | D100: 1005 Jincheng Centre | E100: Tongzhou district | F100: 101101 | G100: Beijing | H100: CN | I100: China | J100: FALSE | K100: FALSE
A101: 100 | B101: 5568311095 | C101: Tonerlagret Sverige AB | D101: Ingenjörsgatan 5 | F101: 41119 | G101: GÖTEBORG | H101: SE | I101: Sverige | J101: TRUE | K101: FALSE
A102: 101 | B102: 5563735629 | C102: AK Mobilkonsult Aktiebolag / Ditec | D102: Pumpvägen 1B | F102: 90420 | G102: UMEÅ | H102: SE | I102: Sverige | J102: TRUE | K102: FALSE
A103: 102 | B103: 5591073662 | C103: Bilverkstadcenter i Jönköping AB | D103: Kabelvägen 6 | F103: 55302 | G103: JÖNKÖPING | H103: SE | I103: Sverige | J103: FALSE | K103: FALSE
A104: 103 | B104: 5569898835 | C104: Ulricehamns Auto AB | D104: Karlsnäsvägen 4 | F104: 52337 | G104: ULRICEHAMN | H104: SE | I104: Sverige | J104: FALSE | K104: FALSE
A105: 104 | B105: 9697491752 | C105: DLT Bil & Släp KB | D105: Stenlidsvägen 27 | F105: 44195 | G105: ALINGSÅS | H105: SE | I105: Sverige | J105: FALSE | K105: FALSE
...

Sheet Lager elsatser
A1: No. | B1: Tillverkare | C1: 7-/13-pol | D1: Artikelnummer | E1: Bilmodell | F1: Årsmodell | G1: Övrigt | H1: Ok? | I1: Till Borås | J1: Artikelnummer
A2: 1 | B2: Erich Jaeger | C2: För bilar utan REC box | D2: Kit 721999 | E2: Ford C-Max, Focus | F2: 2010>
A3: 2 | B3: Erich Jaeger | C3: 7-pol | D3: 737452 | E3: Kia Optima Kombi | F3: 2016>
A4: 3 | B4: Brink | C4: 13-Pol | D4: 744184 | E4: Land Rover Discovery 3, sport | H4: OK | I4: Ja | J4: 744184
A5: 4 | B5: Erich Jaeger | C5: 13-Pol | D5: 749178 | E5: Volvo V40 S40 | F5: 36617 | G5: Tagen till usu289
A6: 5 | B6: GM | C6: 13-Pol | E6: Opel Astra Halv och Kombi | F6: 2011?
A7: 6 | B7: Westfalia | C7: 13-Pol | D7: 307400300113 | E7: Ford S-Max, Galaxy Mondeo | F7: 2006> | G7: Tagen till gyx769
A8: 7 | B8: Erich Jaeger | C8: 13-Pol | D8: 737477 | E8: 5008, 3008 | F8: 2016> | G8: OBS- denna elsats är för icke förberedda bilar. /FP
A9: 8 | B9: Erich Jaeger | C9: 7-pol | D9: 737391 | E9: Kia Optima | F9: 2016>
A10: 9 | B10: Erich Jaeger | C10: 13-Pol | D10: 747024 | E10: Kia Optima | F10: 2016>
A11: 10 | B11: Erich Jaeger | C11: 13-Pol | D11: 748704 | E11: Kia Soul | F11: 2009>
A12: 11 | B12: Westfalia | C12: 13-Pol | D12: 36180-16 | E12: Kia Ceed HB Kombi | F12: 2012> | G12: PKJ652
A13: 12 | B13: Westfalia | C13: 7-pol | E13: Kia Ceed halvkombi , Kia Pro Ceed | F13: 2007>
A14: 13 | B14: Westfalia | C14: 13-Pol | E14: Kia Niro Hybrid | F14: 2016.09>2017.10
A15: 14 | B15: Erich Jaeger | C15: 13-Pol | D15: 747113 | E15: 3008,5008 Opel Grandland | F15: 2015>
A16: 15 | B16: Westfalia | C16: 13-Pol | D16: 303451300113 | E16: BMW X5 X6 | F16: fram till årsmodell -11/2013 | G16: Tagen till SPK169
A17: 16 | B17: Erich Jaeger | C17: 13-Pol | D17: 747266 | E17: Kia Ceed | F17: 2018>
A18: 17 | B18: Erich Jaeger | C18: 13-Pol | D18: 747266 | E18: Kia Ceed | F18: 2018> | G18: Till AMU52L
A19: 18 | B19: Erich Jaeger | C19: 13-Pol | D19: 747266 | E19: Kia Ceed | F19: 2018>
A20: 19 | B20: Erich Jaeger | C20: 7-pol | D20: 737559 | E20: Kia Ceed | F20: 2018>
A21: 20 | B21: Erich Jaeger | C21: 7-pol | D21: 737559 | E21: Kia Ceed | F21: 2018> | H21: GWZ48N
A22: 21 | B22: Erich Jaeger | C22: 7-pol | D22: 737109 | E22: Volvo S60, XC60 | H22: skickad till JHB017
A23: 22 | B23: Jaeger | C23: 7-pol | D23: 1226010100 | E23: Volvo 850, V70 mfl | F23: 93-00
A24: 23 | B24: Erich Jaeger | C24: 7-pol | D24: 737403 | E24: Volvo XC90 S90 V90 | F24: 2015>
A25: 24 | B25: Erich Jaeger | C25: 13-pol | D25: 748242 | E25: Audi,Golf,Seat mfl | H25: Ok | I25: Ja | J25: 748242
A26: 25 | B26: ECS | C26: 13-pol | D26: KI-132DX | E26: Kia flera modeller | F26: 2016>
A27: 26 | B27: ECS | C27: 13-pol | D27: KI-132DX | E27: Kia flera modeller | F27: 2016> | H27: ZEM906
A28: 27 | B28: ECS | C28: 13-pol | D28: KI-132DX | E28: Kia flera modeller | F28: 2016>
A29: 28 | B29: Erich Jaeger | C29: 13-pol | D29: 748520 | E29: Mitsubishi Outlander | F29: 2012> | G29: Ligger snart hos Tågaborg. Ev fel på denna elsatsen, ev inte. =) //TC 20/4
A30: 29 | B30: ECS | C30: 13-pol | D30: BW-028-D1 | E30: BMW, massa modeller | F30: 2013>
A31: 30 | B31: ECS | C31: 13-pol | D31: BW-028-D1 | E31: BMW, massa modeller | F31: 2013>
A32: 31 | B32: AC | C32: 13-pol | D32: 158247-37619-1 (rameder) | E32: Kia Rio 2017> | F32: 2017> | G32: Ligger hos Äpplekullen
A33: 32 | B33: Erich Jaeger | C33: 7-pol | D33: 737422 | E33: Kia Niro 2016> | F33: 2016> | G33: Retur från MTB62R | H33: OK | I33: Ja | J33: 737422
A34: 33 | B34: Erich Jaeger | C34: 13-pol | D34: 747113 | E34: Peugeot 3008 2016> Peugeot 5008 2017> Opel Grandland X 2014 Citroen C5 Aircross 2019> | G34: Endast för förberedda bilar. | H34: Ser orörd ut | I34: Ja | J34: 747113
B35: ECS | C35: 13-pol | D35: VW190H1 | E35: VW, Skoda, Audi massa modeller | F35: 2011>
B36: ECS | C36: 7-pol | D36: VW190B1 | E36: VW, Skoda, Audi massa modeller | F36: 2011>
B37: ECS | C37: 13-pol | D37: AU068H1 | E37: Audi massa modeller | F37: 2011>
B38: ECS | C38: 7-pol | D38: AU068B1 | E38: Audi massa modeller | F38: 2011>
A39: 34 | B39: Erich Jaeger | C39: 13-pol | D39: 747202 | E39: Jaguar F-pace 06/17 >> Range Rover Velar 06/17 >> | F39: 2017> | H39: OK | I39: Ja | J39: 747202
B40: Westfalia | C40: 13-pol | D40: 320134300113 | E40: Volvo V60 2010> | F40: 2010> | G40: Tror den har gott till PDK036
A41: 35 | B41: Westfalia | C41: 13-pol | D41: 34513400107 | E41: Kia | F41: 2018 | G41: Speedy Linköping
B42: Westfalia | C42: 7-spec | D42: 320165300107 | E42: Volvo S90 / V90 2016> | F42: 2016> | G42: Hyllan | H42: OK | I42: Ja | J42: 320165300107 | L42: =IFNA(VLOOKUP(D42,'EAN Codes'!A:C,2,False),"") | P42: Varit hos Bergendahl men ser bra ut, aldrig inkopplat
A43: 36 | B43: Westfalia | C43: 13-pol | D43: 320173300113 | E43: Volvo V60 2010> | G43: Hllan | H43: OK | I43: Ja | J43: 320173300113
A44: 37 | B44: Westfalia | C44: 13-pol | D44: 303352300113 | E44: BMW
B45: Westfalia | C45: 13-pol | D45: 320117300113 | H45: OK | I45: Ja | J45: 320117300113
B46: Westfalia | C46: 13-pol | D46: 345169300113 | H46: OK | I46: Ja | J46: 345169300113

Sheet Lager Takräcke
A1: Tillverkare | B1: Namn | C1: Artikelnummer | D1: Pris rek € | E1: Pris inköp € | F1: inventering 190823 | G1: Order 190823 | H1: Totalt efter beställning | I1: Inventering 191028 | J1: Antal sålda | K1: Beställa hem | L1: Totalt efter beställning | M1: Inventering 191202 | N1: Antal sålda | O1: Beställa hem | P1: Totalt efter beställning | Q1: Inventering 191219 | R1: Antal sålda | S1: Beställa hem Pall 1 | T1: Totalt efter beställning | U1: Inventering 20-01-08 | V1: Totalt efter beställning 1 | W1: Beställ hem | X1: Totalt efter beställning | Y1: Inventering 200204 | Z1: Antal sålda | AA1: Beställ hem | AB1: Total efter beställning | AC1: Inventering 200302 | AD1: Antal sålda | AE1: Beställ hem | AF1: Totalt efter beställning | AG1: Inventering 200415 | AH1: Antal sålda | AI1: Beställa hem | AJ1: Totalt efter beställning | AK1: Inventering 200601 | AL1: Antal sålda | AM1: Beställa hem | AN1: Totalt efter beställning | AO1: Beställt 2020-07-01 | AP1: Inventering 2020-07-13 | AQ1: Beställt 2020-07-14 | AR1: Inventering 2020-08-25 | AS1: Beställt 2020-08-25 | AT1: Totalt efter beställning | AU1: Inventering 2020-09-16 | AV1: Antal sålda | AW1: Beställa hem | AX1: Totalt efter beställning | AY1: Inventering 2020-10-23 | AZ1: Inventering | BA1: Antal Sålda | BB1: Beställa hem | BC1: Totalt efter beställning | BE1: Totalt antal beställt
A2: Menabo | B2: DELTA ALU M SILVER | C2: 000095400000 | D2: 49 | E2: 20.384 | F2: 17 | G2: 0 | H2: =F2+G2 -> 17 | I2: 10 | J2: =H2-I2 -> 7 | K2: 0 | L2: =I2+K2 -> 10 | M2: 6 | N2: =L2-M2 -> 4 | O2: 6 | P2: =M2+O2 -> 12 | Q2: 5 | R2: =P2-Q2 -> 7 | S2: 12 | T2: =Q2+S2 -> 17 | U2: 0 | V2: =U2+S2 -> 12 | W2: 12 | X2: =V2+W2 -> 24 | Y2: 21 | Z2: =X2-Y2 -> 3 | AB2: =Y2+AA2 -> 21 | AC2: 19 | AD2: =AB2-AC2 -> 2 | AF2: =AC2+AE2 -> 19 | AG2: 17 | AH2: =AF2-AG2 -> 2 | AI2: 0 | AJ2: =AG2+AI2 -> 17 | AK2: 12 | AL2: =AJ2-AK2 -> 5 | AN2: =AK2+AM2 -> 12 | AO2: 12 | AR2: 11 | AS2: 6 | AT2: =AR2+AS2 -> 17 | AU2: 15 | AV2: =AT2-AU2 -> 2 | AX2: =AU2+AW2 -> 15 | AY2: 14 | AZ2: 13 | BA2: =AX2-AZ2 -> 2 | BC2: =AZ2+BB2 -> 13 | BE2: =BB2+AW2+AS2+AQ2+AO2+AM2+AJ2 -> 35
A3: Menabo | B3: DELTA ALU L SILVER | C3: 000095500000 | D3: 55.5 | E3: 23.088 | F3: 16 | G3: 0 | H3: =F3+G3 -> 16 | I3: 11 | J3: =H3-I3 -> 5 | K3: 0 | L3: =I3+K3 -> 11 | M3: 5 | N3: =L3-M3 -> 6 | O3: 12 | P3: =M3+O3 -> 17 | Q3: 14 | R3: =P3-Q3 -> 3 | T3: =Q3+S3 -> 14 | U3: 11 | V3: =U3+S3 -> 11 | W3: 8 | X3: =V3+W3 -> 19 | Y3: 12 | Z3: =X3-Y3 -> 7 | AA3: 12 | AB3: =Y3+AA3 -> 24 | AC3: 19 | AD3: =AB3-AC3 -> 5 | AF3: =AC3+AE3 -> 19 | AG3: 12 | AH3: =AF3-AG3 -> 7 | AJ3: =AG3+AI3 -> 12 | AK3: 4 | AL3: =AJ3-AK3 -> 8 | AM3: 12 | AN3: =AK3+AM3 -> 16 | AO3: 12 | AR3: 7 | AS3: 6 | AT3: =AR3+AS3 -> 13 | AU3: 11 | AV3: =AT3-AU3 -> 2 | AX3: =AU3+AW3 -> 11 | AY3: 7 | AZ3: 5 | BA3: =AX3-AZ3 -> 6 | BB3: 6 | BC3: =AZ3+BB3 -> 11 | BE3: =BB3+AW3+AS3+AQ3+AO3+AM3+AJ3 -> 48
A4: Menabo | B4: DLFIX201FP | C4: 000104900000 | D4: 36 | E4: 14.976 | F4: 3 | G4: 0 | H4: =F4+G4 -> 3 | I4: 0 | J4: =H4-I4 -> 3 | K4: 4 | L4: =I4+K4 -> 4 | M4: 3 | N4: =L4-M4 -> 1 | O4: 0 | P4: =M4+O4 -> 3 | Q4: 2 | R4: =P4-Q4 -> 1 | T4: =Q4+S4 -> 2 | U4: 0 | V4: =U4+S4 -> 0 | W4: 2 | X4: =V4+W4 -> 2 | Y4: 2 | Z4: =X4-Y4 -> 0 | AB4: =Y4+AA4 -> 2 | AC4: 2 | AD4: =AB4-AC4 -> 0 | AF4: =AC4+AE4 -> 2 | AG4: 2 | AH4: =AF4-AG4 -> 0 | AJ4: =AG4+AI4 -> 2 | AK4: 2 | AL4: =AJ4-AK4 -> 0 | AN4: =AK4+AM4 -> 2 | AO4: 1 | AR4: 1 | AS4: 1 | AT4: =AR4+AS4 -> 2 | AU4: 2 | AV4: =AT4-AU4 -> 0 | AX4: =AU4+AW4 -> 2 | AY4: 2 | AZ4: 2 | BA4: =AX4-AZ4 -> 0 | BC4: =AZ4+BB4 -> 2 | BE4: =BB4+AW4+AS4+AQ4+AO4+AM4+AJ4 -> 4
A5: Menabo | B5: DLFIX202FP | AR5: 0 | AS5: 1 | AT5: =AR5+AS5 -> 1 | AU5: 1 | AV5: =AT5-AU5 -> 0 | AX5: =AU5+AW5 -> 1 | AY5: 1 | AZ5: 1 | BA5: =AX5-AZ5 -> 0 | BC5: =AZ5+BB5 -> 1 | BE5: =BB5+AW5+AS5+AQ5+AO5+AM5+AJ5 -> 1
A6: Menabo | B6: DLFIX203FP | C6: 000105900000 | D6: 36 | E6: 14.976 | F6: 3 | G6: 0 | H6: =F6+G6 -> 3 | I6: 1 | J6: =H6-I6 -> 2 | K6: 2 | L6: =I6+K6 -> 3 | M6: 4 | N6: =L6-M6 -> -1 | O6: 0 | P6: =M6+O6 -> 4 | Q6: 4 | R6: =P6-Q6 -> 0 | T6: =Q6+S6 -> 4 | U6: 4 | V6: =U6+S6 -> 4 | X6: =V6+W6 -> 4 | Y6: 3 | Z6: =X6-Y6 -> 1 | AB6: =Y6+AA6 -> 3 | AC6: 3 | AD6: =AB6-AC6 -> 0 | AF6: =AC6+AE6 -> 3 | AG6: 2 | AH6: =AF6-AG6 -> 1 | AJ6: =AG6+AI6 -> 2 | AK6: 2 | AL6: =AJ6-AK6 -> 0 | AN6: =AK6+AM6 -> 2 | AO6: 2 | AR6: 2 | AT6: =AR6+AS6 -> 2 | AU6: 2 | AV6: =AT6-AU6 -> 0 | AX6: =AU6+AW6 -> 2 | AY6: 1 | AZ6: 2 | BA6: =AX6-AZ6 -> 0 | BC6: =AZ6+BB6 -> 2 | BE6: =BB6+AW6+AS6+AQ6+AO6+AM6+AJ6 -> 4
A7: Menabo | B7: DLFIX204FP | C7: 000106000000 | D7: 36 | E7: 14.976 | F7: 2 | G7: 0 | H7: =F7+G7 -> 2 | I7: 1 | J7: =H7-I7 -> 1 | K7: 1 | L7: =I7+K7 -> 2 | M7: 0 | N7: =L7-M7 -> 2 | O7: 3 | P7: =M7+O7 -> 3 | Q7: 2 | R7: =P7-Q7 -> 1 | T7: =Q7+S7 -> 2 | U7: 2 | V7: =U7+S7 -> 2 | X7: =V7+W7 -> 2 | Y7: 2 | Z7: =X7-Y7 -> 0 | AB7: =Y7+AA7 -> 2 | AC7: 1 | AD7: =AB7-AC7 -> 1 | AE7: 1 | AF7: =AC7+AE7 -> 2 | AG7: 2 | AH7: =AF7-AG7 -> 0 | AJ7: =AG7+AI7 -> 2 | AK7: 2 | AL7: =AJ7-AK7 -> 0 | AN7: =AK7+AM7 -> 2 | AO7: 3 | AR7: 2 | AS7: 1 | AT7: =AR7+AS7 -> 3 | AU7: 3 | AV7: =AT7-AU7 -> 0 | AX7: =AU7+AW7 -> 3 | AY7: 2 | AZ7: 2 | BA7: =AX7-AZ7 -> 1 | BC7: =AZ7+BB7 -> 2 | BE7: =BB7+AW7+AS7+AQ7+AO7+AM7+AJ7 -> 6
A8: Menabo | B8: DLFIX205FP | C8: 000106100000 | D8: 36 | E8: 14.976 | F8: 3 | G8: 0 | H8: =F8+G8 -> 3 | I8: 3 | J8: =H8-I8 -> 0 | K8: 0 | L8: =I8+K8 -> 3 | M8: 2 | N8: =L8-M8 -> 1 | O8: 1 | P8: =M8+O8 -> 3 | Q8: 3 | R8: =P8-Q8 -> 0 | T8: =Q8+S8 -> 3 | U8: 2 | V8: =U8+S8 -> 2 | X8: =V8+W8 -> 2 | Y8: 2 | Z8: =X8-Y8 -> 0 | AB8: =Y8+AA8 -> 2 | AC8: 2 | AD8: =AB8-AC8 -> 0 | AF8: =AC8+AE8 -> 2 | AG8: 2 | AH8: =AF8-AG8 -> 0 | AJ8: =AG8+AI8 -> 2 | AK8: 2 | AL8: =AJ8-AK8 -> 0 | AN8: =AK8+AM8 -> 2 | AR8: 2 | AT8: =AR8+AS8 -> 2 | AU8: 1 | AV8: =AT8-AU8 -> 1 | AX8: =AU8+AW8 -> 1 | AY8: 1 | AZ8: 1 | BA8: =AX8-AZ8 -> 0 | BC8: =AZ8+BB8 -> 1 | BE8: =BB8+AW8+AS8+AQ8+AO8+AM8+AJ8 -> 2
A9: Menabo | B9: DLFIX206FP | C9: 000106200000 | D9: 36 | E9: 14.976 | F9: 5 | G9: 0 | H9: =F9+G9 -> 5 | I9: 3 | J9: =H9-I9 -> 2 | K9: 1 | L9: =I9+K9 -> 4 | M9: 1 | N9: =L9-M9 -> 3 | O9: 2 | P9: 2 | Q9: 1 | R9: =P9-Q9 -> 1 | S9: 1 | T9: =Q9+S9 -> 2 | U9: 0 | V9: =U9+S9 -> 1 | W9: 1 | X9: =V9+W9 -> 2 | Y9: 0 | Z9: =X9-Y9 -> 2 | AA9: 2 | AB9: =Y9+AA9 -> 2 | AC9: 1 | AD9: =AB9-AC9 -> 1 | AE9: 1 | AF9: =AC9+AE9 -> 2 | AG9: 1 | AH9: =AF9-AG9 -> 1 | AI9: 1 | AJ9: =AG9+AI9 -> 2 | AK9: 1 | AL9: =AJ9-AK9 -> 1 | AM9: 1 | AN9: =AK9+AM9 -> 2 | AO9: 1 | AR9: 1 | AS9: 2 | AT9: =AR9+AS9 -> 3 | AU9: 3 | AV9: =AT9-AU9 -> 0 | AX9: =AU9+AW9 -> 3 | AY9: 3 | AZ9: 3 | BA9: =AX9-AZ9 -> 0 | BC9: =AZ9+BB9 -> 3 | BE9: =BB9+AW9+AS9+AQ9+AO9+AM9+AJ9 -> 6
A10: Menabo | B10: DLFIX208FP | C10: 000106600000 | D10: 36 | E10: 14.976 | F10: 5 | G10: 0 | H10: =F10+G10 -> 5 | I10: 3 | J10: =H10-I10 -> 2 | K10: 0 | L10: =I10+K10 -> 3 | M10: 0 | N10: =L10-M10 -> 3 | O10: 3 | P10: =M10+O10 -> 3 | Q10: 2 | R10: =P10-Q10 -> 1 | T10: =Q10+S10 -> 2 | U10: 2 | V10: =U10+S10 -> 2 | X10: =V10+W10 -> 2 | Y10: 0 | Z10: =X10-Y10 -> 2 | AA10: 2 | AB10: =Y10+AA10 -> 2 | AC10: 1 | AD10: =AB10-AC10 -> 1 | AE10: 4 | AF10: =AC10+AE10 -> 5 | AG10: 4 | AH10: =AF10-AG10 -> 1 | AJ10: =AG10+AI10 -> 4 | AK10: 1 | AL10: =AJ10-AK10 -> 3 | AM10: 2 | AN10: =AK10+AM10 -> 3 | AR10: 0 | AS10: 3 | AT10: =AR10+AS10 -> 3 | AU10: 2 | AV10: =AT10-AU10 -> 1 | AX10: =AU10+AW10 -> 2 | AY10: 1 | AZ10: 1 | BA10: =AX10-AZ10 -> 1 | BB10: 2 | BC10: =AZ10+BB10 -> 3 | BE10: =BB10+AW10+AS10+AQ10+AO10+AM10+AJ10 -> 11
A11: Menabo | B11: DLFIX209FP | C11: 000106700000 | D11: 36 | E11: 14.976 | F11: 2 | G11: 0 | H11: =F11+G11 -> 2 | I11: 2 | J11: =H11-I11 -> 0 | K11: 0 | L11: =I11+K11 -> 2 | M11: 2 | N11: =L11-M11 -> 0 | O11: 0 | P11: =M11+O11 -> 2 | Q11: 1 | R11: =P11-Q11 -> 1 | S11: 1 | T11: =Q11+S11 -> 2 | U11: 0 | V11: =U11+S11 -> 1 | W11: 1 | X11: =V11+W11 -> 2 | Y11: 2 | Z11: =X11-Y11 -> 0 | AB11: =Y11+AA11 -> 2 | AC11: 2 | AD11: =AB11-AC11 -> 0 | AF11: =AC11+AE11 -> 2 | AG11: 2 | AH11: =AF11-AG11 -> 0 | AJ11: =AG11+AI11 -> 2 | AK11: 0 | AL11: =AJ11-AK11 -> 2 | AM11: 2 | AN11: =AK11+AM11 -> 2 | AR11: 1 | AT11: =AR11+AS11 -> 1 | AU11: 0 | AV11: =AT11-AU11 -> 1 | AW11: 2 | AX11: =AU11+AW11 -> 2 | AY11: 2 | AZ11: 2 | BA11: =AX11-AZ11 -> 0 | BC11: =AZ11+BB11 -> 2 | BE11: =BB11+AW11+AS11+AQ11+AO11+AM11+AJ11 -> 6
A12: Menabo | B12: DLKIT02G | C12: 000096400000 | D12: 28 | E12: 11.648 | F12: 4 | G12: 0 | H12: =F12+G12 -> 4 | I12: 3 | J12: =H12-I12 -> 1 | K12: 0 | L12: =I12+K12 -> 3 | M12: 2 | N12: =L12-M12 -> 1 | O12: 0 | P12: =M12+O12 -> 2 | Q12: 2 | R12: =P12-Q12 -> 0 | T12: =Q12+S12 -> 2 | U12: 2 | V12: =U12+S12 -> 2 | X12: =V12+W12 -> 2 | Y12: 1 | Z12: =X12-Y12 -> 1 | AA12: 1 | AB12: =Y12+AA12 -> 2 | AC12: 3 | AD12: =AB12-AC12 -> -1 | AF12: =AC12+AE12 -> 3 | AG12: 3 | AH12: =AF12-AG12 -> 0 | AJ12: =AG12+AI12 -> 3 | AK12: 2 | AL12: =AJ12-AK12 -> 1 | AN12: =AK12+AM12 -> 2 | AR12: 0 | AS12: 1 | AT12: =AR12+AS12 -> 1 | AU12: 1 | AV12: =AT12-AU12 -> 0 | AX12: =AU12+AW12 -> 1 | AY12: 0 | AZ12: 0 | BA12: =AX12-AZ12 -> 1 | BB12: 2 | BC12: =AZ12+BB12 -> 2 | BE12: =BB12+AW12+AS12+AQ12+AO12+AM12+AJ12 -> 6
A13: Menabo | B13: DLKIT03G | C13: 000096500000 | D13: 28 | E13: 11.648 | F13: 4 | G13: 0 | H13: =F13+G13 -> 4 | I13: 2 | J13: =H13-I13 -> 2 | K13: 0 | L13: =I13+K13 -> 2 | M13: 2 | N13: =L13-M13 -> 0 | O13: 0 | P13: =M13+O13 -> 2 | Q13: 2 | R13: =P13-Q13 -> 0 | T13: =Q13+S13 -> 2 | U13: 1 | V13: =U13+S13 -> 1 | W13: 1 | X13: =V13+W13 -> 2 | Y13: 1 | Z13: =X13-Y13 -> 1 | AA13: 1 | AB13: =Y13+AA13 -> 2 | AC13: 2 | AD13: =AB13-AC13 -> 0 | AF13: =AC13+AE13 -> 2 | AG13: 1 | AH13: =AF13-AG13 -> 1 | AI13: 1 | AJ13: =AG13+AI13 -> 2 | AK13: 0 | AL13: =AJ13-AK13 -> 2 | AM13: 2 | AN13: =AK13+AM13 -> 2 | AR13: 1 | AT13: =AR13+AS13 -> 1 | AU13: 0 | AV13: =AT13-AU13 -> 1 | AW13: 2 | AX13: =AU13+AW13 -> 2 | AY13: 1 | AZ13: 1 | BA13: =AX13-AZ13 -> 1 | BB13: 1 | BC13: =AZ13+BB13 -> 2 | BE13: =BB13+AW13+AS13+AQ13+AO13+AM13+AJ13 -> 7
A14: Menabo | B14: DLKIT06G | D14: 28 | E14: 11.648 | F14: 2 | G14: 0 | H14: =F14+G14 -> 2 | I14: 2 | J14: =H14-I14 -> 0 | K14: 0 | L14: =I14+K14 -> 2 | M14: 2 | N14: =L14-M14 -> 0 | O14: 0 | P14: =M14+O14 -> 2 | Q14: 2 | R14: =P14-Q14 -> 0 | T14: =Q14+S14 -> 2 | U14: 2 | V14: =U14+S14 -> 2 | X14: =V14+W14 -> 2 | Y14: 2 | Z14: =X14-Y14 -> 0 | AB14: =Y14+AA14 -> 2 | AC14: 2 | AD14: =AB14-AC14 -> 0 | AF14: =AC14+AE14 -> 2 | AG14: 2 | AH14: =AF14-AG14 -> 0 | AJ14: =AG14+AI14 -> 2 | AK14: 2 | AL14: =AJ14-AK14 -> 0 | AN14: =AK14+AM14 -> 2 | AR14: 1 | AT14: =AR14+AS14 -> 1 | AU14: 1 | AV14: =AT14-AU14 -> 0 | AX14: =AU14+AW14 -> 1 | AY14: 1 | AZ14: 1 | BA14: =AX14-AZ14 -> 0 | BC14: =AZ14+BB14 -> 1 | BE14: =BB14+AW14+AS14+AQ14+AO14+AM14+AJ14 -> 2
A15: Menabo | B15: DLKIT07G | D15: 28 | E15: 11.648 | F15: 3 | G15: 0 | H15: =F15+G15 -> 3 | I15: 2 | J15: =H15-I15 -> 1 | K15: 0 | L15: =I15+K15 -> 2 | M15: 2 | N15: =L15-M15 -> 0 | O15: 0 | P15: =M15+O15 -> 2 | Q15: 2 | R15: =P15-Q15 -> 0 | T15: =Q15+S15 -> 2 | U15: 2 | V15: =U15+S15 -> 2 | X15: =V15+W15 -> 2 | Y15: 2 | Z15: =X15-Y15 -> 0 | AB15: =Y15+AA15 -> 2 | AC15: 2 | AD15: =AB15-AC15 -> 0 | AF15: =AC15+AE15 -> 2 | AG15: 2 | AH15: =AF15-AG15 -> 0 | AJ15: =AG15+AI15 -> 2 | AK15: 2 | AL15: =AJ15-AK15 -> 0 | AN15: =AK15+AM15 -> 2 | AR15: 2 | AT15: =AR15+AS15 -> 2 | AU15: 2 | AV15: =AT15-AU15 -> 0 | AX15: =AU15+AW15 -> 2 | AY15: 2 | AZ15: 2 | BA15: =AX15-AZ15 -> 0 | BC15: =AZ15+BB15 -> 2 | BE15: =BB15+AW15+AS15+AQ15+AO15+AM15+AJ15 -> 2
A16: Menabo | B16: DLKIT08G | C16: 000097000000 | D16: 28 | E16: 11.648 | F16: 3 | G16: 0 | H16: =F16+G16 -> 3 | I16: 2 | J16: =H16-I16 -> 1 | K16: 0 | L16: =I16+K16 -> 2 | M16: 2 | N16: =L16-M16 -> 0 | O16: 0 | P16: =M16+O16 -> 2 | Q16: 1 | R16: =P16-Q16 -> 1 | S16: 1 | T16: =Q16+S16 -> 2 | U16: 1 | V16: =U16+S16 -> 2 | X16: =V16+W16 -> 2 | Y16: 2 | Z16: =X16-Y16 -> 0 | AB16: =Y16+AA16 -> 2 | AC16: 2 | AD16: =AB16-AC16 -> 0 | AF16: =AC16+AE16 -> 2 | AG16: 1 | AH16: =AF16-AG16 -> 1 | AI16: 1 | AJ16: =AG16+AI16 -> 2 | AK16: 2 | AL16: =AJ16-AK16 -> 0 | AN16: =AK16+AM16 -> 2 | AR16: 0 | AS16: 1 | AT16: =AR16+AS16 -> 1 | AU16: 1 | AV16: =AT16-AU16 -> 0 | AX16: =AU16+AW16 -> 1 | AY16: 1 | AZ16: 1 | BA16: =AX16-AZ16 -> 0 | BC16: =AZ16+BB16 -> 1 | BE16: =BB16+AW16+AS16+AQ16+AO16+AM16+AJ16 -> 3
A17: Menabo | B17: DLKIT10G | C17: 000097200000 | D17: 28 | E17: 11.648 | F17: 2 | G17: 0 | H17: 1 | I17: 1 | J17: =H17-I17 -> 0 | K17: 0 | L17: =I17+K17 -> 1 | M17: 1 | N17: =L17-M17 -> 0 | O17: 0 | P17: =M17+O17 -> 1 | Q17: 1 | R17: =P17-Q17 -> 0 | T17: =Q17+S17 -> 1 | U17: 1 | V17: =U17+S17 -> 1 | W17: 1 | X17: =V17+W17 -> 2 | Y17: 1 | Z17: =X17-Y17 -> 1 | AA17: 1 | AB17: =Y17+AA17 -> 2 | AC17: 2 | AD17: =AB17-AC17 -> 0 | AF17: =AC17+AE17 -> 2 | AG17: 2 | AH17: =AF17-AG17 -> 0 | AJ17: =AG17+AI17 -> 2 | AK17: 1 | AL17: =AJ17-AK17 -> 1 | AM17: 1 | AN17: =AK17+AM17 -> 2 | AO17: 2 | AR17: 0 | AS17: 2 | AT17: =AR17+AS17 -> 2 | AU17: 2 | AV17: =AT17-AU17 -> 0 | AX17: =AU17+AW17 -> 2 | AY17: 2 | AZ17: 2 | BA17: =AX17-AZ17 -> 0 | BC17: =AZ17+BB17 -> 2 | BE17: =BB17+AW17+AS17+AQ17+AO17+AM17+AJ17 -> 7
A18: Menabo | B18: DLKIT13G | D18: 28 | E18: 11.648 | U18: 1 | V18: =U18+S18 -> 1 | W18: 1 | X18: =V18+W18 -> 2 | Y18: 2 | Z18: =X18-Y18 -> 0 | AB18: =Y18+AA18 -> 2 | AC18: 2 | AD18: =AB18-AC18 -> 0 | AF18: =AC18+AE18 -> 2 | AG18: 2 | AH18: =AF18-AG18 -> 0 | AJ18: =AG18+AI18 -> 2 | AK18: 2 | AL18: =AJ18-AK18 -> 0 | AN18: =AK18+AM18 -> 2 | AR18: 1 | AT18: =AR18+AS18 -> 1 | AU18: 1 | AV18: =AT18-AU18 -> 0 | AX18: =AU18+AW18 -> 1 | AY18: 1 | AZ18: 1 | BA18: =AX18-AZ18 -> 0 | BC18: =AZ18+BB18 -> 1 | BE18: =BB18+AW18+AS18+AQ18+AO18+AM18+AJ18 -> 2
A19: Menabo | B19: DLKIT17G | C19: 000097900000 | D19: 28 | E19: 11.648 | F19: 6 | G19: 0 | H19: =F19+G19 -> 6 | I19: 6 | J19: =H19-I19 -> 0 | K19: 0 | L19: =I19+K19 -> 6 | M19: 6 | N19: =L19-M19 -> 0 | O19: 0 | P19: =M19+O19 -> 6 | Q19: 5 | R19: =P19-Q19 -> 1 | T19: =Q19+S19 -> 5 | U19: 5 | V19: =U19+S19 -> 5 | X19: =V19+W19 -> 5 | Y19: 5 | Z19: =X19-Y19 -> 0 | AB19: =Y19+AA19 -> 5 | AC19: 4 | AD19: =AB19-AC19 -> 1 | AF19: =AC19+AE19 -> 4 | AG19: 4 | AH19: =AF19-AG19 -> 0 | AJ19: =AG19+AI19 -> 4 | AK19: 3 | AL19: =AJ19-AK19 -> 1 | AN19: =AK19+AM19 -> 3 | AR19: 2 | AT19: =AR19+AS19 -> 2 | AU19: 2 | AV19: =AT19-AU19 -> 0 | AX19: =AU19+AW19 -> 2 | AY19: 1 | AZ19: 0 | BA19: =AX19-AZ19 -> 2 | BB19: 2 | BC19: =AZ19+BB19 -> 2 | BE19: =BB19+AW19+AS19+AQ19+AO19+AM19+AJ19 -> 6
A20: Menabo | B20: DLKIT19G | C20: 000098100000 | D20: 28 | E20: 11.648 | F20: 0 | G20: 2 | H20: =F20+G20 -> 2 | I20: 0 | J20: =H20-I20 -> 2 | K20: 2 | L20: =I20+K20 -> 2 | M20: 1 | N20: =L20-M20 -> 1 | O20: 1 | P20: =M20+O20 -> 2 | Q20: 1 | R20: =P20-Q20 -> 1 | S20: 1 | T20: =Q20+S20 -> 2 | U20: 1 | V20: =U20+S20 -> 2 | X20: =V20+W20 -> 2 | Y20: 1 | Z20: =X20-Y20 -> 1 | AA20: 1 | AB20: =Y20+AA20 -> 2 | AC20: 2 | AD20: =AB20-AC20 -> 0 | AF20: =AC20+AE20 -> 2 | AG20: 1 | AH20: =AF20-AG20 -> 1 | AI20: 1 | AJ20: =AG20+AI20 -> 2 | AK20: 1 | AL20: =AJ20-AK20 -> 1 | AM20: 1 | AN20: =AK20+AM20 -> 2 | AR20: 0 | AS20: 1 | AT20: =AR20+AS20 -> 1 | AU20: 1 | AV20: =AT20-AU20 -> 0 | AX20: =AU20+AW20 -> 1 | AY20: 0 | AZ20: 0 | BA20: =AX20-AZ20 -> 1 | BB20: 2 | BC20: =AZ20+BB20 -> 2 | BE20: =BB20+AW20+AS20+AQ20+AO20+AM20+AJ20 -> 6
A21: Menabo | B21: DLKIT27G | C21: 000098900000 | D21: 28 | E21: 11.648 | F21: 4 | G21: 0 | H21: =F21+G21 -> 4 | I21: 4 | J21: =H21-I21 -> 0 | K21: 0 | L21: =I21+K21 -> 4 | M21: 4 | N21: =L21-M21 -> 0 | O21: 0 | P21: =M21+O21 -> 4 | Q21: 4 | R21: =P21-Q21 -> 0 | T21: =Q21+S21 -> 4 | U21: 4 | V21: =U21+S21 -> 4 | X21: =V21+W21 -> 4 | Y21: 2 | Z21: =X21-Y21 -> 2 | AB21: =Y21+AA21 -> 2 | AC21: 1 | AD21: =AB21-AC21 -> 1 | AE21: 1 | AF21: =AC21+AE21 -> 2 | AG21: 2 | AH21: =AF21-AG21 -> 0 | AJ21: =AG21+AI21 -> 2 | AK21: 2 | AL21: =AJ21-AK21 -> 0 | AN21: =AK21+AM21 -> 2 | AR21: 1 | AT21: =AR21+AS21 -> 1 | AU21: 1 | AV21: =AT21-AU21 -> 0 | AX21: =AU21+AW21 -> 1 | AY21: 1 | AZ21: 1 | BA21: =AX21-AZ21 -> 0 | BC21: =AZ21+BB21 -> 1 | BE21: =BB21+AW21+AS21+AQ21+AO21+AM21+AJ21 -> 2
A22: Menabo | B22: DLKIT29G | C22: 000099100000 | D22: 28 | E22: 11.648 | F22: 2 | G22: 0 | H22: =F22+G22 -> 2 | I22: 2 | J22: =H22-I22 -> 0 | K22: 0 | L22: =I22+K22 -> 2 | M22: 2 | N22: =L22-M22 -> 0 | O22: 0 | P22: =M22+O22 -> 2 | Q22: 2 | R22: =P22-Q22 -> 0 | T22: =Q22+S22 -> 2 | U22: 1 | V22: =U22+S22 -> 1 | W22: 1 | X22: =V22+W22 -> 2 | Y22: 2 | Z22: =X22-Y22 -> 0 | AB22: =Y22+AA22 -> 2 | AC22: 2 | AD22: =AB22-AC22 -> 0 | AF22: =AC22+AE22 -> 2 | AG22: 2 | AH22: =AF22-AG22 -> 0 | AJ22: =AG22+AI22 -> 2 | AK22: 1 | AL22: =AJ22-AK22 -> 1 | AM22: 1 | AN22: =AK22+AM22 -> 2 | AO22: 1 | AR22: 0 | AS22: 1 | AT22: =AR22+AS22 -> 1 | AU22: 1 | AV22: =AT22-AU22 -> 0 | AX22: =AU22+AW22 -> 1 | AY22: 1 | AZ22: 1 | BA22: =AX22-AZ22 -> 0 | BC22: =AZ22+BB22 -> 1 | BE22: =BB22+AW22+AS22+AQ22+AO22+AM22+AJ22 -> 5
A23: Menabo | B23: DLKIT31G | AR23: 1 | AT23: =AR23+AS23 -> 1 | AU23: 1 | AV23: =AT23-AU23 -> 0 | AX23: =AU23+AW23 -> 1 | AY23: 1 | AZ23: 1 | BA23: =AX23-AZ23 -> 0 | BC23: =AZ23+BB23 -> 1 | BE23: =BB23+AW23+AS23+AQ23+AO23+AM23+AJ23 -> 0
A24: Menabo | B24: DLKIT36G | C24: 000099800000 | D24: 28 | E24: 11.648 | F24: 4 | G24: 0 | H24: =F24+G24 -> 4 | I24: 4 | J24: =H24-I24 -> 0 | K24: 0 | L24: =I24+K24 -> 4 | M24: 4 | N24: =L24-M24 -> 0 | O24: 0 | P24: =M24+O24 -> 4 | Q24: 3 | R24: =P24-Q24 -> 1 | T24: =Q24+S24 -> 3 | U24: 4 | V24: =U24+S24 -> 4 | X24: =V24+W24 -> 4 | Y24: 2 | Z24: =X24-Y24 -> 2 | AB24: =Y24+AA24 -> 2 | AC24: 2 | AD24: =AB24-AC24 -> 0 | AF24: =AC24+AE24 -> 2 | AG24: 1 | AH24: =AF24-AG24 -> 1 | AI24: 1 | AJ24: =AG24+AI24 -> 2 | AK24: 2 | AL24: =AJ24-AK24 -> 0 | AN24: =AK24+AM24 -> 2 | AR24: 2 | AT24: =AR24+AS24 -> 2 | AU24: 2 | AV24: =AT24-AU24 -> 0 | AX24: =AU24+AW24 -> 2 | AY24: 2 | AZ24: 2 | BA24: =AX24-AZ24 -> 0 | BC24: =AZ24+BB24 -> 2 | BE24: =BB24+AW24+AS24+AQ24+AO24+AM24+AJ24 -> 2
A25: Menabo | B25: DLKIT38G | C25: 000100000000 | D25: 28 | E25: 11.648 | F25: 3 | G25: 0 | H25: =F25+G25 -> 3 | I25: 3 | J25: =H25-I25 -> 0 | K25: 0 | L25: =I25+K25 -> 3 | M25: 3 | N25: =L25-M25 -> 0 | O25: 0 | P25: =M25+O25 -> 3 | Q25: 3 | R25: =P25-Q25 -> 0 | T25: =Q25+S25 -> 3 | U25: 3 | V25: =U25+S25 -> 3 | X25: =V25+W25 -> 3 | Y25: 3 | Z25: =X25-Y25 -> 0 | AB25: =Y25+AA25 -> 3 | AC25: 2 | AD25: =AB25-AC25 -> 1 | AF25: =AC25+AE25 -> 2 | AG25: 2 | AH25: =AF25-AG25 -> 0 | AJ25: =AG25+AI25 -> 2 | AK25: 0 | AL25: =AJ25-AK25 -> 2 | AM25: 2 | AN25: =AK25+AM25 -> 2 | AR25: 4 | AT25: =AR25+AS25 -> 4 | AU25: 4 | AV25: =AT25-AU25 -> 0 | AX25: =AU25+AW25 -> 4 | AY25: 4 | AZ25: 4 | BA25: =AX25-AZ25 -> 0 | BC25: =AZ25+BB25 -> 4 | BE25: =BB25+AW25+AS25+AQ25+AO25+AM25+AJ25 -> 4
A26: Menabo | B26: DLKIT39G | D26: 28 | E26: 11.648 | J26: 0 | K26: 4 | L26: =I26+K26 -> 4 | M26: 4 | N26: =L26-M26 -> 0 | O26: 0 | P26: =M26+O26 -> 4 | Q26: 4 | R26: =P26-Q26 -> 0 | T26: =Q26+S26 -> 4 | U26: 4 | V26: =U26+S26 -> 4 | X26: =V26+W26 -> 4 | Y26: 4 | Z26: =X26-Y26 -> 0 | AB26: =Y26+AA26 -> 4 | AC26: 4 | AD26: =AB26-AC26 -> 0 | AF26: =AC26+AE26 -> 4 | AG26: 3 | AH26: =AF26-AG26 -> 1 | AJ26: =AG26+AI26 -> 3 | AK26: 3 | AL26: =AJ26-AK26 -> 0 | AN26: =AK26+AM26 -> 3 | AR26: 3 | AT26: =AR26+AS26 -> 3 | AU26: 3 | AV26: =AT26-AU26 -> 0 | AX26: =AU26+AW26 -> 3 | AY26: 3 | AZ26: 2 | BA26: =AX26-AZ26 -> 1 | BC26: =AZ26+BB26 -> 2 | BE26: =BB26+AW26+AS26+AQ26+AO26+AM26+AJ26 -> 3
A27: Menabo | B27: DLKIT41G | C27: 000100300000 | D27: 28 | E27: 11.648 | F27: 3 | G27: 0 | H27: =F27+G27 -> 3 | I27: 3 | J27: =H27-I27 -> 0 | K27: 0 | L27: =I27+K27 -> 3 | M27: 3 | N27: =L27-M27 -> 0 | O27: 0 | P27: =M27+O27 -> 3 | Q27: 3 | R27: =P27-Q27 -> 0 | T27: =Q27+S27 -> 3 | U27: 3 | V27: =U27+S27 -> 3 | X27: =V27+W27 -> 3 | Y27: 3 | Z27: =X27-Y27 -> 0 | AB27: =Y27+AA27 -> 3 | AC27: 3 | AD27: =AB27-AC27 -> 0 | AF27: =AC27+AE27 -> 3 | AG27: 3 | AH27: =AF27-AG27 -> 0 | AJ27: =AG27+AI27 -> 3 | AK27: 3 | AL27: =AJ27-AK27 -> 0 | AN27: =AK27+AM27 -> 3 | AR27: 2 | AT27: =AR27+AS27 -> 2 | AU27: 2 | AV27: =AT27-AU27 -> 0 | AX27: =AU27+AW27 -> 2 | AY27: 2 | AZ27: 2 | BA27: =AX27-AZ27 -> 0 | BC27: =AZ27+BB27 -> 2 | BE27: =BB27+AW27+AS27+AQ27+AO27+AM27+AJ27 -> 3
A28: Menabo | B28: DLKIT48G | C28: 000101700000 | D28: 28 | E28: 11.648 | F28: 2 | G28: 0 | H28: =F28+G28 -> 2 | I28: 2 | J28: =H28-I28 -> 0 | K28: 0 | L28: =I28+K28 -> 2 | M28: 2 | N28: =L28-M28 -> 0 | O28: 0 | P28: =M28+O28 -> 2 | Q28: 2 | R28: =P28-Q28 -> 0 | T28: =Q28+S28 -> 2 | U28: 2 | V28: =U28+S28 -> 2 | X28: =V28+W28 -> 2 | Y28: 1 | Z28: =X28-Y28 -> 1 | AB28: =Y28+AA28 -> 1 | AC28: 1 | AD28: =AB28-AC28 -> 0 | AF28: =AC28+AE28 -> 1 | AG28: 1 | AH28: =AF28-AG28 -> 0 | AJ28: =AG28+AI28 -> 1 | AK28: 1 | AL28: =AJ28-AK28 -> 0 | AN28: =AK28+AM28 -> 1 | AR28: 0 | AS28: 1 | AT28: =AR28+AS28 -> 1 | AU28: 1 | AV28: =AT28-AU28 -> 0 | AX28: =AU28+AW28 -> 1 | AY28: 1 | AZ28: 1 | BA28: =AX28-AZ28 -> 0 | BC28: =AZ28+BB28 -> 1 | BE28: =BB28+AW28+AS28+AQ28+AO28+AM28+AJ28 -> 2
A29: Menabo | B29: DLKIT49G | C29: 000105300000 | D29: 28 | E29: 11.648 | F29: 2 | G29: 0 | H29: =F29+G29 -> 2 | I29: 2 | J29: =H29-I29 -> 0 | K29: 0 | L29: =I29+K29 -> 2 | M29: 2 | N29: =L29-M29 -> 0 | O29: 0 | P29: =M29+O29 -> 2 | Q29: 2 | R29: =P29-Q29 -> 0 | T29: =Q29+S29 -> 2 | U29: 2 | V29: =U29+S29 -> 2 | X29: =V29+W29 -> 2 | Y29: 2 | Z29: =X29-Y29 -> 0 | AB29: =Y29+AA29 -> 2 | AC29: 2 | AD29: =AB29-AC29 -> 0 | AF29: =AC29+AE29 -> 2 | AG29: 2 | AH29: =AF29-AG29 -> 0 | AJ29: =AG29+AI29 -> 2 | AK29: 2 | AL29: =AJ29-AK29 -> 0 | AN29: =AK29+AM29 -> 2 | AR29: 2 | AT29: =AR29+AS29 -> 2 | AU29: 2 | AV29: =AT29-AU29 -> 0 | AX29: =AU29+AW29 -> 2 | AY29: 2 | AZ29: 2 | BA29: =AX29-AZ29 -> 0 | BC29: =AZ29+BB29 -> 2 | BE29: =BB29+AW29+AS29+AQ29+AO29+AM29+AJ29 -> 2
A30: Menabo | B30: DLKIT62G | AR30: 1 | AT30: =AR30+AS30 -> 1 | AU30: 1 | AV30: =AT30-AU30 -> 0 | AX30: =AU30+AW30 -> 1 | AY30: 2 | AZ30: 2 | BA30: =AX30-AZ30 -> -1 | BC30: =AZ30+BB30 -> 2 | BE30: =BB30+AW30+AS30+AQ30+AO30+AM30+AJ30 -> 0
A31: Menabo | B31: FOOT KIT DELT A ALU | C31: 000095300000 | D31: 39.5 | E31: 16.432 | F31: 42 | G31: 0 | H31: =F31+G31 -> 42 | I31: 20 | J31: =H31-I31 -> 22 | K31: 0 | L31: =I31+K31 -> 20 | M31: 10 | N31: =L31-M31 -> 10 | O31: 16 | P31: =M31+O31 -> 26 | Q31: 15 | R31: =P31-Q31 -> 11 | T31: =Q31+S31 -> 15 | U31: 8 | V31: =U31+S31 -> 8 | W31: 24 | X31: =V31+W31 -> 32 | Y31: 18 | Z31: =X31-Y31 -> 14 | AA31: 8 | AB31: =Y31+AA31 -> 26 | AC31: 19 | AD31: =AB31-AC31 -> 7 | AF31: =AC31+AE31 -> 19 | AG31: 11 | AH31: =AF31-AG31 -> 8 | AJ31: =AG31+AI31 -> 11 | AK31: 10 | AL31: =AJ31-AK31 -> 1 | AM31: 8 | AN31: =AK31+AM31 -> 18 | AO31: 16 | AQ31: 8 | AR31: 5 | AS31: 12 | AT31: =AR31+AS31 -> 17 | AU31: 13 | AV31: =AT31-AU31 -> 4 | AX31: =AU31+AW31 -> 13 | AY31: 7 | AZ31: 4 | BA31: =AX31-AZ31 -> 9 | BB31: 16 | BC31: =AZ31+BB31 -> 20 | BE31: =BB31+AW31+AS31+AQ31+AO31+AM31+AJ31 -> 71
A32: Menabo | B32: Leopard | C32: 000088700000 | D32: 131.5 | E32: 54.704 | F32: 7 | G32: 28 | H32: =F32+G32 -> 35 | I32: 17 | J32: =H32-I32 -> 18 | K32: 20 | L32: =I32+K32 -> 37 | M32: 2 | N32: =L32-M32 -> 35 | O32: 20 | P32: =M32+O32 -> 22 | Q32: 7 | R32: =P32-Q32 -> 15 | S32: 24 | T32: =Q32+S32 -> 31 | U32: 0 | V32: =U32+S32 -> 24 | W32: 12 | X32: =V32+W32 -> 36 | Y32: 11 | Z32: =X32-Y32 -> 25 | AA32: 24 | AB32: =Y32+AA32 -> 35 | AC32: 4 | AD32: =AB32-AC32 -> 31 | AE32: 28 | AF32: =AC32+AE32 -> 32 | AG32: 14 | AH32: =AF32-AG32 -> 18 | AI32: 16 | AJ32: =AG32+AI32 -> 30 | AK32: 0 | AL32: =AJ32-AK32 -> 30 | AM32: 32 | AN32: =AK32+AM32 -> 32 | AO32: 16 | AQ32: 20 | AR32: 6 | AT32: =AR32+AS32 -> 6 | AU32: 0 | AV32: =AT32-AU32 -> 6 | AW32: 28 | AX32: =AU32+AW32 -> 28 | AY32: 24 | AZ32: 22 | BA32: =AX32-AZ32 -> 6 | BB32: 8 | BC32: =AZ32+BB32 -> 30 | BE32: =BB32+AW32+AS32+AQ32+AO32+AM32+AJ32 -> 134
A33: Menabo | B33: Leopard L | C33: 000088600000 | D33: 140 | E33: 58.24 | F33: 16 | G33: 20 | H33: =F33+G33 -> 36 | I33: 13 | J33: =H33-I33 -> 23 | K33: 24 | L33: =I33+K33 -> 37 | M33: 17 | N33: =L33-M33 -> 20 | O33: 12 | P33: =M33+O33 -> 29 | Q33: 7 | R33: =P33-Q33 -> 22 | S33: 24 | T33: =Q33+S33 -> 31 | U33: 0 | V33: =U33+S33 -> 24 | W33: 12 | X33: =V33+W33 -> 36 | Y33: 13 | Z33: =X33-Y33 -> 23 | AA33: 24 | AB33: =Y33+AA33 -> 37 | AC33: 4 | AD33: =AB33-AC33 -> 33 | AE33: 28 | AF33: =AC33+AE33 -> 32 | AG33: 7 | AH33: =AF33-AG33 -> 25 | AI33: 24 | AJ33: =AG33+AI33 -> 31 | AK33: 11 | AL33: =AJ33-AK33 -> 20 | AM33: 24 | AN33: =AK33+AM33 -> 35 | AO33: 20 | AQ33: 20 | AR33: 10 | AS33: 20 | AT33: =AR33+AS33 -> 30 | AU33: 13 | AV33: =AT33-AU33 -> 17 | AW33: 16 | AX33: =AU33+AW33 -> 29 | AY33: 17 | AZ33: 15 | BA33: =AX33-AZ33 -> 14 | BB33: 16 | BC33: =AZ33+BB33 -> 31 | BE33: =BB33+AW33+AS33+AQ33+AO33+AM33+AJ33 -> 147
A34: Menabo | B34: Sherman | C34: 000095900000 | D34: 74.5 | E34: 30.992 | F34: 0 | G34: 18 | H34: =F34+G34 -> 18 | I34: 0 | J34: =H34-I34 -> 18 | K34: 18 | L34: =I34+K34 -> 18 | M34: 13 | N34: =L34-M34 -> 5 | O34: 6 | P34: =M34+O34 -> 19 | Q34: 6 | R34: =P34-Q34 -> 13 | S34: 12 | T34: =Q34+S34 -> 18 | U34: 1 | V34: =U34+S34 -> 13 | W34: 6 | X34: =V34+W34 -> 19 | Y34: 14 | Z34: =X34-Y34 -> 5 | AA34: 6 | AB34: =Y34+AA34 -> 20 | AC34: 14 | AD34: =AB34-AC34 -> 6 | AF34: =AC34+AE34 -> 14 | AG34: 7 | AH34: =AF34-AG34 -> 7 | AI34: 6 | AJ34: =AG34+AI34 -> 13 | AK34: 2 | AL34: =AJ34-AK34 -> 11 | AM34: 24 | AN34: =AK34+AM34 -> 26 | AP34: 14 | AQ34: 12 | AR34: 17 | AT34: =AR34+AS34 -> 17 | AU34: 14 | AV34: =AT34-AU34 -> 3 | AX34: =AU34+AW34 -> 14 | AY34: 8 | AZ34: 7 | BA34: =AX34-AZ34 -> 7 | BB34: 12 | BC34: =AZ34+BB34 -> 19 | BE34: =BB34+AW34+AS34+AQ34+AO34+AM34+AJ34 -> 61
A35: Menabo | B35: Sherman XL | C35: 000094700000 | D35: 84 | E35: 34.944 | F35: 7 | G35: 12 | H35: =F35+G35 -> 19 | I35: 3 | J35: =H35-I35 -> 16 | K35: 18 | L35: =I35+K35 -> 21 | M35: 0 | N35: =L35-M35 -> 21 | O35: 12 | P35: =M35+O35 -> 12 | Q35: 13 | R35: =P35-Q35 -> -1 | S35: 6 | T35: =Q35+S35 -> 19 | U35: 6 | V35: =U35+S35 -> 12 | W35: 6 | X35: =V35+W35 -> 18 | Y35: 6 | Z35: =X35-Y35 -> 12 | AA35: 12 | AB35: =Y35+AA35 -> 18 | AC35: 8 | AD35: =AB35-AC35 -> 10 | AE35: 6 | AF35: =AC35+AE35 -> 14 | AG35: 6 | AH35: =AF35-AG35 -> 8 | AI35: 6 | AJ35: =AG35+AI35 -> 12 | AK35: 1 | AL35: =AJ35-AK35 -> 11 | AM35: 18 | AN35: =AK35+AM35 -> 19 | AO35: 6 | AP35: 1 | AQ35: 12 | AR35: 13 | AS35: 6 | AT35: =AR35+AS35 -> 19 | AU35: 15 | AV35: =AT35-AU35 -> 4 | AX35: =AU35+AW35 -> 15 | AY35: 13 | AZ35: 12 | BA35: =AX35-AZ35 -> 3 | BB35: 6 | BC35: =AZ35+BB35 -> 18 | BE35: =BB35+AW35+AS35+AQ35+AO35+AM35+AJ35 -> 60
A36: Menabo | B36: Tiger Black | C36: 000085900000 | D36: 86.5 | E36: 35.984 | F36: 11 | G36: 12 | H36: =F36+G36 -> 23 | I36: 16 | J36: =H36-I36 -> 7 | K36: 8 | L36: =I36+K36 -> 24 | M36: 19 | N36: =L36-M36 -> 5 | O36: 0 | P36: =M36+O36 -> 19 | Q36: 15 | R36: =P36-Q36 -> 4 | T36: =Q36+S36 -> 15 | U36: 12 | V36: =U36+S36 -> 12 | W36: 6 | X36: =V36+W36 -> 18 | Y36: 6 | Z36: =X36-Y36 -> 12 | AA36: 12 | AB36: =Y36+AA36 -> 18 | AC36: 6 | AD36: =AB36-AC36 -> 12 | AE36: 12 | AF36: =AC36+AE36 -> 18 | AG36: 3 | AH36: =AF36-AG36 -> 15 | AI36: 12 | AJ36: =AG36+AI36 -> 15 | AK36: 5 | AL36: =AJ36-AK36 -> 10 | AM36: 12 | AN36: =AK36+AM36 -> 17 | AO36: 8 | AQ36: 12 | AR36: 0 | AT36: =AR36+AS36 -> 0 | AU36: 0 | AV36: =AT36-AU36 -> 0 | AW36: 24 | AX36: =AU36+AW36 -> 24 | AY36: 15 | AZ36: 15 | BA36: =AX36-AZ36 -> 9 | BB36: 8 | BC36: =AZ36+BB36 -> 23 | BE36: =BB36+AW36+AS36+AQ36+AO36+AM36+AJ36 -> 79
A37: Menabo | B37: Tiger Black XL | C37: 000086000000 | D37: 106 | E37: 44.096 | F37: 19 | G37: 4 | H37: =F37+G37 -> 23 | I37: 14 | J37: =H37-I37 -> 9 | K37: 8 | L37: =I37+K37 -> 22 | M37: 16 | N37: =L37-M37 -> 6 | O37: 0 | P37: =M37+O37 -> 16 | Q37: 11 | R37: =P37-Q37 -> 5 | S37: 4 | T37: =Q37+S37 -> 15 | U37: 3 | V37: =U37+S37 -> 7 | W37: 12 | X37: =V37+W37 -> 19 | Y37: 11 | Z37: =X37-Y37 -> 8 | AA37: 6 | AB37: =Y37+AA37 -> 17 | AC37: 2 | AD37: =AB37-AC37 -> 15 | AE37: 12 | AF37: =AC37+AE37 -> 14 | AG37: 0 | AH37: =AF37-AG37 -> 14 | AI37: 16 | AJ37: =AG37+AI37 -> 16 | AK37: 9 | AL37: =AJ37-AK37 -> 7 | AM37: 8 | AN37: =AK37+AM37 -> 17 | AO37: 16 | AQ37: 4 | AR37: 11 | AS37: 12 | AT37: =AR37+AS37 -> 23 | AU37: 19 | AV37: =AT37-AU37 -> 4 | AW37: 4 | AX37: =AU37+AW37 -> 23 | AY37: 18 | AZ37: 17 | BA37: =AX37-AZ37 -> 6 | BB37: 4 | BC37: =AZ37+BB37 -> 21 | BE37: =BB37+AW37+AS37+AQ37+AO37+AM37+AJ37 -> 64
A38: Menabo | B38: Lince | AM38: 4 | AN38: =AK38+AM38 -> 4 | AQ38: 4 | AR38: 4 | AT38: =AR38+AS38 -> 4 | AU38: 3 | AV38: =AT38-AU38 -> 1 | AW38: 4 | AX38: =AU38+AW38 -> 7 | AY38: 8 | AZ38: 6 | BA38: =AX38-AZ38 -> 1 | BC38: =AZ38+BB38 -> 6 | BE38: =BB38+AW38+AS38+AQ38+AO38+AM38+AJ38 -> 12
A39: Menabo | B39: Lince XL | C39: 000088800000 | D39: 148 | E39: 61.568 | F39: 3 | G39: 4 | H39: =F39+G39 -> 7 | I39: 5 | J39: =H39-I39 -> 2 | K39: 0 | L39: =I39+K39 -> 5 | M39: 2 | N39: =L39-M39 -> 3 | O39: 4 | P39: =M39+O39 -> 6 | Q39: 0 | R39: =P39-Q39 -> 6 | S39: 8 | T39: =Q39+S39 -> 8 | U39: 0 | V39: =U39+S39 -> 8 | X39: =V39+W39 -> 8 | Y39: 9 | Z39: =X39-Y39 -> -1 | AB39: =Y39+AA39 -> 9 | AC39: 1 | AD39: =AB39-AC39 -> 8 | AE39: 4 | AF39: =AC39+AE39 -> 5 | AG39: 0 | AH39: =AF39-AG39 -> 5 | AI39: 4 | AJ39: =AG39+AI39 -> 4 | AK39: 1 | AL39: =AJ39-AK39 -> 3 | AM39: 8 | AN39: =AK39+AM39 -> 9 | AP39: 2 | AQ39: 4 | AR39: 0 | AS39: 8 | AT39: =AR39+AS39 -> 8 | AU39: 3 | AV39: =AT39-AU39 -> 5 | AW39: 4 | AX39: =AU39+AW39 -> 7 | AY39: 5 | AZ39: 4 | BA39: =AX39-AZ39 -> 3 | BB39: 4 | BC39: =AZ39+BB39 -> 8 | BE39: =BB39+AW39+AS39+AQ39+AO39+AM39+AJ39 -> 32
A40: Menabo | B40: Jackson | D40: 82 | E40: 34.112 | Q40: 0 | R40: =P40-Q40 -> 0 | S40: 4 | T40: =Q40+S40 -> 4 | U40: 0 | V40: =U40+S40 -> 4 | W40: 8 | X40: =V40+W40 -> 12 | Y40: 12 | Z40: =X40-Y40 -> 0 | AB40: =Y40+AA40 -> 12 | AC40: 9 | AD40: =AB40-AC40 -> 3 | AF40: =AC40+AE40 -> 9 | AG40: 6 | AH40: =AF40-AG40 -> 3 | AI40: 4 | AJ40: =AG40+AI40 -> 10 | AK40: 4 | AL40: =AJ40-AK40 -> 6 | AM40: 8 | AN40: =AK40+AM40 -> 12 | AO40: 4 | AP40: 3 | AQ40: 4 | AR40: 0 | AS40: 12 | AT40: =AR40+AS40 -> 12 | AU40: 9 | AV40: =AT40-AU40 -> 3 | AW40: 4 | AX40: =AU40+AW40 -> 13 | AY40: 9 | AZ40: 9 | BA40: =AX40-AZ40 -> 4 | BB40: 4 | BC40: =AZ40+BB40 -> 13 | BE40: =BB40+AW40+AS40+AQ40+AO40+AM40+AJ40 -> 46
A41: Menabo | B41: Jackson XL | D41: 91 | E41: 37.856 | Q41: 0 | R41: =P41-Q41 -> 0 | S41: 4 | T41: =Q41+S41 -> 4 | U41: 0 | V41: =U41+S41 -> 4 | W41: 8 | X41: =V41+W41 -> 12 | Y41: 10 | Z41: =X41-Y41 -> 2 | AB41: =Y41+AA41 -> 10 | AC41: 5 | AD41: =AB41-AC41 -> 5 | AE41: 4 | AF41: =AC41+AE41 -> 9 | AG41: 0 | AH41: =AF41-AG41 -> 9 | AI41: 12 | AJ41: =AG41+AI41 -> 12 | AK41: 3 | AL41: =AJ41-AK41 -> 9 | AM41: 8 | AN41: =AK41+AM41 -> 11 | AO41: 4 | AQ41: 4 | AR41: 1 | AS41: 12 | AT41: =AR41+AS41 -> 13 | AU41: 11 | AV41: =AT41-AU41 -> 2 | AW41: 4 | AX41: =AU41+AW41 -> 15 | AY41: 10 | AZ41: 7 | BA41: =AX41-AZ41 -> 8 | BB41: 8 | BC41: =AZ41+BB41 -> 15 | BE41: =BB41+AW41+AS41+AQ41+AO41+AM41+AJ41 -> 52
A42: Summa | G42: =SUM(G2:G39) -> 100 | K42: =SUM(K2:K39) -> 110 | O42: =SUM(O2:O39) -> 98 | R42: =P42-Q42 -> 0 | S42: =SUM(S2:S41) -> 102 | T42: =Q42+S42 -> 102 | AB42: =Y42+AA42 -> 0 | AD42: =AB42-AC42 -> 0
R43: =P43-Q43 -> 0 | T43: =Q43+S43 -> 0 | AB43: =Y43+AA43 -> 0 | AD43: =AB43-AC43 -> 0
A44: Skid och Cykelhållare | R44: =P44-Q44 -> 0 | T44: =Q44+S44 -> 0 | AB44: =Y44+AA44 -> 0 | AD44: =AB44-AC44 -> 0
A45: Menabo | B45: Iceberg | C45: 000071800000 | M45: 30 | N45: =#REF!-M45 -> #REF! | O45: 0 | P45: =M45+O45 -> 30 | Q45: 28 | R45: =P45-Q45 -> 2 | T45: =Q45+S45 -> 28 | Y45: 28 | AB45: =Y45+AA45 -> 28 | AC45: 24 | AD45: =AB45-AC45 -> 4
A46: Menabo | B46: Frozen Plus | C46: 000079100000 | M46: 13 | N46: =#REF!-M46 -> #REF! | O46: 0 | P46: =M46+O46 -> 13 | Q46: 15 | R46: =P46-Q46 -> -2 | T46: =Q46+S46 -> 15 | Y46: 12 | AB46: =Y46+AA46 -> 12 | AC46: 2 | AD46: =AB46-AC46 -> 10
A47: Menabo | B47: Silver Ice | C47: 000014700000 | M47: 2 | N47: =#REF!-M47 -> #REF! | O47: 0 | P47: =M47+O47 -> 2 | Q47: 2 | R47: =P47-Q47 -> 0 | T47: =Q47+S47 -> 2 | Y47: 2 | AB47: =Y47+AA47 -> 2 | AC47: 1 | AD47: =AB47-AC47 -> 1
A48: Menabo | B48: Acocagua | C48: 000008500000 | M48: 0 | N48: =#REF!-M48 -> #REF! | O48: 0 | P48: =M48+O48 -> 0 | R48: =P48-Q48 -> 0 | T48: =Q48+S48 -> 0 | AB48: =Y48+AA48 -> 0 | AD48: =AB48-AC48 -> 0
A49: Menabo | B49: Himalaya | C49: 000007800000 | M49: 0 | N49: =#REF!-M49 -> #REF! | O49: 0 | P49: =M49+O49 -> 0 | R49: =P49-Q49 -> 0 | T49: =Q49+S49 -> 0 | AB49: =Y49+AA49 -> 0 | AD49: =AB49-AC49 -> 0
B50: Lås 30 st typ | O50: 0 | P50: =M50+O50 -> 0 | R50: =P50-Q50 -> 0 | T50: =Q50+S50 -> 0 | AB50: =Y50+AA50 -> 0 | AD50: =AB50-AC50 -> 0
A51: Menabo | B51: Juza | C51: 000081000000 | O51: 4 | P51: =M51+O51 -> 4 | Q51: 3 | R51: =P51-Q51 -> 1 | T51: =Q51+S51 -> 3 | Y51: 1 | AB51: =Y51+AA51 -> 1 | AC51: 1 | AD51: =AB51-AC51 -> 0 | AK51: 1 | AM51: 4 | AN51: =AK51+AM51 -> 5
A52: Menabo | B52: Yelo | O52: 4 | P52: =M52+O52 -> 4 | Q52: 4 | R52: =P52-Q52 -> 0 | T52: =Q52+S52 -> 4 | Y52: 4 | AB52: =Y52+AA52 -> 4 | AC52: 4 | AD52: =AB52-AC52 -> 0
A55: Spareparts
A56: Menabo | B56: Lock Tiger/Leopard/Delta | C56: 000084800000 | D56: 10 | E56: 4.16 | S56: 10 | AK56: 0 | AM56: 10 | AN56: =AK56+AM56 -> 10
A57: Menabo | B57: T-Screws (Mixed) | C57: 000110100000 | S57: 10 | AA57: 10 | AK57: 5 | AM57: 10 | AN57: =AK57+AM57 -> 15

Sheet Lager LED-ljus
A1: Artikelnummer | B1: Alternativt artikelnummer? | C1: Från | D1: Antal | E1: Rak / Curved | F1: Mottaget | G1: BarCode | H1: Övrigt | I1: Driftspänning | J1: Styrka | K1: Längd | L1: Antal LED-lampor | M1: Chip | N1: Material | O1: Lins | P1: Stråle | Q1: Vattentålighetsklassificering | R1: Färg | S1: Färgtemperatur | T1: Livstid
A2: MK-02A-120K3 | B2: MK2120 | C2: Tyskland | D2: 10 | E2: Rak | F2: Vecka 49 | G2: 902001279046 | I2: 10-30V (DC) | J2: 120W | K2: 56 cm | L2: 40 | M2: Epistar | N2: Aluminium | O2: PC | P2: Riktad/Spridd | Q2: IP 67 | R2: Svart | S2: ca 6000 K | T2: ca 30 000 timmar
A3: MK-01A-126K3 | B3: MK2060 | C3: Tyskland | D3: 10 | E3: Rak | F3: Vecka 51 | G3: 602168335132 | H3: Beställt dessa?? | I3: 10-30V (DC) | J3: 126W | K3: 51 cm | L3: 42 | M3: Cree | N3: Aluminium | O3: PC | P3: Riktad/Spridd | Q3: IP 67 | R3: Svart | S3: ca 6000 K | T3: ca 30 000 timmar
A4: MK-02C-120K3 | D4: 10 | E4: Curved
A5: MK-03S-018K3 | C5: Kina | D5: 1
A6: MK-03S-090K3 | C6: Kina | D6: 1
A7: MK-01A-018K4 | C7: Kina | D7: 5
A8: MK-01A-018K3 | C8: Kina | D8: 15

Sheet Företagskunder & Potentiella fö
B1: Datum | C1: Namn | D1: Adress | E1: Postnr | F1: Ort | G1: Telefon | H1: E-post | I1: Konaktperson | J1: Övrigt | K1: Typ av företag | L1: Omsättning TKR | M1: Kund/potentiell kund | N1: Besök, datum | O1: Avtal | P1: Övrigt 1 | Q1: Övrigt 2 | R1: Övrigt 3 | S1: Utskick 16-12-01 | T1: Utskick 17-04-01
B2: 42705 | C2: Larssons Bil i Kalmar AB | E2: 39243 | F2: Kalmar | H2: verkstad@larssonsbil.com | M2: Potentiell Kund | S2: x | AL2: Potentiell Kund
B3: 42705 | C3: Speedy bilservice | D3: Cederströms slinga, Eurostop 195 61 | F3: Arlandastad | G3: 08-59121688 | M3: Potentiell Kund | S3: x | AL3: Kund
B4: 42705 | C4: Kent Skoog Bilservice AB - MECA | E4: 23237 | F4: ARLÖV | H4: kent@kentskoog.se | M4: Potentiell Kund | S4: x
B5: 42705 | C5: Min bil Bandhagen | E5: 12459 | F5: Bandhagen | H5: bandhagen@minbil.se | M5: Potentiell Kund | S5: x
B6: 42705 | C6: Speedy bilservice | D6: Rågsvedsvägen 6 | E6: 12450 | F6: BANDHAGEN | G6: 08-99 23 80 | M6: Potentiell Kund | S6: x
B7: 42705 | C7: Blentarps Däck o Mek AB | E7: 27035 | F7: Blentarp | H7: dackmek@telia.com | M7: Potentiell Kund | S7: x
B8: 42705 | C8: Finnvedens Autolack & Karosseri AB | E8: 33015 | F8: BOR | H8: finnvedensautolack@telia.com | M8: Potentiell Kund | S8: x
B9: 42705 | C9: Bilpunkten | E9: 50711 | F9: Borås | H9: ss@bilpunktenboras.se | M9: Potentiell Kund | T9: x
B10: 42705 | C10: Glada Bilen | E10: 50752 | F10: Borås | H10: kontakt@gladabilen.se | M10: Blivit kund | T10: x
B11: 42705 | C11: LH Larsson Bilverkstad | E11: 50462 | F11: Borås | H11: larssons.bilverkstad@adbilverkstad.se | M11: Potentiell Kund | T11: x
B12: 42705 | C12: Nybrons Bilservice | E12: 50435 | F12: Borås | H12: info@nybronsbilservice.se | M12: Potentiell Kund | T12: x
B13: 42705 | C13: Grahns bil & service | E13: 28060 | F13: Broby | H13: anders.andersson@grahnsbilar.se | M13: Potentiell Kund | S13: x
B14: 42705 | C14: Automek Bromma | E14: 16867 | F14: Bromma | H14: info@automekbromma.se | M14: Potentiell Kund | S14: x
B15: 42705 | C15: Bromma däck & bilservice AB | E15: 16865 | F15: Bromma | H15: brommadack@gmail.com | M15: Potentiell Kund | S15: x
B16: 42705 | C16: Jattes bil & Motor | E16: 26936 | F16: Båstad | H16: jattesbil.motor@gmail.com | M16: Potentiell Kund | T16: x
B17: 42705 | C17: Dalsjöfors Bilverkstad | E17: 51633 | F17: Dalsjöfors | H17: dalsjoforsbilverkstad@autoexperten.se | M17: Potentiell Kund | T17: x
B18: 42705 | C18: Danderyds Bilverkstad | E18: 18236 | F18: Danderyd | H18: Info@danderydsbilverkstad.se | M18: Potentiell Kund | S18: x
B19: 42705 | C19: Degeberga Servicestation | E19: 29731 | F19: Degeberga | H19: degeberga@adbilverkstad.se | M19: Potentiell Kund | S19: x
B20: 42705 | C20: Aise 4 U Bilverkstad | E20: 41458 | F20: Göteborg | H20: info@aisbilanddack.se | M20: Potentiell Kund | S20: x
B21: 42705 | C21: BRAB Autoservice - Autoexperten | E21: 41705 | F21: Göteborg | G21: 031-730 32 46 | M21: Potentiell Kund | S21: x
B22: 42705 | C22: Carlyft Sweden AB | E22: 41707 | F22: Göteborg | M22: Potentiell Kund | S22: x
B23: 42705 | C23: Höglund Motorsport AB | E23: 42537 | F23: Göteborg | H23: info@hoglundmotorsport.se | M23: Potentiell Kund | S23: x
B24: 42705 | C24: Autodena AB - ServiceCenter | E24: 30241 | F24: Halmstad | H24: info@autodena.se | M24: Potentiell Kund | S24: x
B25: 42705 | C25: Sture Nilssons Bil AB | E25: 27650 | F25: Hammenhög | G25: 0414-44 08 25 | M25: Potentiell Kund | S25: x
B26: 42705 | C26: Min bil Haninge | E26: 13674 | F26: Haninge | H26: haninge@minbil.se | M26: Potentiell Kund | S26: x
B27: 42705 | C27: Autoteknik H Holmqvist AB, | E27: 25466 | F27: Helsingborg | H27: ab.autoteknik@telia.com | M27: Potentiell Kund | S27: x
B28: 42705 | C28: Jarls Bilservice | E28: 25450 | F28: Helsingborg | H28: info@jarlsbilservice.com | M28: Potentiell Kund | S28: x
B29: 42705 | C29: Kinch Bil AB Toyota Center | E29: 25466 | F29: Helsingborg | H29: info@toyotahelsingborg.se | M29: Potentiell Kund | S29: x
B30: 42705 | C30: Speedy bilservice | D30: Gåsebäcksvägen 12 | E30: 25227 | F30: HELSINGBORG | G30: 042-13 25 50 | M30: Potentiell Kund | S30: x
B31: 42705 | C31: Västra Berga Rostskyddshall AB - AD Bilverkstad | E31: 25468 | F31: Helsingborg | H31: svenskbilvard@hotmail.com | M31: Potentiell Kund | S31: x
B32: 42705 | C32: Biltronic OKQ8 Bilverkstad Bäckebol | E32: 42246 | F32: Hisings Backa | G32: 031-52 65 25 | M32: Potentiell Kund | S32: x
B33: 42705 | C33: BVV Autoservice | E33: 42255 | F33: Hisings Backa | H33: info@bvvbil.se | M33: Potentiell Kund | S33: x
B34: 42705 | C34: Familjebilar i Göteborg AB | E34: 42243 | F34: Hisings Backa | H34: rickard.fagefors@familjebilar.se | M34: Potentiell Kund | S34: x
B35: 42705 | C35: Bil & motorteknink | E35: 14146 | F35: Huddinge | H35: info@bilmotorteknik.se | M35: Potentiell Kund | S35: x
B36: 42705 | C36: Speedy bilservice | D36: Björkholmsvägen 17 | E36: 14146 | F36: Huddinge | G36: 08-7110820 | M36: Potentiell Kund | S36: x
B37: 42705 | C37: Speedy bilservice | D37: Västberga allé 50 | E37: 12630 | F37: HÄGERSTEN | G37: 08-191313 | M37: Potentiell Kund | S37: x
B38: 42705 | C38: Speedy bilservice | D38: Elsa Brändströms gata 201 129 52 | F38: Hägersten | M38: Potentiell Kund | S38: x
B39: 42705 | C39: Dahlqvists Bil AB - Hässleholm | F39: Hässleholm | G39: 0451-74 55 50 | M39: Potentiell Kund | S39: x
B40: 42705 | C40: Höganäs Bilservice AB | E40: 26337 | F40: Höganäs | H40: info@hoganas-bilservice.se | M40: Potentiell Kund | S40: x
B41: 42705 | C41: Höja Bil & Motor AB | E41: 17543 | F41: Järfälla | H41: hoja@boschcarservice.se | M41: Potentiell Kund | S41: x
B42: 42705 | C42: Motordepån AB - MECA | E42: 17562 | F42: Järfälla | H42: motordepan@motordepan.se | M42: Potentiell Kund | S42: x
B43: 42705 | C43: Speedy bilservice | D43: Datavägen 10 | E43: 17543 | F43: JÄRFÄLLA | G43: 08-12140410 | M43: Potentiell Kund | S43: x
B44: 42705 | C44: Asarums Motorservice | D44: Stillmansväg 4 | E44: 37493 | F44: Karlshamn | G44: 0454-32 02 19 | M44: Potentiell Kund | S44: x
B45: 42705 | C45: Automotor i Karlstad Bil Service AB | E45: 65346 | F45: Karlstad | H45: automotor.karlstad@hotmail.com | M45: Potentiell Kund | S45: x
B46: 42705 | C46: Autopulsen | E46: 29162 | F46: Kristianstad | G46: 044-213101 | M46: Potentiell Kund | S46: x
B47: 42705 | C47: Autopulsen | E47: 29162 | F47: Kristianstad | H47: 044-213101 | M47: Potentiell Kund | S47: x
B48: 42705 | C48: OKQ8 Bilverkstad Kungsbacka | E48: 43437 | F48: Kungsbacka | H48: 37947@station.okq8.se | M48: Potentiell Kund | S48: x
B49: 42705 | C49: Madsens Autoteknik | E49: 31232 | F49: Laholm | G49: 0430 - 122 40 | M49: Potentiell Kund | S49: x
B50: 42705 | C50: Kinch Bil Landskrona | F50: Landskrona | H50: info@toyotalandskrona.se | M50: Potentiell Kund | S50: x
B51: 42705 | C51: Mårtenssons Bil AB | E51: 26151 | F51: Landskrona | G51: 0418 - 561 50 | M51: Potentiell Kund | S51: x
B52: 42705 | C52: Tommy bilverkstad | E52: 26142 | F52: Landskrona | G52: 0418-23791 | M52: Potentiell Kund | S52: x
B53: 42705 | C53: Sjöbergs Bilverkstad AB | E53: 56196 | F53: Lekeryd | H53: sjobergs.bilverkstad@telia.com | M53: Potentiell Kund | S53: x
B54: 42705 | C54: Fröjds Motor AB | E54: 36050 | F54: Lessebo | H54: sven-olof@frojdsmotor.se (VD) | M54: Potentiell Kund | S54: x
B55: 42705 | C55: A. Engmans Bilservice AB | E55: 53130 | F55: Lidköping | H55: engmansbilservice@telia.com | M55: Potentiell Kund | S55: x
B56: 42705 | C56: Bil Allt | E56: 53133 | F56: Lidköping | H56: bilallt@telia.com | M56: Potentiell Kund | T56: x
B57: 42705 | C57: Ingavr Ivarssons Bilverkstad | E57: 53196 | F57: Lidköping | H57: bilverkstad@ingvarivarsson.se | M57: Potentiell Kund | T57: x
B58: 42705 | C58: Lidbil | E58: 53119 | F58: Lidköping | H58: mikael.karlsson2@lidbil.se | M58: Potentiell Kund | T58: x
B59: 42705 | C59: Lidköpings biltjänst | E59: 53140 | F59: Lidköping | H59: tony@biltjanst.se | M59: Potentiell Kund | T59: x
B60: 42705 | C60: Lidköpings Fordonsteknik AB | E60: 53197 | F60: Lidköping | H60: johan@fordonsteknik.eu | M60: Potentiell Kund | T60: x
B61: 42705 | C61: Lovene Bil o Lantbruks Service/Autoexperten | E61: 53196 | F61: Lidköping | H61: info@lovenebil.se | M61: Potentiell Kund | T61: x
B62: 42705 | C62: Pers verkstad | E62: 53133 | F62: Lidköping | H62: laga@persverkstad.se | M62: Potentiell Kund | T62: x
B63: 42702 | C63: BR Hörlings Bilservice AB / Meca | D63: Jägarvallsvägen 6 | E63: 58422 | F63: Linköping | H63: horlings@telia.com | M63: Potentiell Kund | T63: x
B64: 42702 | C64: Tornby Bilteknik | D64: Vigfastgatan 3A | F64: Linköping | H64: info@tornbybilteknik.com | M64: Potentiell Kund | T64: x
B65: 42705 | C65: AB LOMMA BILVERKSTAD | E65: 23421 | F65: Lomma | H65: lommabilverkstad@telia.com | K65: Bilverkstad | M65: Potentiell Kund | S65: x
B66: 42705 | C66: Speedy bilservice | D66: Annedalsvägen 9 | E66: 22764 | F66: LUND | G66: 046-14 22 20 | M66: Potentiell Kund | S66: x
B67: 42705 | C67: Dennis & Stefans Bilservice AB | E67: 21455 | F67: Malmö | H67: dsbilservice@telia.com | M67: Potentiell Kund | S67: x
B68: 42705 | C68: HelaBilen | E68: 21124 | F68: Malmö | H68: info@helabilen.se | M68: Potentiell Kund | S68: x
B69: 42705 | C69: Mekodelar Sverige AB | E69: 21376 | F69: Malmö | G69: 040-93 96 99 | M69: Potentiell Kund | S69: x
B70: 42705 | C70: MMC Malmö AB | E70: 21375 | F70: Malmö | H70: ho@mmcmalmo.se hl@mmcmalmo.se | M70: Potentiell Kund | S70: x
B71: 42705 | C71: Speedy bilservice | D71: Cypressvägen 10 A | E71: 21363 | F71: MALMÖ | G71: 040-22 40 40 | M71: Potentiell Kund | S71: x
B72: 42705 | C72: Vianor - Malmö Eriksfältsgatan | E72: 21432 | F72: Malmö | H72: malmo50@vianor.com | M72: Potentiell Kund | S72: x
B73: 42692 | C73: Annasbilar AB | D73: Kyrkvägen 3 66060 Molkom | E73: 660 60 | F73: Molkom | H73: annasbilar@gmail.com | K73: Bilhandlare | M73: Kund | O73: Fri frakt, oavsett mail, telefon eller nätet //TC
B74: 42705 | C74: S.A Bil & Maskin | E74: 26632 | F74: Munka ljungby | H74: sabilomaskin@adbilverkstad.se | M74: Potentiell Kund | S74: x
B75: 42705 | C75: Tage Johansson Bil | E75: 51677 | F75: Målsryd | H75: nfo@tagejohanssonbil.se | L75: 67 234 | M75: Potentiell Kund | T75: x
B76: 42705 | C76: Bo & Jimmy Bilservice AB | E76: 43135 | F76: Mölndal | H76: bayerische@telia.com | M76: Potentiell Kund | S76: x
B77: 42705 | C77: Carpros Verkstad | E77: 43130 | F77: Mölndal | H77: Info@carpros.se | M77: Potentiell Kund | S77: x
B78: 42705 | C78: Speedy bilservice | D78: Södra Ågatan 20B | E78: 43135 | F78: Mölndal | G78: 031-270430 | M78: Potentiell Kund | S78: x
B79: 42705 | C79: Bil & maskinexperten | E79: 43537 | F79: Mölnlycke | H79: info@bil-maskinexperten.se | M79: Potentiell Kund | S79: x
B80: 42705 | C80: MLS Bil & Däck | E80: 43533 | F80: Mölnycke | H80: info@mls.se | M80: Potentiell Kund | S80: x
B81: 42705 | C81: Speedy bilservice | D81: Vattenverksvägen 4 | E81: 13141 | F81: NACKA | G81: 08-718 37 20 | M81: Potentiell Kund | S81: x
B82: 42705 | C82: Auto Svärtinge | D82: Kiselgatan 27 | E82: 602 23 | F82: Norrköping | G82: 011-100183 0730-401096 | I82: Mujo | M82: Kund | O82: 10% rabatt, fri frakt | P82: Meddelat rabatt 161201 //TC
B83: 42705 | C83: Höglandets Bilservice AB | E83: 57140 | F83: Nässjö | G83: 0380-198 00 | M83: Potentiell Kund | S83: x
B84: 42705 | C84: Preem Nässjö | E84: 57140 | F84: Nässjö | G84: 0380-148 90 | M84: Potentiell Kund | S84: x
B85: 42705 | C85: Autoservice Europa | E85: 43333 | F85: Partille | G85: 031-443040 | M85: Potentiell Kund | S85: x
B86: 42705 | C86: Nya Skara Bilverkstad | E86: 53237 | F86: Skara | H86: Simon@skarabil.com | M86: Potentiell Kund | T86: x
B87: 42705 | C87: Skara Autoservice | E87: 53237 | F87: Skara | H87: toni@skaraautoservice.se | M87: Potentiell Kund | T87: x
B88: 42705 | C88: Björkholm Bil AB | E88: 54142 | F88: Skövde | G88: 0500-49 34 00 | M88: Potentiell Kund | S88: x
B89: 42705 | C89: Lindströms Bilel & Diesel - Bosch Car Service | E89: 54125 | F89: Skövde | H89: info@lindstromsbilel.com | M89: Potentiell Kund | S89: x
B90: 42705 | C90: Vianor - Skövde | E90: 54134 | F90: Skövde | G90: 0771-16 33 33 (ett nr till alla verkstäder) | M90: Potentiell Kund | S90: x
B91: 42705 | C91: Min bil Sollentuna | E91: 19254 | F91: Sollentuna | H91: sollentuna@minbil.se | M91: Potentiell Kund | S91: x
B92: 42705 | C92: Speedy bilservice | D92: Västra Vägen 13 | E92: 16961 | F92: SOLNA | G92: 08-730 11 75 | M92: Potentiell Kund | S92: x
B93: 42705 | C93: Autohallen AB | E93: 444 31 | F93: Stenungsund | H93: tommy.autohallen.se | M93: Potentiell Kund | T93: x
B94: 42705 | C94: Brav AB - BDS | E94: 11445 | F94: Stockholm | H94: info@bds.se | M94: Potentiell Kund | S94: x
B95: 42705 | C95: Geting Däck & Bilservice | E95: 11863 | F95: Stockholm | H95: info@geting-bilservice.se | M95: Potentiell Kund | S95: x
B96: 42705 | C96: Kihlströms Bilverkstad AB | E96: 11743 | F96: Stockholm | H96: info@kihlströms.se | M96: Potentiell Kund | S96: x
B97: 42705 | C97: KW Bilservice | F97: Stockholm | H97: info@kwbilservice.se | M97: Potentiell Kund | S97: x
B98: 42705 | C98: ServiceSpecialisten | E98: 11355 | F98: Stockholm | H98: info@servicespecialisten.se | M98: Potentiell Kund | S98: x
B99: 42705 | C99: ServiceSpecialisten | E99: 11355 | F99: Stockholm | H99: info@servicespecialisten.se | M99: Potentiell Kund | S99: x
B100: 42705 | C100: Speedy bilservice | D100: Valhallavägen 161 | E100: 11553 | F100: STOCKHOLM | G100: 08-662 40 45 | M100: Potentiell Kund | S100: x
...

Sheet Följ upp Leads
A1: Datum | B1: HL | C1: HL | D1: HL | E1: FP | F1: FP | G1: FP | H1: TC | I1: TC | J1: TC
A2: 43490 | B2: yencor1977@hotmail.com | C2: patrik.linno@gmail.com | D2: ketto.avila@gmail.com | E2: larsson.ramkvist@outlook.com | F2: josefkapasi@hotmail.com | G2: ola.johansson@rivexpress.se | H2: kimbeligantol1996@gmail.com | I2: william.humes@falun.se | J2: bigganlarsson@live.com
A3: 43491 | H3: hasjoberg@gmail.com
A4: 43492
A5: 43493 | B5: joawag65@gmail.com | C5: joelj@live.se | D5: elmirlindov@gmail.com | E5: bjorn.norlin@hotmail.com | F5: matsjagerud@hotmail.com | G5: hans.waglof@outlook.com | H5: hasjoberg@gmail.com | I5: bjorn.burmeister@hotmail.com | J5: jesper@asphill.com
A6: 43494 | B6: magnus.03692138@telia.com | C6: chrille1966@gmail.com | D6: michaelsvensson@tele2.se | E6: apek.h@hotmail.com | H6: elin_axel@hotmail.com | I6: stefanhedin64@gmail.com | J6: luis_rods@hotmail.com
A7: 43495 | B7: adej_@hotmail.com | C7: sapphoo_@hotmail.com | D7: christer.neanro@elektroskandia.se | H7: kjonsson84@gmail.com | I7: palle.win@gmail.com | J7: jeanette_robertsson@yahoo.se
A8: 43496 | B8: robert.nymo@afconsult.com | C8: patrikviggen@karlstad.se | D8: lundberg.emil1990@gmail.com | H8: alexander@cederschiold.com | I8: peter.ylisuvanto@gmail.com | J8: janali_22@icloud.com
A9: 43497
A10: 43498
A11: 43499
A12: 43500
A13: 43501
A14: 43502
A15: 43503
A16: 43504
A17: 43505
A18: 43506
A19: 43507 | H19: m_malmskold@yahoo.se
A20: 43508
A21: 43509
A22: 43510
A23: 43511
A24: 43512
A25: 43513
A26: 43514
A27: 43515 | H27: marcus.lindkvist24@gmail.com | I27: pellespersson@hotmail.com | J27: ann-sofie.grahn@hotmail.com
A28: 43516 | H28: dieter_hofer@hotmail.com | I28: kvn73@hotmail.com | J28: sven_hoglund@hotmail.com
A29: 43517
A30: 43518
A31: 43519
A32: 43520
A33: 43521
A34: 43522
A35: 43523
A36: 43524
A37: 43525
A38: 43526
A39: 43527
A40: 43528
... A250: 43738
A251: 43739 | H251: NLA149 | I251: Fmf535 | J251: hnj974
A252: 43740 | H252: ESP763 | I252: OOU169
A253: 43741 | G253: BJM646
A254: 43742 | E254: Henrik Josefsson | F254: PKY053 | G254: MTE370
A255: 43743 | E255: stj 176 | F255: Sfz99 | G255: yed017
A256: 43744 | E256: PUW413 | F256: AHZ83P | G256: KSU539
A257: 43745 | E257: OJF724 | F257: CPN04J | G257: xsk802 | H257: JLF319 | I257: Lcu601 | J257: sportputte@hotmail.com
A258: 43746
A259: 43747 | H259: MBE185 | I259: Clm010 | J259: EFM930
A260: 43748
A261: 43749 | E261: DLW963 | F261: HZL902 | G261: Torben Carlsen
A262: 43750 | E262: FSY174 | F262: GMY340 | G262: JWB493
A263: 43751 | E263: Morten Överbye | F263: OTY030 | G263: Bjb989
A264: 43752 | E264: OJA672 | F264: BS21127
A265: 43753
A266: 43754
A267: 43755
A268: 43756
A269: 43757
A270: 43758
A271: 43759
A272: 43760
A273: 43761
A274: 43762
A275: 43763
A276: 43764
... A438: 43926

Sheet Telefonstat
A1: Datum | B1: Alla, antal | C1: Missade, antal | D1: Vidarekopp, antal | E1: Besvarade, antal | F1: Antal Försäljning | G1: Antal Support | H1: Antal sälj telefon | J1: Procentuell del besvarade | K1: Procentuell del missade | L1: Procentuell del vidarekopplade | M1: Andel Försäljning | N1: Andel Support | O1: Andel sälj/säljsamtal
A2: 43719 | B2: 204 | C2: 32 | D2: 12 | E2: 160 | J2: =E2/B2 -> 0.78431373 | K2: =C2/B2 -> 0.15686275 | L2: =D2/B2 -> 0.058823529
A3: 43720 | B3: 197 | C3: 32 | D3: 13 | E3: 152 | J3: =E3/B3 -> 0.7715736 | K3: =C3/B3 -> 0.16243655 | L3: =D3/B3 -> 0.065989848
A4: 43721 | J4: =E4/B4 -> #DIV/0! | K4: =C4/B4 -> #DIV/0! | L4: =D4/B4 -> #DIV/0!
A5: 43722 | J5: =E5/B5 -> #DIV/0! | K5: =C5/B5 -> #DIV/0! | L5: =D5/B5 -> #DIV/0!
A6: 43723 | J6: =E6/B6 -> #DIV/0! | K6: =C6/B6 -> #DIV/0! | L6: =D6/B6 -> #DIV/0!
A7: 43724 | J7: =E7/B7 -> #DIV/0! | K7: =C7/B7 -> #DIV/0! | L7: =D7/B7 -> #DIV/0!
A8: 43725 | J8: =E8/B8 -> #DIV/0! | K8: =C8/B8 -> #DIV/0! | L8: =D8/B8 -> #DIV/0!
A9: 43726 | J9: =E9/B9 -> #DIV/0! | K9: =C9/B9 -> #DIV/0! | L9: =D9/B9 -> #DIV/0!
A10: 43727 | J10: =E10/B10 -> #DIV/0! | K10: =C10/B10 -> #DIV/0! | L10: =D10/B10 -> #DIV/0!
A11: 43728 | J11: =E11/B11 -> #DIV/0! | K11: =C11/B11 -> #DIV/0! | L11: =D11/B11 -> #DIV/0!
A12: 43729 | J12: =E12/B12 -> #DIV/0! | K12: =C12/B12 -> #DIV/0! | L12: =D12/B12 -> #DIV/0!
A13: 43730 | J13: =E13/B13 -> #DIV/0! | K13: =C13/B13 -> #DIV/0! | L13: =D13/B13 -> #DIV/0!
A14: 43731 | J14: =E14/B14 -> #DIV/0! | K14: =C14/B14 -> #DIV/0! | L14: =D14/B14 -> #DIV/0!
A15: 43732 | J15: =E15/B15 -> #DIV/0! | K15: =C15/B15 -> #DIV/0! | L15: =D15/B15 -> #DIV/0!
... A28: 43745 | J28: =E28/B28 -> #DIV/0! | K28: =C28/B28 -> #DIV/0! | L28: =D28/B28 -> #DIV/0!
A29: 43746 | B29: 230 | C29: 43 | D29: 5 | E29: 182 | J29: =E29/B29 -> 0.79130435 | K29: =C29/B29 -> 0.18695652 | L29: =D29/B29 -> 0.02173913
A30: 43747 | J30: =E30/B30 -> #DIV/0! | K30: =C30/B30 -> #DIV/0! | L30: =D30/B30 -> #DIV/0!
A31: 43748 | J31: =E31/B31 -> #DIV/0! | K31: =C31/B31 -> #DIV/0! | L31: =D31/B31 -> #DIV/0!
A32: 43749 | J32: =E32/B32 -> #DIV/0! | K32: =C32/B32 -> #DIV/0! | L32: =D32/B32 -> #DIV/0!
A33: 43750 | J33: =E33/B33 -> #DIV/0! | K33: =C33/B33 -> #DIV/0! | L33: =D33/B33 -> #DIV/0!
A34: 43751 | J34: =E34/B34 -> #DIV/0! | K34: =C34/B34 -> #DIV/0! | L34: =D34/B34 -> #DIV/0!
A35: 43752 | J35: =E35/B35 -> #DIV/0! | K35: =C35/B35 -> #DIV/0! | L35: =D35/B35 -> #DIV/0!
A36: 43753 | J36: =E36/B36 -> #DIV/0! | K36: =C36/B36 -> #DIV/0! | L36: =D36/B36 -> #DIV/0!
A37: 43754 | B37: 173 | C37: 31 | D37: 11 | E37: 131 | J37: =E37/B37 -> 0.75722543 | K37: =C37/B37 -> 0.17919075 | L37: =D37/B37 -> 0.063583815
A38: 43755 | J38: =E38/B38 -> #DIV/0! | K38: =C38/B38 -> #DIV/0! | L38: =D38/B38 -> #DIV/0!
A39: 43756 | J39: =E39/B39 -> #DIV/0! | K39: =C39/B39 -> #DIV/0! | L39: =D39/B39 -> #DIV/0!
A40: 43757 | J40: =E40/B40 -> #DIV/0! | K40: =C40/B40 -> #DIV/0! | L40: =D40/B40 -> #DIV/0!
A41: 43758 | J41: =E41/B41 -> #DIV/0! | K41: =C41/B41 -> #DIV/0! | L41: =D41/B41 -> #DIV/0!
A42: 43759 | J42: =E42/B42 -> #DIV/0! | K42: =C42/B42 -> #DIV/0! | L42: =D42/B42 -> #DIV/0!
A43: 43760 | J43: =E43/B43 -> #DIV/0! | K43: =C43/B43 -> #DIV/0! | L43: =D43/B43 -> #DIV/0!
A44: 43761 | J44: =E44/B44 -> #DIV/0! | K44: =C44/B44 -> #DIV/0! | L44: =D44/B44 -> #DIV/0!
A45: 43762 | B45: 175 | C45: 25 | D45: 8 | E45: 142 | J45: =E45/B45 -> 0.81142857 | K45: =C45/B45 -> 0.14285714 | L45: =D45/B45 -> 0.045714286
A46: 43763 | B46: 165 | C46: 27 | D46: 7 | E46: 131 | J46: =E46/B46 -> 0.79393939 | K46: =C46/B46 -> 0.16363636 | L46: =D46/B46 -> 0.042424242
A47: 43764 | J47: =E47/B47 -> #DIV/0! | K47: =C47/B47 -> #DIV/0! | L47: =D47/B47 -> #DIV/0!
A48: 43765 | J48: =E48/B48 -> #DIV/0! | K48: =C48/B48 -> #DIV/0! | L48: =D48/B48 -> #DIV/0!
A49: 43766 | J49: =E49/B49 -> #DIV/0! | K49: =C49/B49 -> #DIV/0! | L49: =D49/B49 -> #DIV/0!
A50: 43767 | J50: =E50/B50 -> #DIV/0! | K50: =C50/B50 -> #DIV/0! | L50: =D50/B50 -> #DIV/0!
A51: 43768 | J51: =E51/B51 -> #DIV/0! | K51: =C51/B51 -> #DIV/0! | L51: =D51/B51 -> #DIV/0!
A52: 43769 | J52: =E52/B52 -> #DIV/0! | K52: =C52/B52 -> #DIV/0! | L52: =D52/B52 -> #DIV/0!
A53: 43770 | J53: =E53/B53 -> #DIV/0! | K53: =C53/B53 -> #DIV/0! | L53: =D53/B53 -> #DIV/0!
A54: 43771 | J54: =E54/B54 -> #DIV/0! | K54: =C54/B54 -> #DIV/0! | L54: =D54/B54 -> #DIV/0!
A55: 43772 | J55: =E55/B55 -> #DIV/0! | K55: =C55/B55 -> #DIV/0! | L55: =D55/B55 -> #DIV/0!
A56: 43773 | B56: 95 | C56: 20 | D56: 6 | E56: 69 | J56: =E56/B56 -> 0.72631579 | K56: =C56/B56 -> 0.21052632 | L56: =D56/B56 -> 0.063157895
A57: 43774 | J57: =E57/B57 -> #DIV/0! | K57: =C57/B57 -> #DIV/0! | L57: =D57/B57 -> #DIV/0!
A58: 43775 | J58: =E58/B58 -> #DIV/0! | K58: =C58/B58 -> #DIV/0! | L58: =D58/B58 -> #DIV/0!
A59: 43776 | J59: =E59/B59 -> #DIV/0! | K59: =C59/B59 -> #DIV/0! | L59: =D59/B59 -> #DIV/0!
A60: 43777 | J60: =E60/B60 -> #DIV/0! | K60: =C60/B60 -> #DIV/0! | L60: =D60/B60 -> #DIV/0!
A61: 43778 | J61: =E61/B61 -> #DIV/0! | K61: =C61/B61 -> #DIV/0! | L61: =D61/B61 -> #DIV/0!
A62: 43779 | J62: =E62/B62 -> #DIV/0! | K62: =C62/B62 -> #DIV/0! | L62: =D62/B62 -> #DIV/0!
A63: 43780 | J63: =E63/B63 -> #DIV/0! | K63: =C63/B63 -> #DIV/0! | L63: =D63/B63 -> #DIV/0!
A64: 43781 | J64: =E64/B64 -> #DIV/0! | K64: =C64/B64 -> #DIV/0! | L64: =D64/B64 -> #DIV/0!
A65: 43782 | B65: 140 | C65: 18 | D65: 3 | E65: 119 | J65: =E65/B65 -> 0.85 | K65: =C65/B65 -> 0.12857143 | L65: =D65/B65 -> 0.021428571
A66: 43783 | J66: =E66/B66 -> #DIV/0! | K66: =C66/B66 -> #DIV/0! | L66: =D66/B66 -> #DIV/0!
A67: 43784 | J67: =E67/B67 -> #DIV/0! | K67: =C67/B67 -> #DIV/0! | L67: =D67/B67 -> #DIV/0!
A68: 43785 | J68: =E68/B68 -> #DIV/0! | K68: =C68/B68 -> #DIV/0! | L68: =D68/B68 -> #DIV/0!
A69: 43786 | J69: =E69/B69 -> #DIV/0! | K69: =C69/B69 -> #DIV/0! | L69: =D69/B69 -> #DIV/0!
A70: 43787 | J70: =E70/B70 -> #DIV/0! | K70: =C70/B70 -> #DIV/0! | L70: =D70/B70 -> #DIV/0!
A71: 43788 | J71: =E71/B71 -> #DIV/0! | K71: =C71/B71 -> #DIV/0! | L71: =D71/B71 -> #DIV/0!
A72: 43789 | J72: =E72/B72 -> #DIV/0! | K72: =C72/B72 -> #DIV/0! | L72: =D72/B72 -> #DIV/0!
A73: 43790 | J73: =E73/B73 -> #DIV/0! | K73: =C73/B73 -> #DIV/0! | L73: =D73/B73 -> #DIV/0!
A74: 43791 | B74: 145 | C74: 16 | D74: 11 | E74: 118 | J74: =E74/B74 -> 0.8137931 | K74: =C74/B74 -> 0.11034483 | L74: =D74/B74 -> 0.075862069
A75: 43792 | J75: =E75/B75 -> #DIV/0! | K75: =C75/B75 -> #DIV/0! | L75: =D75/B75 -> #DIV/0!
A76: 43793 | J76: =E76/B76 -> #DIV/0! | K76: =C76/B76 -> #DIV/0! | L76: =D76/B76 -> #DIV/0!
A77: 43794 | J77: =E77/B77 -> #DIV/0! | K77: =C77/B77 -> #DIV/0! | L77: =D77/B77 -> #DIV/0!
A78: 43795 | J78: =E78/B78 -> #DIV/0! | K78: =C78/B78 -> #DIV/0! | L78: =D78/B78 -> #DIV/0!
A79: 43796 | J79: =E79/B79 -> #DIV/0! | K79: =C79/B79 -> #DIV/0! | L79: =D79/B79 -> #DIV/0!
A80: 43797 | J80: =E80/B80 -> #DIV/0! | K80: =C80/B80 -> #DIV/0! | L80: =D80/B80 -> #DIV/0!
A81: 43798 | B81: 158 | C81: 17 | D81: 10 | E81: 131 | J81: =E81/B81 -> 0.82911392 | K81: =C81/B81 -> 0.10759494 | L81: =D81/B81 -> 0.063291139
A82: 43799 | J82: =E82/B82 -> #DIV/0! | K82: =C82/B82 -> #DIV/0! | L82: =D82/B82 -> #DIV/0!
A83: 43800 | J83: =E83/B83 -> #DIV/0! | K83: =C83/B83 -> #DIV/0! | L83: =D83/B83 -> #DIV/0!
A84: 43801 | J84: =E84/B84 -> #DIV/0! | K84: =C84/B84 -> #DIV/0! | L84: =D84/B84 -> #DIV/0!
A85: 43802 | J85: =E85/B85 -> #DIV/0! | K85: =C85/B85 -> #DIV/0! | L85: =D85/B85 -> #DIV/0!
A86: 43803 | J86: =E86/B86 -> #DIV/0! | K86: =C86/B86 -> #DIV/0! | L86: =D86/B86 -> #DIV/0!
A87: 43804 | J87: =E87/B87 -> #DIV/0! | K87: =C87/B87 -> #DIV/0! | L87: =D87/B87 -> #DIV/0!
A88: 43805 | J88: =E88/B88 -> #DIV/0! | K88: =C88/B88 -> #DIV/0! | L88: =D88/B88 -> #DIV/0!
A89: 43806 | J89: =E89/B89 -> #DIV/0! | K89: =C89/B89 -> #DIV/0! | L89: =D89/B89 -> #DIV/0!
A90: 43807 | J90: =E90/B90 -> #DIV/0! | K90: =C90/B90 -> #DIV/0! | L90: =D90/B90 -> #DIV/0!
A91: 43808 | J91: =E91/B91 -> #DIV/0! | K91: =C91/B91 -> #DIV/0! | L91: =D91/B91 -> #DIV/0!
A92: 43809 | J92: =E92/B92 -> #DIV/0! | K92: =C92/B92 -> #DIV/0! | L92: =D92/B92 -> #DIV/0!
A93: 43810 | J93: =E93/B93 -> #DIV/0! | K93: =C93/B93 -> #DIV/0! | L93: =D93/B93 -> #DIV/0!
... A125: 43842 | J125: =E125/B125 -> #DIV/0! | K125: =C125/B125 -> #DIV/0! | L125: =D125/B125 -> #DIV/0!
A126: 43843 | B126: 112 | C126: 19 | D126: 7 | E126: 86 | J126: =E126/B126 -> 0.76785714 | K126: =C126/B126 -> 0.16964286 | L126: =D126/B126 -> 0.0625
A127: 43844 | J127: =E127/B127 -> #DIV/0! | K127: =C127/B127 -> #DIV/0! | L127: =D127/B127 -> #DIV/0!
A128: 43845 | J128: =E128/B128 -> #DIV/0! | K128: =C128/B128 -> #DIV/0! | L128: =D128/B128 -> #DIV/0!
A129: 43846 | J129: =E129/B129 -> #DIV/0! | K129: =C129/B129 -> #DIV/0! | L129: =D129/B129 -> #DIV/0!
A130: 43847 | J130: =E130/B130 -> #DIV/0! | K130: =C130/B130 -> #DIV/0! | L130: =D130/B130 -> #DIV/0!
A131: 43848 | J131: =E131/B131 -> #DIV/0! | K131: =C131/B131 -> #DIV/0! | L131: =D131/B131 -> #DIV/0!
A132: 43849 | J132: =E132/B132 -> #DIV/0! | K132: =C132/B132 -> #DIV/0! | L132: =D132/B132 -> #DIV/0!
A133: 43850 | J133: =E133/B133 -> #DIV/0! | K133: =C133/B133 -> #DIV/0! | L133: =D133/B133 -> #DIV/0!
A134: 43851 | J134: =E134/B134 -> #DIV/0! | K134: =C134/B134 -> #DIV/0! | L134: =D134/B134 -> #DIV/0!
A135: 43852 | J135: =E135/B135 -> #DIV/0! | K135: =C135/B135 -> #DIV/0! | L135: =D135/B135 -> #DIV/0!
A136: 43853 | J136: =E136/B136 -> #DIV/0! | K136: =C136/B136 -> #DIV/0! | L136: =D136/B136 -> #DIV/0!
A137: 43854 | J137: =E137/B137 -> #DIV/0! | K137: =C137/B137 -> #DIV/0! | L137: =D137/B137 -> #DIV/0!
A138: 43855 | J138: =E138/B138 -> #DIV/0! | K138: =C138/B138 -> #DIV/0! | L138: =D138/B138 -> #DIV/0!
... A150: 43867 | J150: =E150/B150 -> #DIV/0! | K150: =C150/B150 -> #DIV/0! | L150: =D150/B150 -> #DIV/0!
A151: 43868 | B151: 184 | C151: 23 | D151: 6 | E151: 155 | J151: =IFERROR(E151/B151,"") -> 0.8423913 | K151: =IFERROR(C151/B151,"") -> 0.125 | L151: =IFERROR(D151/B151,"") -> 0.032608696
A152: 43869 | J152: =IFERROR(E152/B152,"") | K152: =IFERROR(C152/B152,"") | L152: =IFERROR(D152/B152,"")
A153: 43870 | J153: =IFERROR(E153/B153,"") | K153: =IFERROR(C153/B153,"") | L153: =IFERROR(D153/B153,"")
A154: 43871 | J154: =IFERROR(E154/B154,"") | K154: =IFERROR(C154/B154,"") | L154: =IFERROR(D154/B154,"")
...

Sheet Returer från kunder
A1: Datum | B1: Tillverkare | C1: Artikelnummer | D1: Typ | E1: Bil | F1: Årsmodell | G1: Kund | I1: Tel nr | J1: Email | K1: Till: | L1: Övrigt
A2: 43108 | B2: Erich Jaeger | C2: 748611, 721999 | E2: YYH940 | G2: Magnus Fredriksson, Auto Bilvård | I2: 0733-141613 | J2: mankan.f83@gmail.com | K2: Hit | L2: Inkommen 25/1 HL
A3: 43108 | C3: LS-2 | E3: YZN203 | G3: Kjell Mannberg | I3: 070-3641599 | J3: kjell.mannberg@gmail.com | L3: Inkommen 10/1/CS
A4: 43110 | B4: Micromel | C4: LS-2 | G4: T-parts / Tobias Olofsson | I4: 0703-101373 | J4: tobias@t-parts.se | K4: Hit | L4: Se mail | M4: Inkommen 30/1/HL
A5: 43112 | C5: LS-2 | E5: BJO068 | G5: Michael Marberg | I5: 0723-222929 | J5: micma02@hotmail.com | K5: Hit | L5: Fel namn på paketen, kund kunde inte hämta ut och vill makulera sin order. Ska läggas in i lager när den kommer i retur./ CS 12/1 | T5: Inkom 1/2 CS
A6: 43115 | C6: LS-1 | E6: BOT182 | G6: Henrik Carlgren | I6: 070-3022092 | J6: henrik.carlgren@live.se | K6: Hit | L6: Inkommen 18/1/CS
A7: 43136 | B7: Erich Jaeger | C7: Modul | E7: Yua253 | G7: Skärgårdens Måleri Värmdö AB | I7: 0709-223000 | J7: djurhamnsmaleri@telia.com | L7: Kund ska skickas oss måtten på paketet eller skicka paketet till oss. //TC 5/2
A8: 43145 | B8: Westfalia | C8: Fast Westfalia dragkrok | E8: Gpp279 | G8: Kund ångra sig inom 14 dagar får dock stå för frakt ut 486kr / 14/2 CS
A9: 43151 | B9: Menabo | C9: Sherman | E9: NHT357 | G9: Allen Palm, vi har skickat fel takräke till kund efter pratat med honom, han retunerar hit och nya är på väg / 20/2 CS
A10: 43151 | B10: Umbra | C10: 02031/F | E10: KSF513 | G10: Ole Halse | I10: 0709-489071 | J10: ole.halse@live.se | K10: Hit | L10: Kund hör av sig så snart han bytt dragen men kan dröja några veckor. / 21/2 CS
A11: 43153 | B11: Steinhof | C11: ? | D11: Dragkrok | G11: Fredrik Bernström fått fel krok vet ej vad han fått, kund har fått rätt krok nu och vi inväntar retur av fel krok, då vet vi vad det är. / CS 22/2
A12: 43160 | B12: Defa | D12: Relä | E12: JDB190 | G12: Ricardo Olivares | H12: Rundan 46 14645 Tullinge | I12: 0703-445523 | J12: ricardo.figueroa79@gmail.com | K12: Hit, kund ombesörjer frakt. Lägg sedan detta i Defa WarmUp Kit, DEF 471280 | L12: Mailat kund om han fått iväg det till oss //TC 18/4 | M12: Kommit i retur 24/4 //TC
A13: 43166 | C13: SMP3 | E13: DZC785 | G13: Jonas Wallinder
A14: 43166 | B14: GJK | C14: 542940 | D14: Golv mattor Premium | E14: Volvo V60 Kombi 2010> | G14: Per Forsberg | H14: Kund har beställt fel. Vi skickar kredit och lägger in i lager när kund retunerat det till oss 7/3 CS
A15: 43171 | B15: Menabo | C15: Leopard L | E15: NHT357 | G15: Allen Palm, vi har åter skickat fel takräke till kund efter pratat med honom, han retunerar hit och nya är leverarade / 12/3 CS
A16: 43185 | B16: Steinhof | C16: SMP-3 | E16: LBJ974 | G16: Tommy Persson | H16: Apelvägen 20 13835 Älta LEVADRESS: Focus Neon Tommy Persson Instrumentvägen 11 12609 Hägersten | I16: 070-8556901 | J16: tommy–@hotmail.com | L16: Beställt en 7-spec istället. Fakturera 500 kr om den inte kommer tillbaka //TC
A17: 43186 | B17: GJK | C17: 102222 | D17: Bagagerumsmatta | E17: APO762 | F17: -9 | G17: Mona Hoff | H17: Order 242228 / kund har fått fel matta, ny är på väg och denna returneras och ska krediteras.
A18: 43193 | B18: Steinhof | C18: V-292 | E18: RBM963 | F18: -15 | G18: Obai Abbas | H18: Kund ångra sig och vill ha avtagbar istället 3/4 CS
A19: 43209 | B19: GJK | C19: 100745 | D19: Bagagerumsmatta | E19: OJP663 | F19: -16 | G19: Kia Optima Kombi 2016> | H19: Mattan passa inte, CS beställt fel då hon missuppfatta Motors, kund returnerar till kontoret 19/4 CS
A20: 43235 | C20: SMP-3 | E20: LNH684 | G20: Ante Larsson | H20: Beställt spec-elsats. Ska skicka tillbaka smp-3 | K20: Kommit 16/5 CS
A21: 43252 | B21: Steinhof | C21: Liten amerkansk kula | G21: Henry Erixon | H21: Fått den lilla när det är stora som han ska ha. Skickat ny kula till honom. ger oss sedan måtten på paketet för retur. //TC 1/6
A22: 43252 | B22: Westfalia | C22: 300096300157 | E22: WCA824 | G22: Arkenklo | H22: Elsats ej skickad till kund. Dem har skickat en adapter istället. Bett om kredit. //TC 1/6
A23: 43283 | B23: Menabo | C23: Sheramn | D23: XL 000094700000 | E23: NEX336 | G23: Olaf Möllenhoff | H23: Passa ej bett om upphämtning 2/7 CS | K23: Kommit 5/7 CS
A24: 43283 | B24: Menabo | C24: Leopard | D24: 88700000 | E24: PUP430 | G24: Bashkim Zeka | H24: Missförstånd med kund, skickat tillbaka / CS
A25: 43283 | B25: Bagagerumsmatta | C25: 101234 | E25: CBY175 | G25: Mikael Ahl | H25: Fel matta pga kund uppget fel sort. Ny matta skickad och faktura löst, ska bara in i lager när den kommer./ CS | O25: Kommit 5/7 CS
A26: 43284 | B26: Steinhof | E26: UGR758 | F26: VW Polo - 04 | G26: Bil & Motorservice i Västerort | H26: Kund vill inte ha krogen då den blev leverarad försent.
A27: 43297 | B27: Imiola / Hakpol | C27: W/031 | D27: Fast | E27: Volkswagen Touareg 2002>2014 | G27: Leif Grefalk | H27: Kund ångra sig och vill avbeställa, bett kund att inte ta emot paketet alls. 16/4 CS

Sheet EAN Codes
A1: =IFERROR(__xludf.DUMMYFUNCTION("IMPORTRANGE(""https://docs.google.com/spreadsheets/d/1SfqQCLFfCUAhG8--qFFKU6T9qBfDcTK3jPQpHE0iMJY/"",""'EAN Codes'!A:C"")"),"Artikelnummer") -> Artikelnummer | B1: =IFERROR(__xludf.DUMMYFUNCTION("""COMPUTED_VALUE"""),"kod EAN") -> kod EAN | C1: =IFERROR(__xludf.DUMMYFUNCTION("""COMPUTED_VALUE"""),"Fabrikat") -> Fabrikat
A2: =IFERROR(__xludf.DUMMYFUNCTION("""COMPUTED_VALUE"""),"303151600001") -> 303151600001 | B2: =IFERROR(__xludf.DUMMYFUNCTION("""COMPUTED_VALUE"""),"4250141101210") -> 4250141101210 | C2: =IFERROR(__xludf.DUMMYFUNCTION("""COMPUTED_VALUE"""),"Westfalia/Witter") -> Westfalia/Witter
A3: =IFERROR(__xludf.DUMMYFUNCTION("""COMPUTED_VALUE"""),"303207600001") -> 303207600001 | B3: =IFERROR(__xludf.DUMMYFUNCTION("""COMPUTED_VALUE"""),"4250141101869") -> 4250141101869 | C3: =IFERROR(__xludf.DUMMYFUNCTION("""COMPUTED_VALUE"""),"Westfalia/Witter") -> Westfalia/Witter
A4: =IFERROR(__xludf.DUMMYFUNCTION("""COMPUTED_VALUE"""),"303212600001") -> 303212600001 | B4: =IFERROR(__xludf.DUMMYFUNCTION("""COMPUTED_VALUE"""),"4250141101944") -> 4250141101944 | C4: =IFERROR(__xludf.DUMMYFUNCTION("""COMPUTED_VALUE"""),"Westfalia/Witter") -> Westfalia/Witter
A5: =IFERROR(__xludf.DUMMYFUNCTION("""COMPUTED_VALUE"""),"303212600001") -> 303212600001 | B5: =IFERROR(__xludf.DUMMYFUNCTION("""COMPUTED_VALUE"""),"4250141101944") -> 4250141101944 | C5: =IFERROR(__xludf.DUMMYFUNCTION("""COMPUTED_VALUE"""),"Westfalia/Witter") -> Westfalia/Witter
A6: =IFERROR(__xludf.DUMMYFUNCTION("""COMPUTED_VALUE"""),"303230600001") -> 303230600001 | B6: =IFERROR(__xludf.DUMMYFUNCTION("""COMPUTED_VALUE"""),"4250141102095") -> 4250141102095 | C6: =IFERROR(__xludf.DUMMYFUNCTION("""COMPUTED_VALUE"""),"Westfalia/Witter") -> Westfalia/Witter
A7: =IFERROR(__xludf.DUMMYFUNCTION("""COMPUTED_VALUE"""),"303232600001") -> 303232600001 | B7: =IFERROR(__xludf.DUMMYFUNCTION("""COMPUTED_VALUE"""),"4250141102118") -> 4250141102118 | C7: =IFERROR(__xludf.DUMMYFUNCTION("""COMPUTED_VALUE"""),"Westfalia/Witter") -> Westfalia/Witter
A8: =IFERROR(__xludf.DUMMYFUNCTION("""COMPUTED_VALUE"""),"303235600001") -> 303235600001 | B8: =IFERROR(__xludf.DUMMYFUNCTION("""COMPUTED_VALUE"""),"4250141102156") -> 4250141102156 | C8: =IFERROR(__xludf.DUMMYFUNCTION("""COMPUTED_VALUE"""),"Westfalia/Witter") -> Westfalia/Witter
A9: =IFERROR(__xludf.DUMMYFUNCTION("""COMPUTED_VALUE"""),"303235600001") -> 303235600001 | B9: =IFERROR(__xludf.DUMMYFUNCTION("""COMPUTED_VALUE"""),"4250141102156") -> 4250141102156 | C9: =IFERROR(__xludf.DUMMYFUNCTION("""COMPUTED_VALUE"""),"Westfalia/Witter") -> Westfalia/Witter
A10: =IFERROR(__xludf.DUMMYFUNCTION("""COMPUTED_VALUE"""),"304054600001") -> 304054600001 | B10: =IFERROR(__xludf.DUMMYFUNCTION("""COMPUTED_VALUE"""),"4250141102491") -> 4250141102491 | C10: =IFERROR(__xludf.DUMMYFUNCTION("""COMPUTED_VALUE"""),"Westfalia/Witter") -> Westfalia/Witter
A11: =IFERROR(__xludf.DUMMYFUNCTION("""COMPUTED_VALUE"""),"304069600001") -> 304069600001 | B11: =IFERROR(__xludf.DUMMYFUNCTION("""COMPUTED_VALUE"""),"4250141102811") -> 4250141102811 | C11: =IFERROR(__xludf.DUMMYFUNCTION("""COMPUTED_VALUE"""),"Westfalia/Witter") -> Westfalia/Witter
A12: =IFERROR(__xludf.DUMMYFUNCTION("""COMPUTED_VALUE"""),"304069600001") -> 304069600001 | B12: =IFERROR(__xludf.DUMMYFUNCTION("""COMPUTED_VALUE"""),"4250141102811") -> 4250141102811 | C12: =IFERROR(__xludf.DUMMYFUNCTION("""COMPUTED_VALUE"""),"Westfalia/Witter") -> Westfalia/Witter
A13: =IFERROR(__xludf.DUMMYFUNCTION("""COMPUTED_VALUE"""),"304074600001") -> 304074600001 | B13: =IFERROR(__xludf.DUMMYFUNCTION("""COMPUTED_VALUE"""),"4250141102842") -> 4250141102842 | C13: =IFERROR(__xludf.DUMMYFUNCTION("""COMPUTED_VALUE"""),"Westfalia/Witter") -> Westfalia/Witter
A14: =IFERROR(__xludf.DUMMYFUNCTION("""COMPUTED_VALUE"""),"304074600001") -> 304074600001 | B14: =IFERROR(__xludf.DUMMYFUNCTION("""COMPUTED_VALUE"""),"4250141102842") -> 4250141102842 | C14: =IFERROR(__xludf.DUMMYFUNCTION("""COMPUTED_VALUE"""),"Westfalia/Witter") -> Westfalia/Witter
A15: =IFERROR(__xludf.DUMMYFUNCTION("""COMPUTED_VALUE"""),"304076600001") -> 304076600001 | B15: =IFERROR(__xludf.DUMMYFUNCTION("""COMPUTED_VALUE"""),"4250141102866") -> 4250141102866 | C15: =IFERROR(__xludf.DUMMYFUNCTION("""COMPUTED_VALUE"""),"Westfalia/Witter") -> Westfalia/Witter
A16: =IFERROR(__xludf.DUMMYFUNCTION("""COMPUTED_VALUE"""),"305179600001") -> 305179600001 | B16: =IFERROR(__xludf.DUMMYFUNCTION("""COMPUTED_VALUE"""),"4250141103306") -> 4250141103306 | C16: =IFERROR(__xludf.DUMMYFUNCTION("""COMPUTED_VALUE"""),"Westfalia/Witter") -> Westfalia/Witter
A17: =IFERROR(__xludf.DUMMYFUNCTION("""COMPUTED_VALUE"""),"305179600001") -> 305179600001 | B17: =IFERROR(__xludf.DUMMYFUNCTION("""COMPUTED_VALUE"""),"4250141103306") -> 4250141103306 | C17: =IFERROR(__xludf.DUMMYFUNCTION("""COMPUTED_VALUE"""),"Westfalia/Witter") -> Westfalia/Witter
A18: =IFERROR(__xludf.DUMMYFUNCTION("""COMPUTED_VALUE"""),"305205600001") -> 305205600001 | B18: =IFERROR(__xludf.DUMMYFUNCTION("""COMPUTED_VALUE"""),"4250141103481") -> 4250141103481 | C18: =IFERROR(__xludf.DUMMYFUNCTION("""COMPUTED_VALUE"""),"Westfalia/Witter") -> Westfalia/Witter
A19: =IFERROR(__xludf.DUMMYFUNCTION("""COMPUTED_VALUE"""),"305205600001") -> 305205600001 | B19: =IFERROR(__xludf.DUMMYFUNCTION("""COMPUTED_VALUE"""),"4250141103481") -> 4250141103481 | C19: =IFERROR(__xludf.DUMMYFUNCTION("""COMPUTED_VALUE"""),"Westfalia/Witter") -> Westfalia/Witter
A20: =IFERROR(__xludf.DUMMYFUNCTION("""COMPUTED_VALUE"""),"305205600001") -> 305205600001 | B20: =IFERROR(__xludf.DUMMYFUNCTION("""COMPUTED_VALUE"""),"4250141103481") -> 4250141103481 | C20: =IFERROR(__xludf.DUMMYFUNCTION("""COMPUTED_VALUE"""),"Westfalia/Witter") -> Westfalia/Witter
A21: =IFERROR(__xludf.DUMMYFUNCTION("""COMPUTED_VALUE"""),"305206600001") -> 305206600001 | B21: =IFERROR(__xludf.DUMMYFUNCTION("""COMPUTED_VALUE"""),"4250141103504") -> 4250141103504 | C21: =IFERROR(__xludf.DUMMYFUNCTION("""COMPUTED_VALUE"""),"Westfalia/Witter") -> Westfalia/Witter
A22: =IFERROR(__xludf.DUMMYFUNCTION("""COMPUTED_VALUE"""),"305206600001") -> 305206600001 | B22: =IFERROR(__xludf.DUMMYFUNCTION("""COMPUTED_VALUE"""),"4250141103504") -> 4250141103504 | C22: =IFERROR(__xludf.DUMMYFUNCTION("""COMPUTED_VALUE"""),"Westfalia/Witter") -> Westfalia/Witter
A23: =IFERROR(__xludf.DUMMYFUNCTION("""COMPUTED_VALUE"""),"305206600001") -> 305206600001 | B23: =IFERROR(__xludf.DUMMYFUNCTION("""COMPUTED_VALUE"""),"4250141103504") -> 4250141103504 | C23: =IFERROR(__xludf.DUMMYFUNCTION("""COMPUTED_VALUE"""),"Westfalia/Witter") -> Westfalia/Witter
A24: =IFERROR(__xludf.DUMMYFUNCTION("""COMPUTED_VALUE"""),"305220600001") -> 305220600001 | B24: =IFERROR(__xludf.DUMMYFUNCTION("""COMPUTED_VALUE"""),"4250141103696") -> 4250141103696 | C24: =IFERROR(__xludf.DUMMYFUNCTION("""COMPUTED_VALUE"""),"Westfalia/Witter") -> Westfalia/Witter
A25: =IFERROR(__xludf.DUMMYFUNCTION("""COMPUTED_VALUE"""),"305220600001") -> 305220600001 | B25: =IFERROR(__xludf.DUMMYFUNCTION("""COMPUTED_VALUE"""),"4250141103696") -> 4250141103696 | C25: =IFERROR(__xludf.DUMMYFUNCTION("""COMPUTED_VALUE"""),"Westfalia/Witter") -> Westfalia/Witter
A26: =IFERROR(__xludf.DUMMYFUNCTION("""COMPUTED_VALUE"""),"305222600001") -> 305222600001 | B26: =IFERROR(__xludf.DUMMYFUNCTION("""COMPUTED_VALUE"""),"4250141103801") -> 4250141103801 | C26: =IFERROR(__xludf.DUMMYFUNCTION("""COMPUTED_VALUE"""),"Westfalia/Witter") -> Westfalia/Witter
A27: =IFERROR(__xludf.DUMMYFUNCTION("""COMPUTED_VALUE"""),"305222600001") -> 305222600001 | B27: =IFERROR(__xludf.DUMMYFUNCTION("""COMPUTED_VALUE"""),"4250141103801") -> 4250141103801 | C27: =IFERROR(__xludf.DUMMYFUNCTION("""COMPUTED_VALUE"""),"Westfalia/Witter") -> Westfalia/Witter
A28: =IFERROR(__xludf.DUMMYFUNCTION("""COMPUTED_VALUE"""),"305222600001") -> 305222600001 | B28: =IFERROR(__xludf.DUMMYFUNCTION("""COMPUTED_VALUE"""),"4250141103801") -> 4250141103801 | C28: =IFERROR(__xludf.DUMMYFUNCTION("""COMPUTED_VALUE"""),"Westfalia/Witter") -> Westfalia/Witter
A29: =IFERROR(__xludf.DUMMYFUNCTION("""COMPUTED_VALUE"""),"305222600001") -> 305222600001 | B29: =IFERROR(__xludf.DUMMYFUNCTION("""COMPUTED_VALUE"""),"4250141103801") -> 4250141103801 | C29: =IFERROR(__xludf.DUMMYFUNCTION("""COMPUTED_VALUE"""),"Westfalia/Witter") -> Westfalia/Witter
A30: =IFERROR(__xludf.DUMMYFUNCTION("""COMPUTED_VALUE"""),"305222600001") -> 305222600001 | B30: =IFERROR(__xludf.DUMMYFUNCTION("""COMPUTED_VALUE"""),"4250141103801") -> 4250141103801 | C30: =IFERROR(__xludf.DUMMYFUNCTION("""COMPUTED_VALUE"""),"Westfalia/Witter") -> Westfalia/Witter
A31: =IFERROR(__xludf.DUMMYFUNCTION("""COMPUTED_VALUE"""),"305222600001") -> 305222600001 | B31: =IFERROR(__xludf.DUMMYFUNCTION("""COMPUTED_VALUE"""),"4250141103801") -> 4250141103801 | C31: =IFERROR(__xludf.DUMMYFUNCTION("""COMPUTED_VALUE"""),"Westfalia/Witter") -> Westfalia/Witter
A32: =IFERROR(__xludf.DUMMYFUNCTION("""COMPUTED_VALUE"""),"305222600001") -> 305222600001 | B32: =IFERROR(__xludf.DUMMYFUNCTION("""COMPUTED_VALUE"""),"4250141103801") -> 4250141103801 | C32: =IFERROR(__xludf.DUMMYFUNCTION("""COMPUTED_VALUE"""),"Westfalia/Witter") -> Westfalia/Witter
A33: =IFERROR(__xludf.DUMMYFUNCTION("""COMPUTED_VALUE"""),"305223600001") -> 305223600001 | B33: =IFERROR(__xludf.DUMMYFUNCTION("""COMPUTED_VALUE"""),"4250141103832") -> 4250141103832 | C33: =IFERROR(__xludf.DUMMYFUNCTION("""COMPUTED_VALUE"""),"Westfalia/Witter") -> Westfalia/Witter
A34: =IFERROR(__xludf.DUMMYFUNCTION("""COMPUTED_VALUE"""),"305223600001") -> 305223600001 | B34: =IFERROR(__xludf.DUMMYFUNCTION("""COMPUTED_VALUE"""),"4250141103832") -> 4250141103832 | C34: =IFERROR(__xludf.DUMMYFUNCTION("""COMPUTED_VALUE"""),"Westfalia/Witter") -> Westfalia/Witter
A35: =IFERROR(__xludf.DUMMYFUNCTION("""COMPUTED_VALUE"""),"305269600001") -> 305269600001 | B35: =IFERROR(__xludf.DUMMYFUNCTION("""COMPUTED_VALUE"""),"4250141104365") -> 4250141104365 | C35: =IFERROR(__xludf.DUMMYFUNCTION("""COMPUTED_VALUE"""),"Westfalia/Witter") -> Westfalia/Witter
A36: =IFERROR(__xludf.DUMMYFUNCTION("""COMPUTED_VALUE"""),"305269600001") -> 305269600001 | B36: =IFERROR(__xludf.DUMMYFUNCTION("""COMPUTED_VALUE"""),"4250141104365") -> 4250141104365 | C36: =IFERROR(__xludf.DUMMYFUNCTION("""COMPUTED_VALUE"""),"Westfalia/Witter") -> Westfalia/Witter
A37: =IFERROR(__xludf.DUMMYFUNCTION("""COMPUTED_VALUE"""),"305274600001") -> 305274600001 | B37: =IFERROR(__xludf.DUMMYFUNCTION("""COMPUTED_VALUE"""),"4250141104563") -> 4250141104563 | C37: =IFERROR(__xludf.DUMMYFUNCTION("""COMPUTED_VALUE"""),"Westfalia/Witter") -> Westfalia/Witter
A38: =IFERROR(__xludf.DUMMYFUNCTION("""COMPUTED_VALUE"""),"305274600001") -> 305274600001 | B38: =IFERROR(__xludf.DUMMYFUNCTION("""COMPUTED_VALUE"""),"4250141104563") -> 4250141104563 | C38: =IFERROR(__xludf.DUMMYFUNCTION("""COMPUTED_VALUE"""),"Westfalia/Witter") -> Westfalia/Witter
A39: =IFERROR(__xludf.DUMMYFUNCTION("""COMPUTED_VALUE"""),"305277600001") -> 305277600001 | B39: =IFERROR(__xludf.DUMMYFUNCTION("""COMPUTED_VALUE"""),"4250141104594") -> 4250141104594 | C39: =IFERROR(__xludf.DUMMYFUNCTION("""COMPUTED_VALUE"""),"Westfalia/Witter") -> Westfalia/Witter
A40: =IFERROR(__xludf.DUMMYFUNCTION("""COMPUTED_VALUE"""),"305277600001") -> 305277600001 | B40: =IFERROR(__xludf.DUMMYFUNCTION("""COMPUTED_VALUE"""),"4250141104594") -> 4250141104594 | C40: =IFERROR(__xludf.DUMMYFUNCTION("""COMPUTED_VALUE"""),"Westfalia/Witter") -> Westfalia/Witter
A41: =IFERROR(__xludf.DUMMYFUNCTION("""COMPUTED_VALUE"""),"305277600001") -> 305277600001 | B41: =IFERROR(__xludf.DUMMYFUNCTION("""COMPUTED_VALUE"""),"4250141104594") -> 4250141104594 | C41: =IFERROR(__xludf.DUMMYFUNCTION("""COMPUTED_VALUE"""),"Westfalia/Witter") -> Westfalia/Witter
A42: =IFERROR(__xludf.DUMMYFUNCTION("""COMPUTED_VALUE"""),"305291600001") -> 305291600001 | B42: =IFERROR(__xludf.DUMMYFUNCTION("""COMPUTED_VALUE"""),"4250141104730") -> 4250141104730 | C42: =IFERROR(__xludf.DUMMYFUNCTION("""COMPUTED_VALUE"""),"Westfalia/Witter") -> Westfalia/Witter
A43: =IFERROR(__xludf.DUMMYFUNCTION("""COMPUTED_VALUE"""),"305291600001") -> 305291600001 | B43: =IFERROR(__xludf.DUMMYFUNCTION("""COMPUTED_VALUE"""),"4250141104730") -> 4250141104730 | C43: =IFERROR(__xludf.DUMMYFUNCTION("""COMPUTED_VALUE"""),"Westfalia/Witter") -> Westfalia/Witter
A44: =IFERROR(__xludf.DUMMYFUNCTION("""COMPUTED_VALUE"""),"305299600001") -> 305299600001 | B44: =IFERROR(__xludf.DUMMYFUNCTION("""COMPUTED_VALUE"""),"4250141104792") -> 4250141104792 | C44: =IFERROR(__xludf.DUMMYFUNCTION("""COMPUTED_VALUE"""),"Westfalia/Witter") -> Westfalia/Witter
A45: =IFERROR(__xludf.DUMMYFUNCTION("""COMPUTED_VALUE"""),"305300600001") -> 305300600001 | B45: =IFERROR(__xludf.DUMMYFUNCTION("""COMPUTED_VALUE"""),"4250141104808") -> 4250141104808 | C45: =IFERROR(__xludf.DUMMYFUNCTION("""COMPUTED_VALUE"""),"Westfalia/Witter") -> Westfalia/Witter
A46: =IFERROR(__xludf.DUMMYFUNCTION("""COMPUTED_VALUE"""),"305301600001") -> 305301600001 | B46: =IFERROR(__xludf.DUMMYFUNCTION("""COMPUTED_VALUE"""),"4250141104815") -> 4250141104815 | C46: =IFERROR(__xludf.DUMMYFUNCTION("""COMPUTED_VALUE"""),"Westfalia/Witter") -> Westfalia/Witter
A47: =IFERROR(__xludf.DUMMYFUNCTION("""COMPUTED_VALUE"""),"305301600001") -> 305301600001 | B47: =IFERROR(__xludf.DUMMYFUNCTION("""COMPUTED_VALUE"""),"4250141104815") -> 4250141104815 | C47: =IFERROR(__xludf.DUMMYFUNCTION("""COMPUTED_VALUE"""),"Westfalia/Witter") -> Westfalia/Witter
A48: =IFERROR(__xludf.DUMMYFUNCTION("""COMPUTED_VALUE"""),"305301600001") -> 305301600001 | B48: =IFERROR(__xludf.DUMMYFUNCTION("""COMPUTED_VALUE"""),"4250141104815") -> 4250141104815 | C48: =IFERROR(__xludf.DUMMYFUNCTION("""COMPUTED_VALUE"""),"Westfalia/Witter") -> Westfalia/Witter
A49: =IFERROR(__xludf.DUMMYFUNCTION("""COMPUTED_VALUE"""),"305302600001") -> 305302600001 | B49: =IFERROR(__xludf.DUMMYFUNCTION("""COMPUTED_VALUE"""),"4250141104822") -> 4250141104822 | C49: =IFERROR(__xludf.DUMMYFUNCTION("""COMPUTED_VALUE"""),"Westfalia/Witter") -> Westfalia/Witter
A50: =IFERROR(__xludf.DUMMYFUNCTION("""COMPUTED_VALUE"""),"305302600001") -> 305302600001 | B50: =IFERROR(__xludf.DUMMYFUNCTION("""COMPUTED_VALUE"""),"4250141104822") -> 4250141104822 | C50: =IFERROR(__xludf.DUMMYFUNCTION("""COMPUTED_VALUE"""),"Westfalia/Witter") -> Westfalia/Witter
A51: =IFERROR(__xludf.DUMMYFUNCTION("""COMPUTED_VALUE"""),"305302600001") -> 305302600001 | B51: =IFERROR(__xludf.DUMMYFUNCTION("""COMPUTED_VALUE"""),"4250141104822") -> 4250141104822 | C51: =IFERROR(__xludf.DUMMYFUNCTION("""COMPUTED_VALUE"""),"Westfalia/Witter") -> Westfalia/Witter
A52: =IFERROR(__xludf.DUMMYFUNCTION("""COMPUTED_VALUE"""),"306216600001") -> 306216600001 | B52: =IFERROR(__xludf.DUMMYFUNCTION("""COMPUTED_VALUE"""),"4250141105492") -> 4250141105492 | C52: =IFERROR(__xludf.DUMMYFUNCTION("""COMPUTED_VALUE"""),"Westfalia/Witter") -> Westfalia/Witter
A53: =IFERROR(__xludf.DUMMYFUNCTION("""COMPUTED_VALUE"""),"306216600001") -> 306216600001 | B53: =IFERROR(__xludf.DUMMYFUNCTION("""COMPUTED_VALUE"""),"4250141105492") -> 4250141105492 | C53: =IFERROR(__xludf.DUMMYFUNCTION("""COMPUTED_VALUE"""),"Westfalia/Witter") -> Westfalia/Witter
A54: =IFERROR(__xludf.DUMMYFUNCTION("""COMPUTED_VALUE"""),"306216600001") -> 306216600001 | B54: =IFERROR(__xludf.DUMMYFUNCTION("""COMPUTED_VALUE"""),"4250141105492") -> 4250141105492 | C54: =IFERROR(__xludf.DUMMYFUNCTION("""COMPUTED_VALUE"""),"Westfalia/Witter") -> Westfalia/Witter
A55: =IFERROR(__xludf.DUMMYFUNCTION("""COMPUTED_VALUE"""),"306248600001") -> 306248600001 | B55: =IFERROR(__xludf.DUMMYFUNCTION("""COMPUTED_VALUE"""),"4250141106062") -> 4250141106062 | C55: =IFERROR(__xludf.DUMMYFUNCTION("""COMPUTED_VALUE"""),"Westfalia/Witter") -> Westfalia/Witter
A56: =IFERROR(__xludf.DUMMYFUNCTION("""COMPUTED_VALUE"""),"307234600001") -> 307234600001 | B56: =IFERROR(__xludf.DUMMYFUNCTION("""COMPUTED_VALUE"""),"4250141106598") -> 4250141106598 | C56: =IFERROR(__xludf.DUMMYFUNCTION("""COMPUTED_VALUE"""),"Westfalia/Witter") -> Westfalia/Witter
A57: =IFERROR(__xludf.DUMMYFUNCTION("""COMPUTED_VALUE"""),"307238600001") -> 307238600001 | B57: =IFERROR(__xludf.DUMMYFUNCTION("""COMPUTED_VALUE"""),"4250141106642") -> 4250141106642 | C57: =IFERROR(__xludf.DUMMYFUNCTION("""COMPUTED_VALUE"""),"Westfalia/Witter") -> Westfalia/Witter
A58: =IFERROR(__xludf.DUMMYFUNCTION("""COMPUTED_VALUE"""),"307241600001") -> 307241600001 | B58: =IFERROR(__xludf.DUMMYFUNCTION("""COMPUTED_VALUE"""),"4250141106697") -> 4250141106697 | C58: =IFERROR(__xludf.DUMMYFUNCTION("""COMPUTED_VALUE"""),"Westfalia/Witter") -> Westfalia/Witter
A59: =IFERROR(__xludf.DUMMYFUNCTION("""COMPUTED_VALUE"""),"307241600001") -> 307241600001 | B59: =IFERROR(__xludf.DUMMYFUNCTION("""COMPUTED_VALUE"""),"4250141106697") -> 4250141106697 | C59: =IFERROR(__xludf.DUMMYFUNCTION("""COMPUTED_VALUE"""),"Westfalia/Witter") -> Westfalia/Witter
A60: =IFERROR(__xludf.DUMMYFUNCTION("""COMPUTED_VALUE"""),"307260600001") -> 307260600001 | B60: =IFERROR(__xludf.DUMMYFUNCTION("""COMPUTED_VALUE"""),"4250141106932") -> 4250141106932 | C60: =IFERROR(__xludf.DUMMYFUNCTION("""COMPUTED_VALUE"""),"Westfalia/Witter") -> Westfalia/Witter
A61: =IFERROR(__xludf.DUMMYFUNCTION("""COMPUTED_VALUE"""),"307262600001") -> 307262600001 | B61: =IFERROR(__xludf.DUMMYFUNCTION("""COMPUTED_VALUE"""),"4250141106956") -> 4250141106956 | C61: =IFERROR(__xludf.DUMMYFUNCTION("""COMPUTED_VALUE"""),"Westfalia/Witter") -> Westfalia/Witter
A62: =IFERROR(__xludf.DUMMYFUNCTION("""COMPUTED_VALUE"""),"307264600001") -> 307264600001 | B62: =IFERROR(__xludf.DUMMYFUNCTION("""COMPUTED_VALUE"""),"4250141106994") -> 4250141106994 | C62: =IFERROR(__xludf.DUMMYFUNCTION("""COMPUTED_VALUE"""),"Westfalia/Witter") -> Westfalia/Witter
A63: =IFERROR(__xludf.DUMMYFUNCTION("""COMPUTED_VALUE"""),"307264600001") -> 307264600001 | B63: =IFERROR(__xludf.DUMMYFUNCTION("""COMPUTED_VALUE"""),"4250141106994") -> 4250141106994 | C63: =IFERROR(__xludf.DUMMYFUNCTION("""COMPUTED_VALUE"""),"Westfalia/Witter") -> Westfalia/Witter
A64: =IFERROR(__xludf.DUMMYFUNCTION("""COMPUTED_VALUE"""),"307283600001") -> 307283600001 | B64: =IFERROR(__xludf.DUMMYFUNCTION("""COMPUTED_VALUE"""),"4250141107182") -> 4250141107182 | C64: =IFERROR(__xludf.DUMMYFUNCTION("""COMPUTED_VALUE"""),"Westfalia/Witter") -> Westfalia/Witter
A65: =IFERROR(__xludf.DUMMYFUNCTION("""COMPUTED_VALUE"""),"307289600001") -> 307289600001 | B65: =IFERROR(__xludf.DUMMYFUNCTION("""COMPUTED_VALUE"""),"4250141107250") -> 4250141107250 | C65: =IFERROR(__xludf.DUMMYFUNCTION("""COMPUTED_VALUE"""),"Westfalia/Witter") -> Westfalia/Witter
A66: =IFERROR(__xludf.DUMMYFUNCTION("""COMPUTED_VALUE"""),"307338600001") -> 307338600001 | B66: =IFERROR(__xludf.DUMMYFUNCTION("""COMPUTED_VALUE"""),"4250141107359") -> 4250141107359 | C66: =IFERROR(__xludf.DUMMYFUNCTION("""COMPUTED_VALUE"""),"Westfalia/Witter") -> Westfalia/Witter
A67: =IFERROR(__xludf.DUMMYFUNCTION("""COMPUTED_VALUE"""),"313082600001") -> 313082600001 | B67: =IFERROR(__xludf.DUMMYFUNCTION("""COMPUTED_VALUE"""),"4250141107588") -> 4250141107588 | C67: =IFERROR(__xludf.DUMMYFUNCTION("""COMPUTED_VALUE"""),"Westfalia/Witter") -> Westfalia/Witter
A68: =IFERROR(__xludf.DUMMYFUNCTION("""COMPUTED_VALUE"""),"313082600001") -> 313082600001 | B68: =IFERROR(__xludf.DUMMYFUNCTION("""COMPUTED_VALUE"""),"4250141107588") -> 4250141107588 | C68: =IFERROR(__xludf.DUMMYFUNCTION("""COMPUTED_VALUE"""),"Westfalia/Witter") -> Westfalia/Witter
A69: =IFERROR(__xludf.DUMMYFUNCTION("""COMPUTED_VALUE"""),"313082600001") -> 313082600001 | B69: =IFERROR(__xludf.DUMMYFUNCTION("""COMPUTED_VALUE"""),"4250141107588") -> 4250141107588 | C69: =IFERROR(__xludf.DUMMYFUNCTION("""COMPUTED_VALUE"""),"Westfalia/Witter") -> Westfalia/Witter
A70: =IFERROR(__xludf.DUMMYFUNCTION("""COMPUTED_VALUE"""),"313121600001") -> 313121600001 | B70: =IFERROR(__xludf.DUMMYFUNCTION("""COMPUTED_VALUE"""),"4250141108103") -> 4250141108103 | C70: =IFERROR(__xludf.DUMMYFUNCTION("""COMPUTED_VALUE"""),"Westfalia/Witter") -> Westfalia/Witter
A71: =IFERROR(__xludf.DUMMYFUNCTION("""COMPUTED_VALUE"""),"313134600001") -> 313134600001 | B71: =IFERROR(__xludf.DUMMYFUNCTION("""COMPUTED_VALUE"""),"4250141108301") -> 4250141108301 | C71: =IFERROR(__xludf.DUMMYFUNCTION("""COMPUTED_VALUE"""),"Westfalia/Witter") -> Westfalia/Witter
A72: =IFERROR(__xludf.DUMMYFUNCTION("""COMPUTED_VALUE"""),"313149600001") -> 313149600001 | B72: =IFERROR(__xludf.DUMMYFUNCTION("""COMPUTED_VALUE"""),"4250141108493") -> 4250141108493 | C72: =IFERROR(__xludf.DUMMYFUNCTION("""COMPUTED_VALUE"""),"Westfalia/Witter") -> Westfalia/Witter
A73: =IFERROR(__xludf.DUMMYFUNCTION("""COMPUTED_VALUE"""),"313149600001") -> 313149600001 | B73: =IFERROR(__xludf.DUMMYFUNCTION("""COMPUTED_VALUE"""),"4250141108493") -> 4250141108493 | C73: =IFERROR(__xludf.DUMMYFUNCTION("""COMPUTED_VALUE"""),"Westfalia/Witter") -> Westfalia/Witter
A74: =IFERROR(__xludf.DUMMYFUNCTION("""COMPUTED_VALUE"""),"313153600001") -> 313153600001 | B74: =IFERROR(__xludf.DUMMYFUNCTION("""COMPUTED_VALUE"""),"4250141108547") -> 4250141108547 | C74: =IFERROR(__xludf.DUMMYFUNCTION("""COMPUTED_VALUE"""),"Westfalia/Witter") -> Westfalia/Witter
A75: =IFERROR(__xludf.DUMMYFUNCTION("""COMPUTED_VALUE"""),"313161600001") -> 313161600001 | B75: =IFERROR(__xludf.DUMMYFUNCTION("""COMPUTED_VALUE"""),"4250141108608") -> 4250141108608 | C75: =IFERROR(__xludf.DUMMYFUNCTION("""COMPUTED_VALUE"""),"Westfalia/Witter") -> Westfalia/Witter
A76: =IFERROR(__xludf.DUMMYFUNCTION("""COMPUTED_VALUE"""),"313166600001") -> 313166600001 | B76: =IFERROR(__xludf.DUMMYFUNCTION("""COMPUTED_VALUE"""),"4250141108776") -> 4250141108776 | C76: =IFERROR(__xludf.DUMMYFUNCTION("""COMPUTED_VALUE"""),"Westfalia/Witter") -> Westfalia/Witter
A77: =IFERROR(__xludf.DUMMYFUNCTION("""COMPUTED_VALUE"""),"313166600001") -> 313166600001 | B77: =IFERROR(__xludf.DUMMYFUNCTION("""COMPUTED_VALUE"""),"4250141108776") -> 4250141108776 | C77: =IFERROR(__xludf.DUMMYFUNCTION("""COMPUTED_VALUE"""),"Westfalia/Witter") -> Westfalia/Witter
A78: =IFERROR(__xludf.DUMMYFUNCTION("""COMPUTED_VALUE"""),"313167600001") -> 313167600001 | B78: =IFERROR(__xludf.DUMMYFUNCTION("""COMPUTED_VALUE"""),"4250141108806") -> 4250141108806 | C78: =IFERROR(__xludf.DUMMYFUNCTION("""COMPUTED_VALUE"""),"Westfalia/Witter") -> Westfalia/Witter
A79: =IFERROR(__xludf.DUMMYFUNCTION("""COMPUTED_VALUE"""),"313167600001") -> 313167600001 | B79: =IFERROR(__xludf.DUMMYFUNCTION("""COMPUTED_VALUE"""),"4250141108806") -> 4250141108806 | C79: =IFERROR(__xludf.DUMMYFUNCTION("""COMPUTED_VALUE"""),"Westfalia/Witter") -> Westfalia/Witter
A80: =IFERROR(__xludf.DUMMYFUNCTION("""COMPUTED_VALUE"""),"313171600001") -> 313171600001 | B80: =IFERROR(__xludf.DUMMYFUNCTION("""COMPUTED_VALUE"""),"4250141108837") -> 4250141108837 | C80: =IFERROR(__xludf.DUMMYFUNCTION("""COMPUTED_VALUE"""),"Westfalia/Witter") -> Westfalia/Witter
A81: =IFERROR(__xludf.DUMMYFUNCTION("""COMPUTED_VALUE"""),"313171600001") -> 313171600001 | B81: =IFERROR(__xludf.DUMMYFUNCTION("""COMPUTED_VALUE"""),"4250141108837") -> 4250141108837 | C81: =IFERROR(__xludf.DUMMYFUNCTION("""COMPUTED_VALUE"""),"Westfalia/Witter") -> Westfalia/Witter
A82: =IFERROR(__xludf.DUMMYFUNCTION("""COMPUTED_VALUE"""),"313175600001") -> 313175600001 | B82: =IFERROR(__xludf.DUMMYFUNCTION("""COMPUTED_VALUE"""),"4250141108967") -> 4250141108967 | C82: =IFERROR(__xludf.DUMMYFUNCTION("""COMPUTED_VALUE"""),"Westfalia/Witter") -> Westfalia/Witter
A83: =IFERROR(__xludf.DUMMYFUNCTION("""COMPUTED_VALUE"""),"313179600001") -> 313179600001 | B83: =IFERROR(__xludf.DUMMYFUNCTION("""COMPUTED_VALUE"""),"4250141109025") -> 4250141109025 | C83: =IFERROR(__xludf.DUMMYFUNCTION("""COMPUTED_VALUE"""),"Westfalia/Witter") -> Westfalia/Witter
A84: =IFERROR(__xludf.DUMMYFUNCTION("""COMPUTED_VALUE"""),"313185600001") -> 313185600001 | B84: =IFERROR(__xludf.DUMMYFUNCTION("""COMPUTED_VALUE"""),"4250141109070") -> 4250141109070 | C84: =IFERROR(__xludf.DUMMYFUNCTION("""COMPUTED_VALUE"""),"Westfalia/Witter") -> Westfalia/Witter
A85: =IFERROR(__xludf.DUMMYFUNCTION("""COMPUTED_VALUE"""),"313188600001") -> 313188600001 | B85: =IFERROR(__xludf.DUMMYFUNCTION("""COMPUTED_VALUE"""),"4250141109117") -> 4250141109117 | C85: =IFERROR(__xludf.DUMMYFUNCTION("""COMPUTED_VALUE"""),"Westfalia/Witter") -> Westfalia/Witter
A86: =IFERROR(__xludf.DUMMYFUNCTION("""COMPUTED_VALUE"""),"313189600001") -> 313189600001 | B86: =IFERROR(__xludf.DUMMYFUNCTION("""COMPUTED_VALUE"""),"4250141109124") -> 4250141109124 | C86: =IFERROR(__xludf.DUMMYFUNCTION("""COMPUTED_VALUE"""),"Westfalia/Witter") -> Westfalia/Witter
A87: =IFERROR(__xludf.DUMMYFUNCTION("""COMPUTED_VALUE"""),"313194600001") -> 313194600001 | B87: =IFERROR(__xludf.DUMMYFUNCTION("""COMPUTED_VALUE"""),"4250141109148") -> 4250141109148 | C87: =IFERROR(__xludf.DUMMYFUNCTION("""COMPUTED_VALUE"""),"Westfalia/Witter") -> Westfalia/Witter
A88: =IFERROR(__xludf.DUMMYFUNCTION("""COMPUTED_VALUE"""),"313200600001") -> 313200600001 | B88: =IFERROR(__xludf.DUMMYFUNCTION("""COMPUTED_VALUE"""),"4250141109308") -> 4250141109308 | C88: =IFERROR(__xludf.DUMMYFUNCTION("""COMPUTED_VALUE"""),"Westfalia/Witter") -> Westfalia/Witter
A89: =IFERROR(__xludf.DUMMYFUNCTION("""COMPUTED_VALUE"""),"313203600001") -> 313203600001 | B89: =IFERROR(__xludf.DUMMYFUNCTION("""COMPUTED_VALUE"""),"4250141109339") -> 4250141109339 | C89: =IFERROR(__xludf.DUMMYFUNCTION("""COMPUTED_VALUE"""),"Westfalia/Witter") -> Westfalia/Witter
A90: =IFERROR(__xludf.DUMMYFUNCTION("""COMPUTED_VALUE"""),"313204600001") -> 313204600001 | B90: =IFERROR(__xludf.DUMMYFUNCTION("""COMPUTED_VALUE"""),"4250141109346") -> 4250141109346 | C90: =IFERROR(__xludf.DUMMYFUNCTION("""COMPUTED_VALUE"""),"Westfalia/Witter") -> Westfalia/Witter
A91: =IFERROR(__xludf.DUMMYFUNCTION("""COMPUTED_VALUE"""),"313231600001") -> 313231600001 | B91: =IFERROR(__xludf.DUMMYFUNCTION("""COMPUTED_VALUE"""),"4250141109483") -> 4250141109483 | C91: =IFERROR(__xludf.DUMMYFUNCTION("""COMPUTED_VALUE"""),"Westfalia/Witter") -> Westfalia/Witter
A92: =IFERROR(__xludf.DUMMYFUNCTION("""COMPUTED_VALUE"""),"313231600001") -> 313231600001 | B92: =IFERROR(__xludf.DUMMYFUNCTION("""COMPUTED_VALUE"""),"4250141109483") -> 4250141109483 | C92: =IFERROR(__xludf.DUMMYFUNCTION("""COMPUTED_VALUE"""),"Westfalia/Witter") -> Westfalia/Witter
A93: =IFERROR(__xludf.DUMMYFUNCTION("""COMPUTED_VALUE"""),"313240600001") -> 313240600001 | B93: =IFERROR(__xludf.DUMMYFUNCTION("""COMPUTED_VALUE"""),"4250141109605") -> 4250141109605 | C93: =IFERROR(__xludf.DUMMYFUNCTION("""COMPUTED_VALUE"""),"Westfalia/Witter") -> Westfalia/Witter
A94: =IFERROR(__xludf.DUMMYFUNCTION("""COMPUTED_VALUE"""),"314236600001") -> 314236600001 | B94: =IFERROR(__xludf.DUMMYFUNCTION("""COMPUTED_VALUE"""),"4250141110007") -> 4250141110007 | C94: =IFERROR(__xludf.DUMMYFUNCTION("""COMPUTED_VALUE"""),"Westfalia/Witter") -> Westfalia/Witter
A95: =IFERROR(__xludf.DUMMYFUNCTION("""COMPUTED_VALUE"""),"314236600001") -> 314236600001 | B95: =IFERROR(__xludf.DUMMYFUNCTION("""COMPUTED_VALUE"""),"4250141110007") -> 4250141110007 | C95: =IFERROR(__xludf.DUMMYFUNCTION("""COMPUTED_VALUE"""),"Westfalia/Witter") -> Westfalia/Witter
A96: =IFERROR(__xludf.DUMMYFUNCTION("""COMPUTED_VALUE"""),"314257600001") -> 314257600001 | B96: =IFERROR(__xludf.DUMMYFUNCTION("""COMPUTED_VALUE"""),"4250141110267") -> 4250141110267 | C96: =IFERROR(__xludf.DUMMYFUNCTION("""COMPUTED_VALUE"""),"Westfalia/Witter") -> Westfalia/Witter
A97: =IFERROR(__xludf.DUMMYFUNCTION("""COMPUTED_VALUE"""),"314270600001") -> 314270600001 | B97: =IFERROR(__xludf.DUMMYFUNCTION("""COMPUTED_VALUE"""),"4250141110465") -> 4250141110465 | C97: =IFERROR(__xludf.DUMMYFUNCTION("""COMPUTED_VALUE"""),"Westfalia/Witter") -> Westfalia/Witter
A98: =IFERROR(__xludf.DUMMYFUNCTION("""COMPUTED_VALUE"""),"314275600001") -> 314275600001 | B98: =IFERROR(__xludf.DUMMYFUNCTION("""COMPUTED_VALUE"""),"4250141110496") -> 4250141110496 | C98: =IFERROR(__xludf.DUMMYFUNCTION("""COMPUTED_VALUE"""),"Westfalia/Witter") -> Westfalia/Witter
A99: =IFERROR(__xludf.DUMMYFUNCTION("""COMPUTED_VALUE"""),"314280600001") -> 314280600001 | B99: =IFERROR(__xludf.DUMMYFUNCTION("""COMPUTED_VALUE"""),"4250141110601") -> 4250141110601 | C99: =IFERROR(__xludf.DUMMYFUNCTION("""COMPUTED_VALUE"""),"Westfalia/Witter") -> Westfalia/Witter
A100: =IFERROR(__xludf.DUMMYFUNCTION("""COMPUTED_VALUE"""),"314282600001") -> 314282600001 | B100: =IFERROR(__xludf.DUMMYFUNCTION("""COMPUTED_VALUE"""),"4250141110632") -> 4250141110632 | C100: =IFERROR(__xludf.DUMMYFUNCTION("""COMPUTED_VALUE"""),"Westfalia/Witter") -> Westfalia/Witter
...

Sheet OBS Bilmodeller
A1: Hyundai | B1: Modell | C1: Årsmodell | D1: OBS | E1: Ev lösning
A2: Volvo | B2: V70 | C2: alla | D2: Bromsljus sitter i bakluckan. Se till att luckan är stängd eller låset låst när man mäter fram signal för canbusanpassade elsatser.
A3: Volvo | B3: V60 | C3: alla | D3: Bromsljus sitter i bakluckan. Se till att luckan är stängd eller låset låst när man mäter fram signal för canbusanpassade elsatser.
A4: Audi | B4: Q5 | C4: Alla | D4: Bromsljus sitter i bakluckan. Se till att luckan är stängd eller låset låst när man mäter fram signal för canbusanpassade elsatser.
A5: Audi | B5: Q3 | C5: Alla | D5: Bromsljus sitter i bakluckan. Se till att luckan är stängd eller låset låst när man mäter fram signal för canbusanpassade elsatser.
A6: Peugeot | B6: 508 kombi | C6: 11> | D6: GT-Line??? Man kan misstänka det på motorbeteckningen 2.2 HDI | E6: Bosal krok finns till denna. Avtagbar
A7: Hyundai | B7: i30 | D7: Backsensorer? Kör på avtagbar.
A8: Suzuki | B8: Swift
A9: Mitusubishi | B9: Outlander | C9: 07>12 | D9: Bagagelucke-problemet. Dessa bilarna har oftast tvådelad lucka bak. Den undre luckan fälls ner och lägger sig på kulan. Så denna bilen måste ha ett avtagbart drag.

Sheet Reklamationer
A1: Datum | B1: Inlagd av | C1: Namn | D1: Datum Beställt/Monterat | E1: Reg nr | F1: Bilmodell | G1: Orsak Reklamation | H1: Montering var? | I1: Åtgärd | J1: Klar? | K1: 1 | L1: 2 | M1: 3 | N1: 4 | O1: 5 | P1: 6 | Q1: 7 | R1: 8 | S1: 9
A2: 42419 | C2: Helen Tainio | D2: 42389 | E2: KGU944 | F2: KIA Carens | G2: PDC fungerar ej | I2: Laga PDC | J2: Ja | K2: massa grejer | L2: massa grejer | M2: massa grejer | N2: Ingen ström alls till släpet helt plötsligt. Dem vill komma till Örebro och ta bort allt. Sagt till dem att kolla hängsäkringen, då borde allt komma igång. Pratat med Therese 3/6, 0733-647677 | O2: Pratat med Willy 8/6. Han var ganska lugn men inte helt överrens om ingen kompensation. Förslagsvis ger vi 500 kr i kompensation för körningen, så lugnar dem ner sig. Han hade inte hittat hängsäkringen i helgen, bad honom att leta fram denna. Måste vara säkringen som är trasig. | P2: Pratat lugnt och sansat med Willy. Han betalar in orignalfakturan. Ta tillbaka inkassot. Skicka en bagagerumsmatta till honom som kompensation. Eventuellt är det glapp in i boxen, han tror att han löst det själv. Men återkommer det i framtiden så får han slå oss en signal. //TC 22/12 | Q2: Satt inkassot på hold till mitten av Januari. Preventia ska säga till kund att han måste betala in innan årsskiftet. //TC 22/12
A3: 42458 | B3: TC | C3: Stefan Dantanus | D3: 42458 | E3: AKA921 | F3: OPEL Insignia | G3: Lång lista, se mail | H3: Femmans | I3: Se lista | J3: Ja | K3: Åtgärdslista skickad till kund och verkstad | L3: Fuad tagit hem plastdel | M3: Kund ska höra av sig när han har tid att komma till verkstaden | N3: 3/6: Inbokad hos Femmans 17/6 kl 10. Mailat Fuad och lagt in i kalendern. Åtgärdslista finns på mailen. | O3: Ingen verkstad som kommer ihåg hur dem gjorde med styrsignalerna till bakluckan tyvärr... Kollat med dem som monterat på liknande bil. //TC
